Workbook

Sheet CONSOLIDADO 5 AÑOS
A1: CUERPO DE BOMBEROS VOLUNTARIOS, LA UNIÓN, VALLE DEL CAUCA INFORME DE ACTIVIDADES DESDE EL AÑO 2021 HASTA EL 2025
A2: EMERGENCIAS | B2: CANTIDAD | C2: % INCIDENCIA
A3: CAÍDA / CORTES DE ARBOL | B3: =COUNTIF('2021'!B:B,'CONSOLIDADO 5 AÑOS'!A3) + COUNTIF('2022'!B:B,'CONSOLIDADO 5 AÑOS'!A3) + COUNTIF('2023'!B:B,'CONSOLIDADO 5 AÑOS'!A3) + COUNTIF('2024'!B:B,'CONSOLIDADO 5 AÑOS'!A3) + COUNTIF('2025'!B:B,'CONSOLIDADO 5 AÑOS'!A3) -> 103 | C3: =B3/$B$26 -> 0.056937535
A4: CONTROL DE ABEJAS | B4: =COUNTIF('2021'!B:B,'CONSOLIDADO 5 AÑOS'!A4) + COUNTIF('2022'!B:B,'CONSOLIDADO 5 AÑOS'!A4) + COUNTIF('2023'!B:B,'CONSOLIDADO 5 AÑOS'!A4) + COUNTIF('2024'!B:B,'CONSOLIDADO 5 AÑOS'!A4) + COUNTIF('2025'!B:B,'CONSOLIDADO 5 AÑOS'!A4) -> 205 | C4: =B4/$B$26 -> 0.11332228
A5: CONTROL DE AVISPAS | B5: =COUNTIF('2021'!B:B,'CONSOLIDADO 5 AÑOS'!A5) + COUNTIF('2022'!B:B,'CONSOLIDADO 5 AÑOS'!A5) + COUNTIF('2023'!B:B,'CONSOLIDADO 5 AÑOS'!A5) + COUNTIF('2024'!B:B,'CONSOLIDADO 5 AÑOS'!A5) + COUNTIF('2025'!B:B,'CONSOLIDADO 5 AÑOS'!A5) -> 20 | C5: =B5/$B$26 -> 0.011055832
A6: CAÍDA DE CUERDAS | B6: =COUNTIF('2021'!B:B,'CONSOLIDADO 5 AÑOS'!A6) + COUNTIF('2022'!B:B,'CONSOLIDADO 5 AÑOS'!A6) + COUNTIF('2023'!B:B,'CONSOLIDADO 5 AÑOS'!A6) + COUNTIF('2024'!B:B,'CONSOLIDADO 5 AÑOS'!A6) + COUNTIF('2025'!B:B,'CONSOLIDADO 5 AÑOS'!A6) -> 17 | C6: =B6/$B$26 -> 0.0093974572
A7: CORTO CIRCUITO | B7: =COUNTIF('2021'!B:B,'CONSOLIDADO 5 AÑOS'!A7) + COUNTIF('2022'!B:B,'CONSOLIDADO 5 AÑOS'!A7) + COUNTIF('2023'!B:B,'CONSOLIDADO 5 AÑOS'!A7) + COUNTIF('2024'!B:B,'CONSOLIDADO 5 AÑOS'!A7) + COUNTIF('2025'!B:B,'CONSOLIDADO 5 AÑOS'!A7) -> 41 | C7: =B7/$B$26 -> 0.022664456
A8: COLAPSO DE ESTRUCTURAS | B8: =COUNTIF('2021'!B:B,'CONSOLIDADO 5 AÑOS'!A8) + COUNTIF('2022'!B:B,'CONSOLIDADO 5 AÑOS'!A8) + COUNTIF('2023'!B:B,'CONSOLIDADO 5 AÑOS'!A8) + COUNTIF('2024'!B:B,'CONSOLIDADO 5 AÑOS'!A8) + COUNTIF('2025'!B:B,'CONSOLIDADO 5 AÑOS'!A8) -> 5 | C8: =B8/$B$26 -> 0.002763958
A9: CAPACITACIONES | B9: =COUNTIF('2021'!B:B,'CONSOLIDADO 5 AÑOS'!A9) + COUNTIF('2022'!B:B,'CONSOLIDADO 5 AÑOS'!A9) + COUNTIF('2023'!B:B,'CONSOLIDADO 5 AÑOS'!A9) + COUNTIF('2024'!B:B,'CONSOLIDADO 5 AÑOS'!A9) + COUNTIF('2025'!B:B,'CONSOLIDADO 5 AÑOS'!A9) -> 11 | C9: =B9/$B$26 -> 0.0060807076
A10: EXTRICACIÓN VEHICULAR | B10: =COUNTIF('2021'!B:B,'CONSOLIDADO 5 AÑOS'!A10) + COUNTIF('2022'!B:B,'CONSOLIDADO 5 AÑOS'!A10) + COUNTIF('2023'!B:B,'CONSOLIDADO 5 AÑOS'!A10) + COUNTIF('2024'!B:B,'CONSOLIDADO 5 AÑOS'!A10) + COUNTIF('2025'!B:B,'CONSOLIDADO 5 AÑOS'!A10) -> 13 | C10: =B10/$B$26 -> 0.0071862908
A11: FUGA DE GAS NATURAL | B11: =COUNTIF('2021'!B:B,'CONSOLIDADO 5 AÑOS'!A11) + COUNTIF('2022'!B:B,'CONSOLIDADO 5 AÑOS'!A11) + COUNTIF('2023'!B:B,'CONSOLIDADO 5 AÑOS'!A11) + COUNTIF('2024'!B:B,'CONSOLIDADO 5 AÑOS'!A11) + COUNTIF('2025'!B:B,'CONSOLIDADO 5 AÑOS'!A11) -> 79 | C11: =B11/$B$26 -> 0.043670536
A12: FUGA DE GAS GLP | B12: =COUNTIF('2021'!B:B,'CONSOLIDADO 5 AÑOS'!A12) + COUNTIF('2022'!B:B,'CONSOLIDADO 5 AÑOS'!A12) + COUNTIF('2023'!B:B,'CONSOLIDADO 5 AÑOS'!A12) + COUNTIF('2024'!B:B,'CONSOLIDADO 5 AÑOS'!A12) + COUNTIF('2025'!B:B,'CONSOLIDADO 5 AÑOS'!A12) -> 6 | C12: =B12/$B$26 -> 0.0033167496
A13: INCENDIO FORESTAL | B13: =COUNTIF('2021'!B:B,'CONSOLIDADO 5 AÑOS'!A13) + COUNTIF('2022'!B:B,'CONSOLIDADO 5 AÑOS'!A13) + COUNTIF('2023'!B:B,'CONSOLIDADO 5 AÑOS'!A13) + COUNTIF('2024'!B:B,'CONSOLIDADO 5 AÑOS'!A13) + COUNTIF('2025'!B:B,'CONSOLIDADO 5 AÑOS'!A13) -> 182 | C13: =B13/$B$26 -> 0.10060807
A14: INCENDIO ESTRUCTURAL | B14: =COUNTIF('2021'!B:B,'CONSOLIDADO 5 AÑOS'!A14) + COUNTIF('2022'!B:B,'CONSOLIDADO 5 AÑOS'!A14) + COUNTIF('2023'!B:B,'CONSOLIDADO 5 AÑOS'!A14) + COUNTIF('2024'!B:B,'CONSOLIDADO 5 AÑOS'!A14) + COUNTIF('2025'!B:B,'CONSOLIDADO 5 AÑOS'!A14) -> 46 | C14: =B14/$B$26 -> 0.025428413
... A25: VISITAS DE SEGURIDAD | B25: =COUNTIF('2021'!B:B,'CONSOLIDADO 5 AÑOS'!A25) + COUNTIF('2022'!B:B,'CONSOLIDADO 5 AÑOS'!A25) + COUNTIF('2023'!B:B,'CONSOLIDADO 5 AÑOS'!A25) + COUNTIF('2024'!B:B,'CONSOLIDADO 5 AÑOS'!A25) + COUNTIF('2025'!B:B,'CONSOLIDADO 5 AÑOS'!A25) -> 415 | C25: =B25/$B$26 -> 0.22940851
A26: TOTAL | B26: =SUM(B3:B25) -> 1809 | C26: =B26/$B$26 -> 1
D43: CANTIDAD DE EMERGENCIAS Y ACTIVIDADES ANUALES
D44: 2021 | E44: 2022 | F44: 2023 | G44: 2024 | H44: 2025 | I44: TOTAL | J44: PROM. X AÑO
D45: ='2021'!B331 -> 316 | E45: ='2022'!B485 -> 470 | F45: ='2023'!B404 -> 389 | G45: ='2024'!B413 -> 398 | H45: ='2025'!B251 -> 236 | I45: =SUM(D45:H45) -> 1809 | J45: =AVERAGE(D45:H45) -> 361.8

Sheet CONSOLIDADO AÑO 2026
A1: CUERPO DE BOMBEROS VOLUNTARIOS, LA UNIÓN, VALLE DEL CAUCA INFORME DE ACTIVIDADES EN LO CORRIDO DEL AÑO 2026
A2: EMERGENCIAS | B2: CANTIDAD | C2: % INCIDENCIA
A3: CAÍDA / CORTES DE ARBOL | B3: =COUNTIF('2026'!$B:$B, 'CONSOLIDADO AÑO 2026'!$A$3:$A$25) -> 24 | C3: =B3/$B$26 -> 0.043875686
A4: CONTROL DE ABEJAS | B4: =COUNTIF('2026'!$B:$B, 'CONSOLIDADO AÑO 2026'!$A$3:$A$25) -> 25 | C4: =B4/$B$26 -> 0.045703839
A5: CONTROL DE AVISPAS | B5: =COUNTIF('2026'!$B:$B, 'CONSOLIDADO AÑO 2026'!$A$3:$A$25) -> 6 | C5: =B5/$B$26 -> 0.010968921
A6: CAÍDA DE CUERDAS | B6: =COUNTIF('2026'!$B:$B, 'CONSOLIDADO AÑO 2026'!$A$3:$A$25) -> 4 | C6: =B6/$B$26 -> 0.0073126143
A7: CORTO CIRCUITO | B7: =COUNTIF('2026'!$B:$B, 'CONSOLIDADO AÑO 2026'!$A$3:$A$25) -> 8 | C7: =B7/$B$26 -> 0.014625229
A8: COLAPSO DE ESTRUCTURAS | B8: =COUNTIF('2026'!$B:$B, 'CONSOLIDADO AÑO 2026'!$A$3:$A$25) -> 3 | C8: =B8/$B$26 -> 0.0054844607
A9: CAPACITACIONES | B9: =COUNTIF('2026'!$B:$B, 'CONSOLIDADO AÑO 2026'!$A$3:$A$25) -> 0 | C9: =B9/$B$26 -> 0
A10: EXTRICACIÓN VEHICULAR | B10: =COUNTIF('2026'!$B:$B, 'CONSOLIDADO AÑO 2026'!$A$3:$A$25) -> 0 | C10: =B10/$B$26 -> 0
A11: FUGA DE GAS NATURAL | B11: =COUNTIF('2026'!$B:$B, 'CONSOLIDADO AÑO 2026'!$A$3:$A$25) -> 23 | C11: =B11/$B$26 -> 0.042047532
A12: FUGA DE GAS GLP | B12: =COUNTIF('2026'!$B:$B, 'CONSOLIDADO AÑO 2026'!$A$3:$A$25) -> 1 | C12: =B12/$B$26 -> 0.0018281536
A13: INCENDIO FORESTAL | B13: =COUNTIF('2026'!$B:$B, 'CONSOLIDADO AÑO 2026'!$A$3:$A$25) -> 42 | C13: =B13/$B$26 -> 0.07678245
A14: INCENDIO ESTRUCTURAL | B14: =COUNTIF('2026'!$B:$B, 'CONSOLIDADO AÑO 2026'!$A$3:$A$25) -> 13 | C14: =B14/$B$26 -> 0.023765996
... A25: VISITAS DE SEGURIDAD | B25: =COUNTIF('2026'!$B:$B, 'CONSOLIDADO AÑO 2026'!$A$3:$A$25) -> 5 | C25: =B25/$B$26 -> 0.0091407678
A26: TOTAL | B26: =SUM(B3:B25) -> 547 | C26: =B26/$B$26 -> 1

Sheet DETALLADO X MES 2026
A1: CUERPO DE BOMBEROS VOLUNTARIOS - LA UNIÓN VALLE | Z1: ="TOTAL DE EMERGENCIAS POR MES DE "&J2&" (2021-2025)" -> TOTAL DE EMERGENCIAS POR MES DE INCENDIO FORESTAL (2021-2025) | AA1: ="VARIACIÓN ANUAL DE "&J2&" (2021-2025)" -> VARIACIÓN ANUAL DE INCENDIO FORESTAL (2021-2025) | AB1: ="TOTAL DE "&J2&" POR AÑO (2021-2025)" -> TOTAL DE INCENDIO FORESTAL POR AÑO (2021-2025) | AC1: BUSCAR | AD1: CAÍDA / CORTES DE ARBOL | AE1: CONTROL DE ABEJAS | AF1: CONTROL DE AVISPAS | AG1: CAÍDA DE CUERDAS | AH1: CORTO CIRCUITO | AI1: COLAPSO DE ESTRUCTURAS | AJ1: CAPACITACIONES | AK1: EXTRICACIÓN VEHICULAR | AL1: FUGA DE GAS NATURAL | AM1: FUGA DE GAS GLP | AN1: INCENDIO FORESTAL | AO1: INCENDIO ESTRUCTURAL | AP1: INCENDIO VEHICULAR | AQ1: INUNDACIÓN | AR1: LABORES DE PREVENCION O ACOMPAÑAMIENTO EN GESTION DEL RIESGO | AS1: MATERIALES PELIGROSOS / DERRAMES | AT1: PRIMEROS AUXILIOS | AU1: RESCATE DE PERSONA / PARAPENTE | AV1: RESCATE DE ANIMAL | AW1: REUNIÓN EN LA ALCALDÍA | AX1: REUNIONES DE SERVICIO SOCIAL | AY1: SUMINISTROS DE AGUA | AZ1: VISITAS DE SEGURIDAD
A2: CONSOLIDAD ESTADÍSTICO DE: | J2: INCENDIO FORESTAL | Z2: ="TOTAL DE EMERGENCIAS POR MES DE "&A87&" HASTA ABRIL (2021-2026)" -> TOTAL DE EMERGENCIAS POR MES DE INCENDIO FORESTAL HASTA ABRIL (2021-2026) | AA2: ="VARIACIÓN ANUAL DE "&A87&" HASTA ENERO (2021-2026)" -> VARIACIÓN ANUAL DE INCENDIO FORESTAL HASTA ENERO (2021-2026) | AB2: ="TOTAL ANUAL DE "&A87&" HASTA ENERO (2021-2026)" -> TOTAL ANUAL DE INCENDIO FORESTAL HASTA ENERO (2021-2026)
A3: AÑO | B3: VARIACIÓN MENSUAL DEL TOTAL DE EMERGENCIAS POR AÑO | N3: TOTAL | O3: % INCIDENCIA | P3: PROM. X MES | Q3: PROM. X AÑO | R3: VARIACION % ANUAL
B4: ENERO | C4: FEBRERO | D4: MARZO | E4: ABRIL | F4: MAYO | G4: JUNIO | H4: JULIO | I4: AGOSTO | J4: SEPTIEMBRE | K4: OCTUBRE | L4: NOVIEMBRE | M4: DICIEMBRE
A5: 2021 | B5: =SUM('2021'!C4:C27) -> 4 | C5: =SUM('2021'!C29:C65) -> 4 | D5: =SUM('2021'!C67:C95) -> 0 | E5: =SUM('2021'!C97:C114) -> 0 | F5: =SUM('2021'!C116:C138) -> 1 | G5: =SUM('2021'!C140:C158) -> 1 | H5: =SUM('2021'!C160:C190) -> 2 | I5: =SUM('2021'!C192:C236) -> 0 | J5: =SUM('2021'!C238:C267) -> 0 | K5: =SUM('2021'!C269:C294) -> 0 | L5: =SUM('2021'!C296:C319) -> 0 | M5: =SUM('2021'!C321:C330) -> 0 | N5: =SUM(B5:M5) -> 12 | O5: =N5/$N$11 -> 0.065934066 | P5: =AVERAGE(B5:M5) -> 1 | Q5: =AVERAGE(N5:N9) -> 36.4 | R5: 0
A6: 2022 | B6: =SUM('2022'!C4:C22) -> 3 | C6: =SUM('2022'!C24:C54) -> 3 | D6: =SUM('2022'!C56:C87) -> 1 | E6: =SUM('2022'!C89:C128) -> 0 | F6: =SUM('2022'!C130:C167) -> 2 | G6: =SUM('2022'!C169:C210) -> 0 | H6: =SUM('2022'!C212:C270) -> 1 | I6: =SUM('2022'!C272:C324) -> 3 | J6: =SUM('2022'!C326:C364) -> 1 | K6: =SUM('2022'!C366:C408) -> 2 | L6: =SUM('2022'!C410:C452) -> 2 | M6: =SUM('2022'!C454:C484) -> 4 | N6: =SUM(B6:M6) -> 22 | O6: =N6/$N$11 -> 0.12087912 | P6: =AVERAGE(B6:M6) -> 1.8333333 | R6: =IF(N5=0,IF(N6=0,"0%","100%"),(N6-N5)/N5) -> 0.83333333
A7: 2023 | B7: =SUM('2023'!C4:C38) -> 6 | C7: =SUM('2023'!C40:C99) -> 4 | D7: =SUM('2023'!C101:C133) -> 1 | E7: =SUM('2023'!C135:C177) -> 1 | F7: =SUM('2023'!C179:C202) -> 1 | G7: =SUM('2023'!C204:C225) -> 6 | H7: =SUM('2023'!C227:C255) -> 8 | I7: =SUM('2023'!C257:C274) -> 8 | J7: =SUM('2023'!C285:C328) -> 14 | K7: =SUM('2023'!C330:C349) -> 1 | L7: =SUM('2023'!C351:C381) -> 3 | M7: =SUM('2023'!C383:C403) -> 9 | N7: =SUM(B7:M7) -> 62 | O7: =N7/$N$11 -> 0.34065934 | P7: =AVERAGE(B7:M7) -> 5.1666667 | R7: =IF(N6=0,IF(N7=0,"0%","100%"),(N7-N6)/N6) -> 1.8181818
A8: 2024 | B8: =SUM('2024'!C4:C12) -> 15 | C8: =SUM('2024'!C51:C105) -> 6 | D8: =SUM('2024'!C107:C166) -> 11 | E8: =SUM('2024'!C168:C207) -> 3 | F8: =SUM('2024'!C209:C212) -> 0 | G8: =SUM('2024'!C239:C263) -> 0 | H8: =SUM('2024'!C265:C290) -> 2 | I8: =SUM('2024'!C292:C324) -> 7 | J8: =SUM('2024'!C326:C342) -> 4 | K8: =SUM('2024'!C344:C370) -> 0 | L8: =SUM('2024'!C372:C390) -> 1 | M8: =SUM('2024'!C392:C412) -> 6 | N8: =SUM(B8:M8) -> 55 | O8: =N8/$N$11 -> 0.3021978 | P8: =AVERAGE(B8:M8) -> 4.5833333 | R8: =IF(N7=0,IF(N8=0,"0%","100%"),(N8-N7)/N7) -> -0.11290323
A9: 2025 | B9: =SUM('2025'!C4:C32) -> 7 | C9: =SUM('2025'!C34:C55) -> 0 | D9: =SUM('2025'!C57:C75) -> 1 | E9: =SUM('2025'!C77:C103) -> 2 | F9: =SUM('2025'!C105:C127) -> 1 | G9: =SUM('2025'!C129:C142) -> 0 | H9: =SUM('2025'!C144:C169) -> 5 | I9: =SUM('2025'!C171:C182) -> 6 | J9: =SUM('2025'!C184:C204) -> 5 | K9: =SUM('2025'!C206:C223) -> 1 | L9: =SUM('2025'!C225:C238) -> 0 | M9: =SUM('2025'!C240:C250) -> 3 | N9: =SUM(B9:M9) -> 31 | O9: =N9/$N$11 -> 0.17032967 | P9: =AVERAGE(B9:M9) -> 2.5833333 | R9: =IF(N8=0,IF(N9=0,"0%","100%"),(N9-N8)/N8) -> -0.43636364
A10: 2026 | B10: =SUM('2026'!C4:C18) -> 2 | C10: =SUM('2026'!C20:C53) -> 3 | D10: =SUM('2026'!C55:C78) -> 8 | E10: =SUM('2026'!C80:C101) -> 2 | F10: =SUM('2026'!C103:C127) -> 1 | G10: =SUM('2026'!C129:C151) -> 2 | H10: =SUM('2026'!C153:C171) -> 8 | I10: =SUM('2026'!C173:C527) -> 7
A11: GRAN TOTAL POR AÑOS | N11: =SUM(N5:N9) -> 182 | O11: =SUM(O5:O9) -> 1
A86: CUERPO DE BOMBEROS VOLUNTARIOS - LA UNIÓN VALLE ANÁLISIS COMPARATIVO DE EMERGENCIAS ACUMULADAS EN LO CORRIDO DEL AÑO FRENTE A AÑOS ANTERIORES
A87: =J2 -> INCENDIO FORESTAL
A88: AÑO | B88: ENERO | C88: FEBRERO | D88: MARZO | E88: ABRIL | F88: MAYO | G88: JUNIO | H88: JULIO | I88: AGOSTO | J88: SEPTIEMBRE | K88: OCTUBRE | L88: NOVIEMBRE | M88: DICIEMBRE | N88: TOTAL | O88: % INCIDENCIA | P88: PROM. X MES | Q88: PROM. X AÑO | R88: VARIACION % ANUAL
A89: 2021 | B89: =B5 -> 4 | C89: =C5 -> 4 | D89: =D5 -> 0 | E89: =E5 -> 0 | F89: =F5 -> 1 | G89: =G5 -> 1 | H89: =H5 -> 2 | I89: =I5 -> 0 | N89: =SUM(B89:M89) -> 12 | O89: =N89/$N$95 -> 0.075471698 | P89: =AVERAGE(B89:M89) -> 1.5 | Q89: =AVERAGE(N89:N94) -> 26.5 | R89: 0
A90: 2022 | B90: =B6 -> 3 | C90: =C6 -> 3 | D90: =D6 -> 1 | E90: =E6 -> 0 | F90: =F6 -> 2 | G90: =G6 -> 0 | H90: =H6 -> 1 | I90: =I6 -> 3 | N90: =SUM(B90:M90) -> 13 | O90: =N90/$N$95 -> 0.081761006 | P90: =AVERAGE(B90:M90) -> 1.625 | R90: =IF(N89=0,IF(N90=0,"0%","100%"),(N90-N89)/N89) -> 0.083333333
A91: 2023 | B91: =B7 -> 6 | C91: =C7 -> 4 | D91: =D7 -> 1 | E91: =E7 -> 1 | F91: =F7 -> 1 | G91: =G7 -> 6 | H91: =H7 -> 8 | I91: =I7 -> 8 | N91: =SUM(B91:M91) -> 35 | O91: =N91/$N$95 -> 0.22012579 | P91: =AVERAGE(B91:M91) -> 4.375 | R91: =IF(N90=0,IF(N91=0,"0%","100%"),(N91-N90)/N90) -> 1.6923077
A92: 2024 | B92: =B8 -> 15 | C92: =C8 -> 6 | D92: =D8 -> 11 | E92: =E8 -> 3 | F92: =F8 -> 0 | G92: =G8 -> 0 | H92: =H8 -> 2 | I92: =I8 -> 7 | N92: =SUM(B92:M92) -> 44 | O92: =N92/$N$95 -> 0.27672956 | P92: =AVERAGE(B92:M92) -> 5.5 | R92: =IF(N91=0,IF(N92=0,"0%","100%"),(N92-N91)/N91) -> 0.25714286
A93: 2025 | B93: =B9 -> 7 | C93: =C9 -> 0 | D93: =D9 -> 1 | E93: =E9 -> 2 | F93: =F9 -> 1 | G93: =G9 -> 0 | H93: =H9 -> 5 | I93: =I9 -> 6 | N93: =SUM(B93:M93) -> 22 | O93: =N93/$N$95 -> 0.13836478 | P93: =AVERAGE(B93:M93) -> 2.75 | R93: =IF(N92=0,IF(N93=0,"0%","100%"),(N93-N92)/N92) -> -0.5
A94: 2026 | B94: =B10 -> 2 | C94: =C10 -> 3 | D94: =D10 -> 8 | E94: =E10 -> 2 | F94: =F10 -> 1 | G94: =G10 -> 2 | H94: =H10 -> 8 | I94: =I10 -> 7 | N94: =SUM(B94:M94) -> 33 | O94: =N94/$N$95 -> 0.20754717 | P94: =AVERAGE(B94:M94) -> 4.125 | R94: =IF(N93=0,IF(N94=0,"0%","100%"),(N94-N93)/N93) -> 0.5
A95: GRAN TOTAL POR AÑOS | N95: =SUM(N89:N94) -> 159 | O95: =SUM(O89:O94) -> 1

Sheet 2026
A1: TIPO DE INCIDENTE | B1: INCIDENTES Y ACTIVIDADES | C1: CANTIDAD DE | D1: DÍA DEL EVENTO | E1: DURACIÓN DEL EVENTO | F1: DIRECCIÓN O LUGAR DE REFERENCIA | G1: BARRIO CORREGIMIENTO O VEREDA | H1: DESCRIPCIÓN DEL EVENTO | I1: AREA AFECTADA (SOLO SI APLICA) | J1: N° DE UNIDADES QUE ASISTIERON | K1: VEHÍCULO | L1: COORDENADAS
C2: ='DETALLADO X MES 2026'!J2 -> INCENDIO FORESTAL
A3: ENERO
A4: INCENDIOS | B4: INCENDIO FORESTAL | C4: =COUNTIF(B4:B18,C2) -> 2 | D4: 46024 | E4: 1 HORA Y MEDIA | F4: VIA LAS CINTAS | H4: INFORMAN DE HUMO EN LA MONTAÑA | I4: 200 MTR | J4: 9 | K4: B-4, L-1, L-2
A5: OTROS | B5: CAÍDA / CORTES DE ARBOL | D5: 46028 | E5: 4.10 HORAS | F5: LA BASCULA DE CERVALLE | G5: CORCEGA | H5: ARBOL QUE CAE TAPONANDO PARTE DE LA VIA Y AFECTANDO UNA VIVIENDA | I5: 100 M/2 | J5: 3 | K5: L-1
A6: OTROS | B6: CONTROL DE AVISPAS | D6: 46029 | E6: 1 HORA | F6: CALLE 20 CRA 17 | G6: LA CRUZ | H6: RECUPERACION Y LIBERACION DE ENJAMBRE DE AVISPAS QUE ESTAN DENTRO DE UNA VIVIENDA | I6: 10 MT/2 | J6: 3 | K6: L-2
A7: INCENDIOS | B7: INCENDIO ESTRUCTURAL | D7: 46030 | E7: 12 MNTOS | F7: CALLE 13 CRA 8 | G7: LAS LAJAS | H7: POSIBLE INCENDIO ESTRUCTURAL,RESULTANDO SER UN SARTEN QUE SE ESTABA QUEMANDO | I7: 10 MT/2 | J7: 3 | K7: B-4
A8: RESCATES | B8: RESCATE DE PERSONA / PARAPENTE | D8: 46035 | E8: 1 HORA | F8: MANZANA B CASA 6 | G8: LA ANDINA | H8: INFORMAN DE UN MENOR ATRAPADO EN UN BAÑO, POR UN CAJON QUE CAE Y BLOQUEA LA PUERTA | I8: . | J8: 4 | K8: B-3
A9: INCENDIOS | B9: INCENDIO ESTRUCTURAL | D9: 46038 | E9: 2 HORAS | F9: CARRERA 15 CON CALLE 15 | G9: CENTRO | H9: INCENDIO EN UN LOCAL DEL CENTRO | I9: . | J9: 8 | K9: B-2, B-4
A10: RESCATES | B10: RESCATE DE PERSONA / PARAPENTE | D10: 46042 | E10: 2 HORAS | F10: ZONA DEL AJISAL | G10: EL AJISAL | H10: RESCATE DE PILOTO DE PARAPENTE QUE CAE EN LA ZONA ALTA DEL AJISAL, PILOTO SALE POR SUS PROPIOS MEDIOS | I10: * | J10: 8 | K10: L-1, L-2
A11: FALSA ALARMA | B11: INCENDIO FORESTAL | D11: 46043 | E11: 27 MNTOS | F11: VIA LAS CINTAS | G11: LAS CINTAS | H11: QUEMA VEGETAL CONTROLADA | I11: * | J11: 6 | K11: B-2, L-2
A12: RESCATES | B12: RESCATE DE PERSONA / PARAPENTE | D12: 23/12/0026 | E12: 2.30 HORAS | F12: CERRO DE SANTA ELENA | G12: SANTA ELENA | H12: PILOTOS DE PARAPENTES QUE SE ENREDAN EN VUELO Y SUFREN CAIDA SALIENDO ILESOS | I12: * | J12: 10 | K12: B-3, L-2
A13: OTROS | B13: CONTROL DE ABEJAS | D13: 23/12/0026 | E13: 40 MNTOS | F13: VIA A SAN LUIS | G13: SAN LUIS | H13: NO SE ENCONTRO LA DIRECCION | I13: * | J13: 2 | K13: L-2
A14: MATERIALES PELIGROSOS | B14: FUGA DE GAS NATURAL | D14: 46048 | E14: 54 MNTOS | F14: CRA 15 #7a 36 | G14: LA CIUDADELA BAJA | H14: FUERTE OLOR A GAS ,SIN ENCONTRAR CAUSAS | I14: 45MT/2 | J14: 2 | K14: L-1
A15: INCENDIOS | B15: INCENDIO ESTRUCTURAL | D15: 46050 | E15: 2.33 HORAS | F15: TRANS 17 CRA 17 | G15: SAN PEDRO | H15: INCENDIO ESTRUCTURAL EN VIVIENDA UTILIADA PARA ALMACENAR PRODUCTOS DE RECICLAJE | I15: * | J15: 11 | K15: B-2, B-4, L-2, OTROS
A16: MATERIALES PELIGROSOS | B16: FUGA DE GAS NATURAL | D16: 46050 | E16: 43 MNTOS | F16: CRA 18 #14 19 | G16: popular | H16: FUGA DE GAS EN VIVIENDA | I16: * | J16: 6 | K16: B-4
A17: RESCATES | B17: RESCATE DE ANIMAL | D17: 46052 | E17: 1 HORA | F17: CALLE 8 # 9 - 120 | G17: LAS PALMAS | H17: GATO QUE QUEDA ATRAPADO EN UN TECHO | I17: . | J17: 4 | K17: B-3
A18: RESCATES | B18: RESCATE DE PERSONA / PARAPENTE | D18: 46052 | E18: 2 HORAS | F18: VOLADERO DE LA AGUADA | G18: LA AGUADA | H18: PILOTO DE PARAPENTE QUE CAE EN EL SECTOR DEL VOLADERO DE LA AGUADA,SE REQUIERE TRASLADO EN AMBULANCIA | I18: * | J18: 5 | K18: L-2
A19: FEBRERO
A20: OTROS | B20: CONTROL DE ABEJAS | C20: =COUNTIF(B20:B53,C2) -> 3 | D20: 46056 | E20: 30 MINUTOS | F20: COLEGIO ITDG | G20: EL AMPARO | H20: ABEJAS AL PARECER PASAGERAS | I20: N/A | J20: 2 | K20: L-2
A21: MATERIALES PELIGROSOS | B21: FUGA DE GAS GLP | D21: 46056 | E21: 30 MINUTOS | F21: CR 15 7A-36 | G21: LA CIUDADELA | H21: CILINDRO DE GAS QUE PRESENTA FUGA, SE TRAJO PARA LA PARTE DE LA ESCUELA | I21: N/A | J21: 1 | K21: L-2
A22: RESCATES | B22: RESCATE DE ANIMAL | D22: 46057 | E22: 1 HORA 30 MINUTOS | F22: TRASVERSAL 17 | H22: RESCATE DE UN FELINO EN UN ALJIBER | I22: N/A | J22: 6 | K22: B-3
A23: INCENDIOS | B23: INCENDIO FORESTAL | D23: 46055 | E23: 40 MNTOS | F23: CRA 16 #25 04 | G23: LA CAMPESINA | H23: QUEMA DE RESIDUOS SOLIDOPS QUE ESTAN REALIZANDO DOS ADULTOS MAYORES. SE REALIZA SOFOCACION | I23: 10 MT/2 | J23: 2 | K23: B-4
A24: INCENDIOS | B24: INCENDIO FORESTAL | D24: 46058 | E24: 45 MNTOS | F24: LA CAMPESINA ALTA | G24: LA CAMPESINA | H24: POSIBLE QUEMA DE DESECHOS SIENDO FALSA ALARMA | I24: * | J24: 6 | K24: B-4, L-2
A25: INSPECCIONES DE SEGURIDAD | B25: VISITAS DE SEGURIDAD | D25: 46059 | E25: 3 HORAS | F25: BAR LOS AMIGOS, EL REY DEL DESPECHO Y FINCA VILLA LIANA | G25: LA UNION | H25: SE REALIZAN VISITA PARA DAR CONCEPTO DE SEGURIDAD | I25: . | J25: 1 | K25: L-1
A26: MATERIALES PELIGROSOS | B26: MATERIALES PELIGROSOS / DERRAMES | D26: 46062 | E26: 2 HORAS | F26: CARRERA 15 CON CALLE 12 | G26: BELEN | H26: INFORMAN DE UN BULTO QUE CAE DE UNA MOTO, CON UN PRODUCTO AGRICOLA TOXICO | I26: . | J26: 5 | K26: B-4, L-2
A27: OTROS | B27: CAÍDA / CORTES DE ARBOL | D27: 46062 | E27: 45 MNTOS | F27: VIA PANORAMA KM1 EL AMPARO SAN LUIS | G27: MARTINDOZA | H27: ARBOL QUE CAE TAPONANDO EL CARRIL EN SENTIDO EL AMPARO SAN LUIS | I27: 100 MT/2 | J27: 7 | K27: B-3
A28: MATERIALES PELIGROSOS | B28: FUGA DE GAS NATURAL | D28: 46063 | E28: 30 MINUTOS | F28: PAJARO DE ORO | G28: PAJARO DE ORO | H28: FUGA DE GAS NATURAL | I28: N/A | J28: 5 | K28: B-2, L-2
A29: MATERIALES PELIGROSOS | B29: FUGA DE GAS NATURAL | D29: 46065 | E29: 1 HORA | F29: CALLE 17 # 14 - 57 | G29: EL POPULAR | H29: INFORMAN DE UNA FUGA DE GAS DURANTE TRABAJO EN LA VIA | I29: . | J29: 5 | K29: B-4, L-2
A30: MATERIALES PELIGROSOS | B30: FUGA DE GAS NATURAL | D30: 46066 | E30: 30 MINUTOS | F30: CRA 15 CON CL 17 | H30: FUGA DE GAS POR ROMPIMIENTO DEL TUBO QUE LO TRANSPORTA | I30: N/A | J30: 7 | K30: B-2, L-2
A31: INCENDIOS | B31: INCENDIO FORESTAL | D31: 46065 | E31: 4.40 HORAS | F31: MORELIA | G31: SANTA RITA | H31: APOYO OPERATIVO CON MAQUINAA EXTINTORA,CARROTANQUE Y PERSONAL, AL CBV DE ROLDANILLO EN QUEMA DE RESIDUOS AGRICOLAS,QUE SE SALEN DE CONTROL | I31: 2 HECTAREAS | J31: 11 | K31: B-4, L-1, OTROS
A32: INCENDIOS | B32: CORTO CIRCUITO | D32: 46068 | E32: 1 HORA | F32: VIA SAN LUIS S/N 730 | G32: SAN LUIS | H32: INFORMAN DE UN POSTE EN LLAMAS | I32: . | J32: 3 | K32: B-4
A33: MATERIALES PELIGROSOS | B33: FUGA DE GAS NATURAL | D33: 46070 | E33: 47 MNTOS | F33: CALLE 21 CRA 15 ESQU | G33: SAN PEDRO | H33: FUGA DE GAS NATURAL POR ROMPIMIENTO EN LA TUBERIA AL REALIZAR TRABAJOS DE CONSTRUCCION | I33: 100MT/2 | J33: 5 | K33: B-2, L-2
A34: RESCATES | B34: RESCATE DE ANIMAL | D34: 46071 | E34: 1 HORA | F34: CARRERA 10 # 15 - 28 | G34: BELEN | H34: INFORMAN DE UN GATO EN UN ARBOL QUE SE DIFICULTA BAJAR POR MOTIVOS DE LLUVIA | I34: . | J34: 3 | K34: B-2
A35: OTROS | B35: CAÍDA / CORTES DE ARBOL | D35: 46074 | E35: 2 HORAS | F35: CRA 12 CALLE10 | G35: BELEN | H35: POR FUERTES VIENTO EN EL MNPIO SE CAE UN ARBOL SOBRE LA PARTE SUPERIOR DE UNA VIVIENDA, RESULTANDO AFECTADO EL TECHO | I35: 40 M/2 | J35: 5 | K35: L-2
A36: OTROS | B36: COLAPSO DE ESTRUCTURAS | D36: 46074 | E36: 1 HORA | F36: EL JORDAN | G36: EL JORDAN | H36: TECHO DE GUADUA Y ZINC QUE POR LOS FUERTE VIENTOS EN EL MPIO SE CAE A LA VIA PUBLICA | I36: 40 MT/2 | J36: 5 | K36: L-2
A37: RESCATES | B37: CONTROL DE ABEJAS | D37: 46073 | E37: 1.05 HORAS | F37: CALLE 11 CRA 15 ESQ | G37: CALLE LINDA | H37: VERIFICACION DE ABEJAS EN VIVIENDA | I37: * | J37: 1 | K37: L-1
A38: RESCATES | B38: CONTROL DE ABEJAS | D38: 46073 | E38: 20 MNTOS | F38: CASA CONSISTORIAL | G38: ZONA CENTRO | H38: APOYO A PERSONAL DE LA ALCALDIA EN RECUPERACION DE ABEJAS | I38: 30 MT/2 | J38: 2 | K38: L-1
A39: RESCATES | B39: CONTROL DE ABEJAS | D39: 46074 | E39: 40 MNTOS | F39: CASA CONSISTORIAL | G39: ZONA CENTRO | H39: APOYO OPERATIVO AL PERSONAL DE HUMATA PARA CAPTURAR ABEJAS QUE ESTAN EN EL TECHO DE LA CASA CONSISTORIAL | I39: 50 MT/2 | J39: 5 | K39: L-2
A40: OTROS | B40: CAÍDA / CORTES DE ARBOL | D40: 46076 | E40: 1.05 HORAS | F40: CRA 27 23 125 | G40: EL CARMEN | H40: ARBOL QUE CAE POR FUERTES AGUACEROS EN LA MADRUGA , TAPOBNANDO LA VIA ENTRE SAN JOSE Y EL AJISAL DEJANDO HABITANTES SIN PASO VEHICULAR | I40: 50MT/2 | J40: 4 | K40: L-1
A41: OTROS | B41: CAÍDA / CORTES DE ARBOL | D41: 46076 | E41: 2.13 HORAS | F41: CRA 12 #10 31 | G41: BELEN | H41: ARBOL QUE CAE SOBRE UN TECHO DE LA VIVIENDA, DEBIDO A FUERTES AGUACEROS DURANTE EL FIN DE SEMANA | I41: 20 MT/2 | J41: 5 | K41: B-2, L-1
A42: OTROS | B42: CAÍDA / CORTES DE ARBOL | D42: 46076 | E42: 2.15 | F42: QUEBRADA LA UNION CRA 12 | G42: BELEN | H42: ARBOL QUE CAE AL CAUCE DE LA QUEBRADA POR LA CRA 12 PUENTE DE LOS MIRANDAS | I42: 20 MT/2 | J42: 5 | K42: B-2, L-1
... A49: OTROS | B49: LABORES DE PREVENCION O ACOMPAÑAMIENTO EN GESTION DEL RIESGO | D49: 46079 | E49: 1 HORA | F49: QUEBRADA LA UNION | G49: EL JORDAN | H49: CRESIENTE SUBITA | I49: N/A | J49: 4 | K49: L-2
A50: OTROS | B50: CONTROL DE ABEJAS | D50: 46080 | E50: 0.0625 | F50: CR 12A 8-74 | G50: CIUDADELA | H50: ABEJAS EN UNA CASA | I50: N/A | J50: 6 | K50: B-3
A51: RESCATES | B51: RESCATE DE ANIMAL | D51: 46081 | E51: 20 MINUTOS | F51: CLL 23 # 14-16 | G51: SAN PEDRO | H51: RESCATE DE UNA ZARIGUELLA PERO AL LLEGAR AL SITIO YA SE HABIA IDO | I51: N/A | J51: 2 | K51: B-3
A52: OTROS | B52: CAÍDA / CORTES DE ARBOL | D52: 46081 | E52: 3 HORAS | F52: LA BATEA | H52: ARBOL QUE CALLO SOBRE LA VIA | I52: N/A | J52: 3 | K52: L-1
A53: OTROS | B53: CAÍDA / CORTES DE ARBOL | D53: 46081 | E53: 3 HORAS | F53: VIA LA UNION LA VICTORIA | G53: N/A | H53: CAIDA DE ARBOL SOBRE LA VIA | I53: N/A | J53: 3 | K53: L-1
A54: MARZO
A55: OTROS | B55: CONTROL DE ABEJAS | C55: =COUNTIF(B55:B78,C2) -> 8 | D55: 46083 | E55: 4.15 HORAS | F55: CEMENTERIO MUNICIPAL | G55: SAN PEDRO | H55: CONTROL Y RECUPERACION DE TRES COLMENAS DE ABEJAS QUE ESTAN EN BOBEDAS DEL CEMENTERIO. SE REQUIERE APOYO DE APICULTORES PARTICULARES Y FUNCIONARIO DE AGRICULTURA | I55: 200MT/2 | J55: 5 | K55: B-3
A56: INCENDIOS | B56: INCENDIO FORESTAL | D56: 46085 | E56: 1.15 HORAS | F56: FINCA LA ESPERANZA | G56: CORCEGA | H56: QUEMA DE RESIDUOS AGRICOLAS QUE SE SALE DE CONTROL A LOS TRABAJADORES DE LA FINCA | I56: 1 PLAZA | J56: 6 | K56: B-4, L-2
A57: INCENDIOS | B57: INCENDIO FORESTAL | D57: 46086 | E57: 39 MNTOS | F57: LINDEROS | G57: LA ISLA | H57: QUEMA DE CAÑA QUE ESTA SIENDO CONTROLADA POR TRABAJADORES DE LA FINCA SE DEJAN RECOMENDACIONES | I57: * | J57: 5 | K57: B-2, L-1
A58: OTROS | B58: CAÍDA / CORTES DE ARBOL | D58: 46094 | E58: 4 HORAS | F58: QUEBRADA LA UNION | G58: LA MILAGROSA | H58: ARBOLES QUE CAEN POR CRECIENTES SUBITAS AL CAUCE DE LA QUEBRADA LA UNION TAPONANDO EL FLUJO DE LA MISMA | I58: 200 MT | J58: 4 | K58: L-1
A59: MATERIALES PELIGROSOS | B59: FUGA DE GAS NATURAL | D59: 46094 | E59: 40 MNTOS | F59: CALL 15 CRA 21 ESQ | G59: SAN PEDRO | H59: FUGA DE GAS POR ROMPIMIENTO DE LA TUBERIA EN LA CONSTRUCCION AL FRENTE DEL CEMENTERIO | I59: 10 MT | J59: 3 | K59: B-4
A60: INCENDIOS | B60: INCENDIO ESTRUCTURAL | D60: 46094 | E60: 30 MNTOS | F60: MANZ B CASA 5 | G60: URBA LA ESPERANZA | H60: INCENDIO EN UNA CERCA, POR QUEMAS DE BASURAS EN EL INTERIOR DE LA VIVIENDA, LA CUAL SE LE SALE DE CONTROL | I60: 20 MT | J60: 3 | K60: B-4
A61: INCENDIOS | B61: INCENDIO FORESTAL | D61: 46094 | E61: 30 MINUT6OS | F61: FINCA DOCTOR ESTEFEN | G61: LAS BRISAS | H61: INCENDIO QUE SE SALIO DE CONTROL PERO FUE CONTROLADO POR GENTE DEL LUGAR | I61: N/A | J61: 3 | K61: B-4
A62: INCENDIOS | B62: INCENDIO FORESTAL | D62: 46097 | E62: 2 HORAS | F62: LINDEROS | H62: INCENDIO POR POSIBLE QUEMA CONTROLADA QUE SALIO DE CONTROL | I62: 2.75 HECTAREAS | J62: 7 | K62: B-4, L-1
A63: RESCATES | B63: CONTROL DE ABEJAS | D63: 46097 | E63: 1.10 HORAS | F63: CRA 11 CALLE 18a | G63: POPULAR | H63: RECUPERACION DE UN ENJAMBRE DE ABEJAS QUE LLEVA TRES DIAS EN UNA LLANTA EN LOS LAGOS DE PESCA VILLA KERLY | I63: 100/ MT | J63: 2 | K63: L-1
A64: RESCATES | B64: CONTROL DE AVISPAS | D64: 46097 | E64: 25 MNTOS | F64: CALLE 13 CRA 17 | G64: LA CRUZ | H64: ENJAMBRE DE AVISPAS QUE SE ENCUENTRAN EN UN ARBOL PEQUEÑO ,AFECTANDO LOS HABITANTES DE LA VIVIENDA | I64: 20 MT/2 | J64: 2 | K64: L-1
A65: OTROS | B65: CAÍDA / CORTES DE ARBOL | D65: 46098 | E65: 27 MNTOS | F65: VIA LA UNION LA VICTORIA KL 0.5 | G65: RURAL | H65: RAMA DE UN ARBOL QUE CAE SOBRE LA CABINA DE UN TRACTO CAMION OCASIONANDO DAÑOS MATERIALES | I65: 30 MT | J65: 3 | K65: B-4
A66: MATERIALES PELIGROSOS | B66: FUGA DE GAS NATURAL | D66: 46100 | E66: UNA HORA Y DIEZ MINUTOS | F66: VIA PANORAMA | G66: CORREGIMIENTO DE SAN LUIS | H66: ROTURA DE TUVERIA DE GAS | I66: N/P | J66: 4 | K66: B-2
A67: INCENDIOS | B67: INCENDIO VEHICULAR | D67: 46100 | E67: 30 MINUTOS | F67: CALLE 15 CON CRA 16 ESQUINA | H67: INCENDIO VEHICULAR CONTROLADO POR LA POBLACION CIVIL | I67: N/A | J67: 3 | K67: B-4
A68: INCENDIOS | B68: INCENDIO FORESTAL | D68: 46101 | E68: 2.21 HORAS | F68: CORCEGA ASORUT | G68: CORCEGA | H68: QUEMA DE CAÑA DE AZUCAR | I68: 3 HECTAREAAS | J68: 7 | K68: B-4, L-2
A69: INCENDIOS | B69: INCENDIO FORESTAL | D69: 46101 | E69: 40 MNTOS | F69: LUCERO BAJO | G69: LUCERO BAJO | H69: QUEMA DE PASTOS QUE SE SALEN DE CONTROL SE REFRIGERA LA ORILLA DEL CERCO | I69: 30MT | J69: 7 | K69: B-4, L-2
A70: INCENDIOS | B70: INCENDIO FORESTAL | D70: 46104 | E70: 1 HORA | F70: URBANIZACION LOS ANGELES | G70: LOS ANGELES | H70: INFORMAN DE UNA QUEMA DE PASTIZAL QUE NO PUEDEN APAGAR | I70: 500 MTR | J70: 3 | K70: B-2
A71: INCENDIOS | B71: INCENDIO FORESTAL | D71: 46104 | E71: 30 MINUTOS | F71: KL 23 VIA A SANLUIS | G71: MARTINDOSA | H71: QUEMA CONTROLADA POR TRABAJADORES | I71: N/A | J71: 2 | K71: B-2
A72: OTROS | B72: FUGA DE GAS NATURAL | D72: 46105 | E72: 1 HORA | F72: CLL 22 # 15-57 | G72: SAN LUIS | H72: FUGA DE GAS NATURAL POR ROMPIMIENTO DE TUBO | I72: N/A | J72: 3 | K72: B-4
A73: OTROS | B73: FUGA DE GAS NATURAL | D73: 46108 | E73: 30 MINUTOS | F73: CL 14 # 7-01 | G73: LA LAJAS | H73: FUGA DE GAS POR ROMPIMIENTO DE TUBO | I73: N/A | J73: 4 | K73: B-4
A74: OTROS | B74: LABORES DE PREVENCION O ACOMPAÑAMIENTO EN GESTION DEL RIESGO | D74: 46110 | E74: 3.21 HORAS | F74: CALLES DEL MUNICIPIO | G74: CALLES DEL MUNICIPIO | H74: ACOMPAÑAMIENTO DURANTE LA PROCESION DEL DOMINGO DE RAMOS | I74: * | J74: 15 | K74: B-3, B-4, L-1
A75: RESCATES | B75: RESCATE DE ANIMAL | D75: 46111 | E75: 2.30 | F75: CR 15 # 19 24 | H75: ZARIGUELLA ATRAPADAS | I75: N/A | J75: 3 | K75: L-1
A76: RESCATES | B76: RESCATE DE ANIMAL | D76: 46111 | E76: 1 HORA | F76: CR 21 # 12-65 | G76: PASO ANCHO | H76: ZARIGUELLA ATRAPADA EN UN CIELO RAZO | I76: N/A | J76: 3 | K76: L-1
A77: RESCATES | B77: RESCATE DE ANIMAL | D77: 46112 | E77: 1.15 HORAS | F77: CRA 15 19 24 | G77: POPULAR | H77: RESCATE DE ZARIGUEYA QUE ESTABA EN UNA VIVIENDA | I77: * | J77: 2 | K77: L-1
A78: RESCATES | B78: CONTROL DE AVISPAS | D78: 46112 | E78: 1.54 HORAS | F78: CRA 21 15 78 | G78: PASOANCHO | H78: RECOLECCION DE AVISPAS | I78: * | J78: 4 | K78: L-1
A79: ABRIL
A80: OTROS | B80: CAÍDA / CORTES DE ARBOL | C80: =COUNTIF(B80:B101,C2) -> 2 | D80: 46113 | E80: 1 HORA | F80: PARQUE PRINICIPAL ARGEMIRO ESCOBAR CARDONA | G80: CENTRO | H80: INFORMAN DE UN ARBOL QUE CAE DEBIDO A VIENTOS FUERTES | I80: . | J80: 3 | K80: L-1
A81: OTROS | B81: LABORES DE PREVENCION O ACOMPAÑAMIENTO EN GESTION DEL RIESGO | D81: 46114 | E81: 4 HORAS | F81: PARROQUIA SAN JOSE | G81: CENTRO | H81: ACOMPAÑAMIENTO DURANTE PROCESION Y PRESTADA DE GUARDIA EN LA IGLESIA | I81: . | J81: 26 | K81: B-2, B-3
A82: MATERIALES PELIGROSOS | B82: FUGA DE GAS NATURAL | D82: 46118 | E82: 1.13 HORAS | F82: SAN LUIS POR LA ESQUINA DEL SABOR | G82: SAN LUIS | H82: ROMPIMIENTO DE TUBERIA DE GAS NATURAL, | I82: 100 M/2 | J82: 3 | K82: B-2
A83: OTROS | B83: LABORES DE PREVENCION O ACOMPAÑAMIENTO EN GESTION DEL RIESGO | D83: 46115 | E83: 4.55 HORAS | F83: CALLES DEL MUNICIPIO | G83: SAN LUIS A LA UNION ZONA CENTRO | H83: ACOMPAÑAMIENTO A EVENTOS RELIGIOSOS DE LA SEMANA SANTA | I83: * | J83: 22 | K83: B-2, B-3, B-4
A84: OTROS | B84: LABORES DE PREVENCION O ACOMPAÑAMIENTO EN GESTION DEL RIESGO | D84: 46115 | E84: 0.10416667 | F84: CALLES DEL PUEBLO | H84: ACOMPAÑAMIENTO EN LA PROCESION | I84: N/A | J84: 20 | K84: B-2, B-3
A85: INSPECCIONES DE SEGURIDAD | B85: VISITAS DE SEGURIDAD | D85: 46122 | E85: 2 HORAS | F85: MEDIVALLE SAS, SALSAMENTARIA LOS HATEÑOS, PAMELA GORDILLO | G85: LA UNION | H85: SE REALIZAN VISITAS A ESTABLECIMIENTOS DEL MUNICIPIO PARA CONCEPTOS DE SEGURIDAD | I85: . | J85: 1 | K85: L-3
A86: MATERIALES PELIGROSOS | B86: FUGA DE GAS NATURAL | D86: 46122 | E86: 30 MINUTOS | F86: CALLE 14 7 73 | G86: LAS LAJAS | H86: INFORMAN DE UNA DAÑO EN LA TUVERIA DEL GAS POR TRABAJOS EN LA VIA | I86: . | J86: 3 | K86: B-2
A87: OTROS | B87: INCENDIO FORESTAL | D87: 46122 | E87: 4.10 HORAS | F87: VIA ROLDANILLO LA UNION | G87: HIGUERON SANTA RITA | H87: APOYO OPERATIVO CON MAQUINA EXTINTORA Y PERSONAL PARA CONTROLAR INCENDIO FORESTAL | I87: * | J87: 8 | K87: B-4, L-1
A88: OTROS | B88: LABORES DE PREVENCION O ACOMPAÑAMIENTO EN GESTION DEL RIESGO | D88: 46116 | E88: 1 HORA Y 30 MINUTOS | F88: PROCESIÓN PARROQUIA SAN JOSE | G88: CENTRO | H88: ACOMPAÑAMIENTO A EVENTOS RELIGIOSOS DE LA SEMANA SANTA | I88: N/A | J88: 10 | K88: B-2, B-3
A89: OTROS | B89: CONTROL DE ABEJAS | D89: 46125 | E89: 4 HORAS | F89: FINCA VILLEDO LA JULIANA | G89: SAN LUIS | H89: INFORMAN DE UN ATAQUE DE ABEJAS A UN TERNERO Y A UN TRABAJADOR DE LA FINCA | I89: . | J89: 4 | K89: B-3
A90: INSPECCIONES DE SEGURIDAD | B90: VISITAS DE SEGURIDAD | D90: 46125 | E90: 2 HORAS | F90: ULTRAIMAGEN, MOTO SPORT, VALLAS MOTOS | G90: CENTRO | H90: VISITAS PARA REALIZAR CONCEPTO DE SEGURIDAD | I90: . | J90: 2 | K90: L-3
A91: INSPECCIONES DE SEGURIDAD | B91: VISITAS DE SEGURIDAD | D91: 46125 | E91: 2 HORAS | F91: RECICLAJE, DPIN PANTHER COFFE BAR, SARAY, TIENDA SOFI | G91: CENTRO | H91: SE REALIZAN VISITA PARA CONCEPTO DE SEGURIDAD | I91: . | J91: 1 | K91: L-3
A92: OTROS | B92: LABORES DE PREVENCION O ACOMPAÑAMIENTO EN GESTION DEL RIESGO | D92: 46127 | E92: 1.30HORAS | F92: ALCANDIA MNPAL | G92: BELEN | H92: REUNION CMGRD ASUNTO CABALGATA 18 ABRIL | I92: * | J92: 1 | K92: N/A
A93: MATERIALES PELIGROSOS | B93: MATERIALES PELIGROSOS / DERRAMES | D93: 46130 | E93: 18 MNTOS | F93: CRA 7 CALLE 13 | G93: BELEN | H93: FUGA DE GAS VEHICULAR, POR EL SISTENA DE TUBERIA | I93: * | J93: 4 | K93: B-2
A94: OTROS | B94: CONTROL DE ABEJAS | D94: 46131 | E94: 2 HORAS | F94: FINCA MARGARITA | G94: PAJARO DE ORO | H94: INFORMAN DE UN ENJAMBRE DE ABEJAS CERCA A UNOS ESTABLOS | I94: . | J94: 3 | K94: L-2
A95: OTROS | B95: PRIMEROS AUXILIOS | D95: 46131 | E95: 30 MINUTOS | F95: SABANAZO | G95: SABANAZO | H95: INFORMAN DE UN ACCIDENTE DE TRANSITO CERCA AL LUGAR DONDE SE ENCONTRABA LA L-2 REALIZANDO UNA LIBERACION DE ABEJAS. SE ATIENDEN DOS LESIONADOS Y LUEGO SON ENTREGADOS A LA AMBULANCIA SUB SALUD | I95: . | J95: 3 | K95: L-2
A96: RESCATES | B96: RESCATE DE ANIMAL | D96: 46133 | E96: 1 HORA | F96: FINCA LA MANUELA | G96: SAN LUIS | H96: INFORMAN DE LA FINCA, QUE ENCUENTRAN UNA CULEBRA ENRREDADA EN UNA MALLA | I96: . | J96: 3 | K96: L-2
... A99: INCENDIOS | B99: INCENDIO ESTRUCTURAL | D99: 46139 | E99: 24 MNTOS | F99: EL PARAISO | G99: EL PARAISO | H99: INCENDIO ESTRUCRURAL EN UNA BODEGA,POSIBLEMENTE POR UNA VELADORA, LA COMUNIDAD YA TENIA CONTROLADA LA SITUACION | I99: 50 MT/2 | J99: 7 | K99: B-4, L-1
A100: OTROS | B100: CONTROL DE ABEJAS | D100: 46142 | E100: 1 HORA | F100: PARQUE PRINCIPAL | H100: PANAL DE ABEJAS EN EL POSTE DE LA CAMARA | I100: N/A | J100: 3 | K100: B-3
A101: INCENDIOS | B101: INCENDIO FORESTAL | D101: 46142 | E101: 44 MINUTOS | F101: CL 24 12-03 | G101: SAN PEDRO | H101: SINGLA QUER SE QUEMA EN UNA URBANIZACION EN CONSTRUCIO | I101: 10 MTS LINEALES | J101: 2 | K101: B-2
A102: MAYO
A103: INCENDIOS | B103: CORTO CIRCUITO | C103: =COUNTIF(B103:B127,C2) -> 1 | D103: 46144 | E103: 1 HORA | F103: VIA LA UNION - LA VICTORIA | G103: PANORAMA | H103: INFORMA DE UN ARBOL QUE CAE A LA VIA Y ESTA ENERGIZADO PRODUCIENDO CHISPAS | I103: . | J103: 2 | K103: B-4
A104: OTROS | B104: LABORES DE PREVENCION O ACOMPAÑAMIENTO EN GESTION DEL RIESGO | D104: 46145 | E104: 2 HORAS | F104: CORCEGA | G104: CORCEGA | H104: INFORMAN DE DESBORDAMIENTO DEL AGUA EN LA CANAL | I104: . | J104: 4 | K104: L-2
A105: OTROS | B105: LABORES DE PREVENCION O ACOMPAÑAMIENTO EN GESTION DEL RIESGO | D105: 46146 | E105: 1 HORA | F105: QUEBRADA LA UNION | H105: CRESIENTE DE LAS QUEBRADAS DE LA UNION | I105: N/A | J105: 3 | K105: L-2
A106: OTROS | B106: CONTROL DE ABEJAS | D106: 46149 | E106: 32 MNTOS | F106: CEMENTERIO MNCIPAL | G106: SAN PEDRO | H106: VERIFICACION DE ABEJAS | I106: * | J106: 2 | K106: L-2
A107: RESCATES | B107: CONTROL DE ABEJAS | D107: 46150 | E107: 2.15 HORAS | F107: CEMENTERIO MUNICIPAL | G107: SAN PEDRO | H107: RECUPERACION DE 2 ENJAMBRES DE ABEJAS QUE ESTAN EN LAS BOVEDAS DEL CEMENTERIO, SE RECIBE APOYO DE LA OFICINA DE AGRICULTURA MNPAL CON UN FUNCIONARIO | I107: 100 M/2 | J107: 2 | K107: B-3
A108: RESCATES | B108: RESCATE DE ANIMAL | D108: 46154 | E108: 1 HORA | F108: CR 23 22 78 | G108: EL CARMEN | H108: INFORMAN DE UN PERRO QUE CAE A UN POZO | I108: . | J108: 5 | K108: B-3
...

Sheet 2025
A1: TIPO DE INCIDENTE | B1: INCIDENTES Y ACTIVIDADES | C1: CANTIDAD DE | D1: DÍA DEL EVENTO | E1: DURACIÓN DEL EVENTO | F1: DIRECCIÓN O LUGAR DE REFERENCIA | G1: BARRIO CORREGIMIENTO O VEREDA | H1: DESCRIPCIÓN DEL EVENTO | I1: AREA AFECTADA (SOLO SI APLICA) | J1: N° DE UNIDADES QUE ASISTIERON | K1: VEHÍCULO
C2: ='DETALLADO X MES 2026'!J2 -> INCENDIO FORESTAL
A3: ENERO
A4: OTROS | B4: FUGA DE GAS NATURAL | C4: =COUNTIF(B4:B32,C2) -> 7 | D4: 45666 | E4: 1 HORA | F4: CALLE 23A 12 68 | G4: SAN PEDRO | H4: RUPTURA DE TUBERIA DE GAS DURANTE TRABAJO EN VIVIENDA | I4: . | J4: 4
A5: INSPECCIONES DE SEGURIDAD | B5: VISITAS DE SEGURIDAD | D5: 45670 | E5: 1 HORA | F5: CALLE 15 CRA 15 ESQ | G5: ZONA CENTRO | H5: VISITA DE SEGURIDAD A BANCO DE OCCIDENTE | I5: * | J5: 1
A6: INSPECCIONES DE SEGURIDAD | B6: VISITAS DE SEGURIDAD | D6: 45670 | E6: 1 HORA | F6: CRA 14 CALLE 12 | G6: ZONA CENTRO | H6: VISITA DE SEGURIDAD A LOCAL DIVINAS BELLEZA INTEGRAL | I6: * | J6: 1
A7: INSPECCIONES DE SEGURIDAD | B7: LABORES DE PREVENCION O ACOMPAÑAMIENTO EN GESTION DEL RIESGO | D7: 45671 | E7: 1.10 HORAS | F7: CAPILLA DE LA ERMITA | G7: BELEN | H7: SE REALIZA INSPECCION OCULAR A LA CAPILLA DE LA ERMITA, DEBIDO A SU DETERIORO EN EL TECHO | I7: * | J7: 2
A8: OTROS | B8: RESCATE DE ANIMAL | D8: 45672 | E8: 1 HORA | F8: FINCA LOS LIMONES | G8: VEREDA EL GUASIMO | H8: SE REALIZA CONTROL DE UN ENJAMBRE DE AVISPAS | I8: . | J8: 3
A9: FALSA ALARMA | B9: INCENDIO FORESTAL | D9: 45674 | E9: 28 MINUTOS | F9: ALREDEDORES BARRIO EL AMPARO | G9: EL AMPARO | H9: REPORTE DE UN INCENDIO FORESTAL QUE RESULTÓ EN FALSA ALARMA YA QUE SE TRATABA DE UNA QUEMA CONTROLADA DENTRO DE LOS PREDIOS DE UNA EMPRESA PRIVADA | I9: NA | J9: 5
A10: RESCATES | B10: RESCATE DE ANIMAL | D10: 45675 | E10: 37 MNTOS | F10: CALLE 22 CRA 18 | G10: SAN PEDRO | H10: RESCATE ANIMAL DE UNA SARIGUEYA LA CUAL NO SE ENCONTRO EN LA VIVIENDA | I10: * | J10: 2
A11: INCENDIOS | B11: INCENDIO FORESTAL | D11: 45676 | E11: 3.37 HORAS | F11: APOYO OPERATIVO AL CBV LA VICTORIA | G11: LA VICTORIA | H11: APOYO OPERATIVO EN INCENDIO AGRICOLA AL CBV DE LA VICTORIA | I11: * | J11: 4
A12: INCENDIOS | B12: INCENDIO VEHICULAR | D12: 46011 | E12: 1.33 HORAS | F12: HACIENDA EL CORTIJO | G12: CORCEGA | H12: SE RECIBE LLAMADO DE LA SÑRA LEYDI INFORMANDO DE UNA QUEMA DE CAÑA,AL LLEGAR AL SITIO ES UN INCENDIO VEHICULAR AGRICOLA | I12: * | J12: 10
A13: OTROS | B13: FUGA DE GAS NATURAL | D13: 45678 | E13: 35 MNTOS | F13: CRA 19 #19 40 | G13: SAN PEDRO ARRIBA | H13: FUGA DE GAS NATURAL POR ROMPIMIENTO DE TUBERIA | I13: * | J13: 4
A14: INSPECCIONES DE SEGURIDAD | B14: VISITAS DE SEGURIDAD | D14: 45679 | E14: 1.30HORAS | F14: BANCO DE LA MUJER | G14: ZONA CENTRO | H14: VISITA DE SEGURIDAD A ENTIDA BANCARIA | I14: * | J14: 1
A15: INCENDIOS | B15: INCENDIO FORESTAL | D15: 45680 | E15: 39 MNTOS | F15: LINDEROS | G15: LINDEROS | H15: QUEMA DE RASTROJO POR LA TERCERA CANAL | I15: 100 MT | J15: 5
A16: BUSQUEDA Y RESCATE | B16: RESCATE DE PERSONA / PARAPENTE | D16: 45681 | E16: 2.30 HORAS | F16: LA BALASTRERA VIA QUEBREDA GRANDE | G16: LA BALASTRERA | H16: APOYO OPERATIVO A PONAL EN LA BUSQUEDAD DE PERSONA DESAPARECIDA EN LA ZONA MONTAÑOSA DE LA UNION | I16: * | J16: 4
... A19: RESCATES | B19: RESCATE DE ANIMAL | D19: 45681 | E19: 2.12 HORAS | F19: CRA 25 12 73 | G19: VIA CASA BLANCA | H19: SE REALIZA EL RESCATE DELOS GATOS ,EL DIA ANTERIOR NO FUE POSIBLE REALIZAR EL RESCATE,POR QUE NO SE ENCONTRARON LOS ANIMALITOS | I19: * | J19: 2
A20: INCENDIOS | B20: INCENDIO FORESTAL | D20: 45682 | E20: 2 HORAS | F20: LA VICTORIA | H20: APOYO A LA VICTORIA VALLE DEL CAUCA EN INCENDIO FORESTAL | I20: N/A | J20: 4
A21: BUSQUEDA Y RESCATE | B21: RESCATE DE PERSONA / PARAPENTE | D21: 45682 | E21: 1.34 HORAS | F21: LA BALASTRERA | G21: LA BALASTRERA VIA QUEBRADA GRANDE | H21: SE PRESTA APOYO PARA RECUPERACION DE CADAVER Y MOTOCICLETA DE PERSONA QUE ESTABA DESAPARECIDA | I21: * | J21: 5
A22: INCENDIOS | B22: INCENDIO FORESTAL | D22: 45683 | E22: 4.10 HORAS | F22: LA VICTORIA VALLE | G22: LA VICTORIA | H22: APOYO OPERATIVO EN INCENDIO AGRICOLA AL CBV DE LOA VICTORIA | I22: * | J22: 4
A23: INCENDIOS | B23: INCENDIO ESTRUCTURAL | D23: 45684 | E23: 3.10 HORAS | F23: VEREDA EL RINCON | G23: VEREDA EL RINCON | H23: INCENDIO ESTRUCTURAL CON PERDIDA TOTAL DE VIVIENDA,ENCERES,MOTOCICLETA Y ANIMALES DOMESTICOS | I23: * | J23: 13
A24: OTROS | B24: CONTROL DE ABEJAS | D24: 45685 | E24: 1 HORA | F24: CALLE 18B 12 21 | G24: EL POPULAR | H24: UN ENJAMBRE DE ABEJAS EN EL TECHO DE UN TERCER PISO | I24: . | J24: 5
A25: OTROS | B25: SUMINISTROS DE AGUA | D25: 45685 | E25: 3 HORAS | F25: ZONAS VERDES DEL MUNICIPIO | G25: SAN LUIS - BELEN | H25: SE PRESTA SERVICIO DE RIEGO EN ALGUNOS LUGAR CON ZONA VERDE EN EL MUNICIPIO | I25: . | J25: 4
A26: RESCATES | B26: RESCATE DE PERSONA / PARAPENTE | D26: 45686 | E26: 1 HORA | F26: EL LUCERO | G26: EL LUCERO | H26: PARAPENTE QUE ATERRISO AL PARECER CON DIFICULTAD | I26: N/A | J26: 9
A27: INCENDIOS | B27: INCENDIO FORESTAL | D27: 45686 | E27: 30 MINUTOS | F27: CR 8 CLL 14 | G27: BELEN | H27: INFORMA LA COMUNIDAD QUE UNA PERSONA QUEMA UNA BASURA QUE SE ENCONTRABA EN UN LOTE Y SE SALE DE CONTROL | I27: . | J27: 4
A28: OTROS | B28: PRIMEROS AUXILIOS | D28: 45686 | E28: 1 HORA | F28: VIA LA UNION - SAN LUIS | G28: PRADOS DEL NORTE | H28: SE PRESTA PRIMEROS AUXILIOS A UNA PERSONA TRAS COLISION DE DOS MOTOCICLISTAS | I28: . | J28: 4
A29: INSPECCIONES DE SEGURIDAD | B29: VISITAS DE SEGURIDAD | D29: 45687 | E29: 23 MNTOS | F29: CALLE 14 3 172 | G29: LAS LAJAS | H29: SE REALIZA INSPECCION DE SEGURIDAD A ESTABLECIMIENTO LOKATEL COCTELES | I29: * | J29: 1
A30: INSPECCIONES DE SEGURIDAD | B30: VISITAS DE SEGURIDAD | D30: 45687 | E30: TREINTE MINUTOS | F30: CALL 14 # 3 172 | G30: LAS LAJAS | H30: INSPECION DE SEGURIDAD | I30: N/P | J30: 1
A31: INCENDIOS | B31: INCENDIO FORESTAL | D31: 45688 | E31: UNA HORA | F31: KR 15 EL LUCERO | G31: BARRIO EL LUCERO PISTA DE MOTOS | H31: INCENDIO DE SINGLA | I31: N/P | J31: 4
A32: OTROS | B32: CONTROL DE ABEJAS | D32: 45688 | E32: 1.15 HORAS | F32: IGLESIA DE LA ERMITA | G32: LAS LAJAS | H32: CONTROL Y RECUPERACION DE ABEJAS E | I32: * | J32: 2
A33: FEBRERO
A34: MATERIALES PELIGROSOS | B34: MATERIALES PELIGROSOS / DERRAMES | C34: =COUNTIF(B34:B55,C2) -> 0 | D34: 45689 | E34: 1.26 HORAS | F34: CRA 18 Y 19 CALLE 16 HASTA | G34: SECTOR DE LA GALERIA | H34: DERRAME DE ACEITE DE MOTOR APROXIMADAMENTE 160 MT | I34: 160 MT LINEALES | J34: 6 | K34: B-2, B-3
A35: RESCATES | B35: RESCATE DE PERSONA / PARAPENTE | D35: 45690 | E35: CUATRO HORAS | F35: VEREDA EL LUCERO | G35: EL LUCERO | H35: SE REALIZA EL RESCATE DE UN PARAPENTE QUE CAE EN ZONA BOSCOSA DE LA VEREDA EL LUCERO, SIENDO ENCONTRADO SIN LECIONES Y MOVILIZÁNDOSE POR SUS PROPIOS MEDIOS. SE HACE LA EXTRACIÓN DEL ÁREA Y SE DEJA EN LA TERMINAL DE TRANSPORTES YA QUE SU ALOJAMIENTO SE UBICA EN ROLDANILLO. | I35: NA | J35: 8 | K35: B-3, L-1
A36: OTROS | B36: PRIMEROS AUXILIOS | D36: 45692 | E36: 49 MNTOS | F36: VEREDA EL RINCON | G36: VEREDA EL RINCON | H36: PERSONA QUE RESULTA AFECTEDA EN DEDO DE LA MANO IZQUIERDA EN LABORES DEL CAMPO,FUE TRASLADADA AL HOSPITAL LOCAL | I36: * | J36: 2 | K36: L-1
A37: OTROS | B37: INUNDACIÓN | D37: 45693 | E37: 26 MNTO | F37: PUENTE DE LOS MIRANDAS | G37: LAS LAJAS | H37: VIVIENDA QUE RESULTA INUNDADA POR COLAPSO DE AGUAS LLUVIAS EN LA VIA, SIN INTERVENSION | I37: 40 MT | J37: 5 | K37: B-3
A38: OTROS | B38: INUNDACIÓN | D38: 45693 | E38: 25 MNTOS | F38: CRA 11 CALLE 8 ESQUINA | G38: BELEN | H38: VIVIENDAS QUE RESULTAN AFECTADAS POR AGUAS LLUVIAS, DEVIDO AL TAPONAMIENTO DEL SERVICIO DE ALCANTARILLADO, SIN INTERVENSION DE LAS UNIDADES | I38: 80 MT | J38: 5 | K38: B-3
A39: INCENDIOS | B39: CORTO CIRCUITO | D39: 45694 | E39: 35 MNTOS | F39: CALLE 18 CRA 13 | G39: PORTAL DE LA ANDINA | H39: INCENDIO ELECTRICO EN TRANSFORMADOR | I39: * | J39: 2 | K39: B-2
A40: MATERIALES PELIGROSOS | B40: FUGA DE GAS GLP | D40: 45694 | E40: 3.25 HORAS | F40: VIA PANORAMA KL 1 VIA R/NILLO HOTEL LOS VIÑEDOS | G40: EL PORTACHUELO | H40: FUGA DE GLP POR AVERIA DE VALVULA DE ALIVIO | I40: 100 MT | J40: 9 | K40: B-3, B-4
A41: MATERIALES PELIGROSOS | B41: FUGA DE GAS GLP | D41: 45694 | E41: 3.15 HORAS | F41: HOTEL LOS VIÑEDOS | G41: EL PORTACHUELO | H41: FUGA DE GAS POR ROMPIMIENTO DE TAPON, QUE SE HABIA INSTALADO EN LA PRIMER EMERGENCIA EN EL MISMO CONTENEDOR | I41: 100 MT | J41: 5 | K41: B-2, OTROS
A42: MATERIALES PELIGROSOS | B42: FUGA DE GAS NATURAL | D42: 45696 | E42: 1.07 HORAS | F42: CALLE 23 # 12 83 | G42: SAN PEDRO | H42: FUGA DE GAS NATURAL POR ROMPIMIENTO DE TUBERIA | I42: 50 MT | J42: 4 | K42: B-2
A43: FALSA ALARMA | B43: INCENDIO ESTRUCTURAL | D43: 45696 | E43: 1 HORA | F43: FINCA DE EDUARDO JIMENEZ | G43: CORSEGA | H43: POSIBLE INCENDIO EXTRUCTURAL | I43: N/A | J43: 4 | K43: B-2
A44: OTROS | B44: INUNDACIÓN | D44: 45699 | E44: 54 MNTOS | F44: CALLE 23 CRA 12 | G44: SAN PEDRO | H44: DOS VIVIENDAS QUE RESULTAN AFECTADAS POR COLAPSO DEL SISTEMA DE ALCANTARILLADO DEL MUNICIPIO, | I44: 150 MT | J44: 3 | K44: B-3
A45: MATERIALES PELIGROSOS | B45: MATERIALES PELIGROSOS / DERRAMES | D45: 45700 | E45: 1 HORA | F45: CALLE 14 CRA 14 | G45: PARQUE PRIN CIPAL | H45: DERRAME DE ACEITE AUTOMOTOR, EN LA VIA PUBLICA, SE UTILIZA CISCO PARA SU CONTENCION | I45: 20 MT | J45: 2 | K45: B-3
A46: MATERIALES PELIGROSOS | B46: FUGA DE GAS NATURAL | D46: 45701 | E46: 23 MNTOS | F46: CRA 15 CALLE 21 | G46: HOSPITAL GONZALO CONTRERAS | H46: POSIBLE FUGA DE GAS EN EN HOSPITAL GONZALO CONTRERAS | I46: * | J46: 2 | K46: B-2
... A55: RESCATES | B55: RESCATE DE ANIMAL | D55: 45707 | E55: 3 H | F55: VEREDA EL RINCON | G55: VEREDA EL RINCON | H55: RESCATE ANIMAL | I55: - | J55: 5 | K55: L-2
A56: MARZO
A57: RESCATES | B57: RESCATE DE PERSONA / PARAPENTE | C57: =COUNTIF(B57:B75,C2) -> 1 | D57: 45717 | E57: 49 MNTOS | F57: HOTEL LOS VIÑEDOS | G57: HOTEL LOS VIÑEDOS | H57: RESCATE A PERSONA | I57: * | J57: 3 | K57: L-2
A58: OTROS | B58: CONTROL DE ABEJAS | D58: 45721 | E58: 25 MNTOS | F58: CALLE 23 FINCA SANTA ANA | G58: SAN PABLO | H58: CONTROL DE ABEJAS EL CUAL NO SE PUEDE REALIZAR POR LA COMPLEJIDA DONDE SE ENCUENTRA EL ENJAMBRE | I58: * | J58: 3 | K58: B-2
A59: RESCATES | B59: RESCATE DE PERSONA / PARAPENTE | D59: 45722 | E59: 5.15 HORAS | F59: TORO V | G59: PATIO BONITO | H59: SE PRESTA APOYO OPERATIVO AL CBV DE TORO PARA BUSQUEDA DE MENOR DESAPARECIDO EL DIA05/03/2025 WEN LA ZONA MONTAÑOSA DEL MNPIO | I59: * | J59: 4 | K59: L-1
A60: OTROS | B60: CONTROL DE ABEJAS | D60: 45723 | E60: UNA HORA | F60: CALLE 23 25 232 | G60: EL CARMEN | H60: REPORTAN UN ENJAMBRE DE ABEJAS | I60: . | J60: 3 | K60: L-1
A61: OTROS | B61: CONTROL DE ABEJAS | D61: 45723 | E61: 1.10 HORAS | F61: IGLESIA DE LA ERMITA | G61: BELEN | H61: CONTROL DEABEJAS EN LA IGLESIA DE LA ERMITA | I61: * | J61: 3 | K61: B-2
A62: OTROS | B62: CONTROL DE ABEJAS | D62: 45723 | E62: 1 HORA | F62: VALLE LINDO | G62: LA HABANA | H62: CONTROL DE ABEJAS EN VALLE LINDO | I62: * | J62: 3 | K62: B-2
A63: RESCATES | B63: PRIMEROS AUXILIOS | D63: 45728 | E63: 40 MNTOS | F63: VIA PANORAMA LA UNION ROLDAANILLO | G63: EL PICACHO | H63: VEHICULO UE PIERDE EL CONTROL Y SE SALE DE LA VIA, CAE A LA CUNETA SIN PERSONAS LESSIONADAS | I63: * | J63: 3 | K63: L-2
A64: RESCATES | B64: RESCATE DE ANIMAL | D64: 45729 | E64: 30 MINUTOS | F64: PUENTE - LAGO DE MONICA | G64: LAGOS DE MONICA | H64: INFORMA DE UN MICO SOBRE EL PUENTE | I64: . | J64: 5 | K64: L-2
A65: INCENDIOS | B65: CORTO CIRCUITO | D65: 45729 | E65: 40 MINUTOS | F65: CR 13 9 15 | G65: LA FLORESTA | H65: INFORMA UNA CIUDADANA DE UN CABLE QUE ESTA PRODUCIENDO CHISPAS | I65: . | J65: 5 | K65: L-2
A66: OTROS | B66: CONTROL DE ABEJAS | D66: 45730 | E66: 2 HORAS | F66: FINCA LA FLORESTA | G66: LA FLORESTA | H66: SE REALIZA CONTROL Y LIBERACION DE ABEJAS | I66: . | J66: 4 | K66: L-2
A67: INSPECCIONES DE SEGURIDAD | B67: VISITAS DE SEGURIDAD | D67: 45733 | E67: 1.15 HORAS | F67: CA15 #17 69 | G67: POPULAR | H67: VISITA DE SEGURIDAD A LOCAL COMERCIAL DE CELULARES | I67: * | J67: 1 | K67: L-1
A68: OTROS | B68: CONTROL DE ABEJAS | D68: 45733 | E68: 1 HORA | F68: CRA 15 #7 28 | G68: LA CIUDADELA | H68: VERIFICACION DE ENJAMBRE DE ABEJAS | I68: * | J68: 1 | K68: L-1
A69: INCENDIOS | B69: INCENDIO FORESTAL | D69: 45735 | E69: 1.15 HORAS | F69: FINCA SAN JUANITO | G69: LA ISLA | H69: QUEMA DE PASTIZAL QUE SE SALE DE CONTROL | I69: 1 HECTAREA | J69: 5 | K69: B-2
... A74: INSPECCIONES DE SEGURIDAD | B74: VISITAS DE SEGURIDAD | D74: 45742 | E74: 2.39 HORAS | F74: MADERAS PLASTICAS VIA LA UNION TORO | G74: EL RODEO | H74: VISITA DE SEGURIDAD EN FABRICA DE MADESRAS PLASTICAS | I74: * | J74: 1 | K74: L-1
A75: INSPECCIONES DE SEGURIDAD | B75: VISITAS DE SEGURIDAD | D75: 45743 | E75: 2.30 HORAS | F75: CRA 13 CALLE 15 | G75: BELEN | H75: VISITA DE SEGURIDAD EN ESTABLECIMIENTO BANCARIO | I75: 9 | J75: 1 | K75: L-3
A76: ABRIL
A77: INCENDIOS | B77: INCENDIO FORESTAL | C77: =COUNTIF(B77:B103,C2) -> 2 | D77: 45750 | E77: 2 HORAS | F77: EL RODEO FABRICA DE MADERAS PLASTICAS | G77: EL RODEO | H77: INCENDIO DE COVERTURA VEGETAL EN LA PARTE DE ATRAS DELA FABRICA,PERSONAL DE LA EMPRESA COLABORAN CON EL CONTROL DEL INCENDIO | I77: 5 HECTAREAS | J77: 7 | K77: B-2, B-4
A78: OTROS | B78: LABORES DE PREVENCION O ACOMPAÑAMIENTO EN GESTION DEL RIESGO | D78: 45751 | E78: 3.55 HORAS | F78: VIA PAJARO DE ORO | G78: PAJARO DE ORO | H78: ACOMPAÑAMIENTO EN LA CAMINATA DE LA INSTITUCCION EDUCATIVA SAN JOSE | I78: * | J78: 5 | K78: L-2
A79: OTROS | B79: LABORES DE PREVENCION O ACOMPAÑAMIENTO EN GESTION DEL RIESGO | D79: 45751 | E79: 0.14583333 | F79: ZONA RURAL | H79: CAMINATA COLEGIO SAN JOSE | I79: N/A | J79: 6 | K79: L-2
A80: INCENDIOS | B80: INCENDIO FORESTAL | D80: 45752 | E80: 1 HORA | F80: FINCA LAS PALMAS | G80: VIA LA UNION - ROLDANILLO | H80: QUEMA DE BASURA | I80: . | J80: 3 | K80: B-2
A81: RESCATES | B81: RESCATE DE ANIMAL | D81: 45755 | E81: 40MNTOS | F81: URBAN LOS ANGELES 32 B 37 | G81: LOS ANGELES | H81: CAPTURA DE RETIL (SERPIENTE) QUE ESTA EN UNA VIVIENDA | I81: * | J81: 4 | K81: L-2
A82: OTROS | B82: RESCATE DE ANIMAL | D82: 45756 | E82: 1 HORA | F82: FINCA EL PALMAR | G82: MARTINDOZA | H82: CAPTURA DE SERPIENTE QUE ESTA DENTRO DE UNA HABITACION | I82: * | J82: 2 | K82: L-2
A83: OTROS | B83: CAÍDA / CORTES DE ARBOL | D83: 45757 | E83: 1.30 HORAS | F83: VIA PANORAMA KL 5 LA UNION TORO | G83: PEDREGAL | H83: POR FUERTES LLUVIAS SE CAE UN ARBOL TAPONANDO LA VIA LA UNION TORO | I83: * | J83: 5 | K83: L-2
A84: OTROS | B84: INUNDACIÓN | D84: 45757 | E84: 1.20 HORAS | F84: CRA 15 5 05 | G84: EL LUCERO | H84: VIVIENDA QUE RESULTA INUNDADA POR FUERTES AGUACEROS EN EL SECTOR, SE DESBORDA LA QUEBRADA EL LUCERO | I84: 7 HECTAREAS CULTIVO DE UVA Y VIVIENDA | J84: 4 | K84: L-2
A85: RESCATES | B85: RESCATE DE ANIMAL | D85: 45758 | E85: 1.15 HORAS | F85: FINCA DE LOS CARDENAS | G85: PASO ANCHO | H85: CAPTURA DE UN REPTIL ESPECIE BABILLA,EL CUAL ESTA EN EL SOLAR DE LA CASAFINCA SE HACE SU RESPECTIVA ENTREGA A LA CVC | I85: * | J85: 4 | K85: L-2
A86: RESCATES | B86: RESCATE DE ANIMAL | D86: 45759 | E86: HORA Y MEDIA | F86: FINCA ESTERLINA | G86: PAJARO DE ORO | H86: SERPIENTE EN UN ARBOL | I86: . | J86: 3 | K86: L-1
A87: FALSA ALARMA | B87: FUGA DE GAS NATURAL | D87: 45760 | E87: 50 MINUTOS | F87: CORREGIMIENTO SAN LUIS | G87: CORREGIMIENTO SAN LUIS | H87: SE LLAMA PARA REPORTAR FUGA DE GN EN VIVIENDA, LOS HABITANTES INDICAN QUE ABRIERON LA LLAVE DEL CONTADOR Y SE EMPEZÓ A SENTIR MUY FUERTE EL OLOR A GAS, SE DAN LAS INDICACIONES PERTINENTES Y SE ENVÍAN UNIDADES A VERIFICAR. AL LLEGAR AL SITIO SE HACE PROCESO DE VERIFICACIÓN SIN ENCONTRAR FUGA EN EL CONTADOR O EN ALGÚN LUGAR DE LA VIVIENDA (NI SITIOS CERCANOS). SE RECOMIENDA COMUNICARSE CON LA EMPRESA DE GAS PARA QUE HAGAN UN ANÁLISIS MÁS PROFUNDO Y SE DA RETIRO DEL SITIO PARA REGRESAR A LA INSTITUCIÓN. | I87: NA | J87: 2 | K87: B-2
A88: OTROS | B88: LABORES DE PREVENCION O ACOMPAÑAMIENTO EN GESTION DEL RIESGO | D88: 45760 | E88: 2.43 HORAS | F88: RECORRIDO DOMINGO DE RAMOS | G88: CALLES DEL MUNICIPIO | H88: ACOMPAÑAMIENTO EN ACTOS LITURGICOS DE LA IGLESIA SAN JOSE | I88: * | J88: 27 | K88: B-2, B-3, L-2
A89: FALSA ALARMA | B89: INCENDIO ESTRUCTURAL | D89: 45761 | E89: 35 MNTOS | F89: CRA 16 CALLE 19 | G89: PPULAR | H89: MENORES DE EDAD QUE SE ENCUENTRAN SOLOS EN UNA VIVIENDA,LOS CUALES PONEN A COCINAR ALIMENTOS, POR DESCUIDO SE QUEMAN PROVOCANDO GRAN CANTIDAD DE HUMO, ALERTANDO A LOS VECINOS | I89: * | J89: 3 | K89: B-2
A90: OTROS | B90: CAÍDA / CORTES DE ARBOL | D90: 45761 | E90: 3 HORAS | F90: SEGUNDO PASO | G90: PAJARO DE ORO | H90: ARBOL QUE CAE, EN EL CAUCE DE LA QUEBRADA OBSTACULIZANDO EL CAUCE | I90: * | J90: 4 | K90: B-3
A91: OTROS | B91: LABORES DE PREVENCION O ACOMPAÑAMIENTO EN GESTION DEL RIESGO | D91: 45764 | E91: 4 HORAS | F91: SONA URBANA | H91: ACOMPAÑAMIENTO PROCESION DE PRENDIMIENTO | I91: N/A | J91: 26 | K91: B-3, L-2
A92: OTROS | B92: LABORES DE PREVENCION O ACOMPAÑAMIENTO EN GESTION DEL RIESGO | D92: 45764 | E92: 2 HORAS | F92: ZONA URBANA | H92: ACOMPAÑAMIENTO SANTISIMO | I92: N/A | J92: 26 | K92: B-3, L-2
A93: MATERIALES PELIGROSOS | B93: FUGA DE GAS NATURAL | D93: 45765 | E93: 1 HORA | F93: CALLE 21 # 10A 19 | G93: LAS BRISAS | H93: FUGA DE GAS NATURAL | I93: N/A | J93: 5 | K93: B-2
A94: OTROS | B94: LABORES DE PREVENCION O ACOMPAÑAMIENTO EN GESTION DEL RIESGO | D94: 45765 | E94: 0.14583333 | F94: ZONA URBANA | H94: PROCESION DEL SANTO SEPULCRO | I94: N/A | J94: 23 | K94: B-2, B-3, L-2
A95: OTROS | B95: LABORES DE PREVENCION O ACOMPAÑAMIENTO EN GESTION DEL RIESGO | D95: 45765 | E95: 4.23 HORAS | F95: CALLES DEL MUNICIPIO | G95: MUNICIPIO | H95: ACOMPAÑAMIENTO EN SANTO VIA CRUCIS | I95: * | J95: 30 | K95: B-2, B-3, L-1, L-2
A96: OTROS | B96: LABORES DE PREVENCION O ACOMPAÑAMIENTO EN GESTION DEL RIESGO | D96: 45766 | E96: 1 HORA | F96: ZONA URBANA | H96: ACOMPAÑAMIENTO PROCESION DE LA SOLEDAD | I96: N/A | J96: 15 | K96: B-2, B-3, L-2
A97: OTROS | B97: LABORES DE PREVENCION O ACOMPAÑAMIENTO EN GESTION DEL RIESGO | D97: 45767 | E97: 3 HORAS | F97: ALCALDIA MUNICIPAL | H97: CUMPLEAÑOS DEL MUNICIPIO | I97: N/A | J97: 11 | K97: B-3
A98: OTROS | B98: LABORES DE PREVENCION O ACOMPAÑAMIENTO EN GESTION DEL RIESGO | D98: 45767 | E98: 2 H | F98: CALLE PRINCIPALES DEL MUNICIPIO | G98: CENTRO | H98: PROCESION DEL RESUCITADO | I98: NA | J98: 11 | K98: B-2, B-3
A99: OTROS | B99: CORTO CIRCUITO | D99: 45768 | E99: 30 MINUTOS | F99: CLL 16 3 288 | G99: LAS LAJAS | H99: INFORMAN DE UN POSTE QUE PRESENTA CORTO CIRCUITO | I99: . | J99: 4 | K99: B-2
A100: INCENDIOS | B100: INCENDIO VEHICULAR | D100: 45768 | E100: 1 HORA | F100: CALLE 14 # 6-01 CUERPO DE BOMBEROS | G100: LAS LAJAS | H100: VEHICULO DE BASURA QUE PRESENTA MUCHO HUMO EN LA PARTE TRACERA | I100: N/A | J100: 7 | K100: B-2
A101: MATERIALES PELIGROSOS | B101: MATERIALES PELIGROSOS / DERRAMES | D101: 45769 | E101: 2 HORAS | F101: CALLE 14 CRA 12 Y 13 | G101: BELEN , ZONA CENTRO | H101: PRODUCTO QUIMICO QUE SE DERAMA EN VIA PUBLICA, SUMINISTRAN INFORMACION DEL PRODUCTO, COMOCIDO COMO BLACK DIAMOND LIQUIDO, | I101: 160 MTS APROX | J101: 9 | K101: B-2, L-2
A102: INCENDIOS | B102: CORTO CIRCUITO | D102: 45770 | E102: UNA HORA | F102: VIA LA UNION - LA VICTORIA | G102: CORSEGA | H102: INFORMAN DE UN CABLE DE ALTA TENSION QUE CAE EN LA CARRETERA Y HACE CHISPAS | I102: . | J102: 6 | K102: B-3
A103: MATERIALES PELIGROSOS | B103: MATERIALES PELIGROSOS / DERRAMES | D103: 45771 | E103: 3 HORAS | F103: LAS CINTAS | G103: EL PICACHO | H103: INFORMAN UN DERRAME EN LA VIA LA UNION - LA VICTORIA Y YA SE CAYERON MOTOCICLISTAS | I103: . | J103: 11 | K103: B-2, B-3, L-1, L-2
A104: MAYO
A105: OTROS | B105: CONTROL DE AVISPAS | C105: =COUNTIF(B105:B127,C2) -> 1 | D105: 45778 | E105: 1 HORA | F105: TRASVERSAL 17 # 17-50 | H105: AVISTAS EN UNA CASA | I105: N/A | J105: 3 | K105: L-2
A106: OTROS | B106: LABORES DE PREVENCION O ACOMPAÑAMIENTO EN GESTION DEL RIESGO | D106: 45782 | E106: 49 MNTOS | F106: QUEBRADA LA UNION Y EL LUCERO | G106: EL LUCERO BAJO | H106: MONITOREO A LAS QUEBRADAS LA UNION Y EL LUCERO BAJO | I106: * | J106: 3 | K106: L-2
A107: OTROS | B107: LABORES DE PREVENCION O ACOMPAÑAMIENTO EN GESTION DEL RIESGO | D107: 45782 | E107: 1.49 HORAS | F107: QUEBRADA LA UNION -EL LUCERO | G107: EL LUCERO BAJO | H107: SE PRESTA APOYO OPERATIVO A PERSONA PARA RECUPERAR UNA MOTOCICLETA QUE FUE ARRASTRADA POR LA CRECIENTE DE LA QUEBRADA LA UNION | I107: * | J107: 5 | K107: B-3
A108: OTROS | B108: PRIMEROS AUXILIOS | D108: 45783 | E108: 1.26 HORAS | F108: VEREDA EL AJISAL | G108: VEREDA EL AJISAL | H108: SE PRESTA PRIMEROS AUXILIOS A PERSONA DE NACIONALIDAD EXTRANJERA ESPAÑOLA | I108: * | J108: 2 | K108: L-2
A109: OTROS | B109: LABORES DE PREVENCION O ACOMPAÑAMIENTO EN GESTION DEL RIESGO | D109: 45783 | E109: 1.33 HORAS | F109: SEGUNDO PASO EL TIGRE | G109: PAJARO DE ORO | H109: APOYO OPERATIVO EN PODA DE ARBOLES | I109: * | J109: 2 | K109: L-1
A110: OTROS | B110: CAÍDA / CORTES DE ARBOL | D110: 45784 | E110: 1 HORA | F110: VIA PANORAMA LA UNION --ROLDANILLO | G110: PORTACHUELO | H110: ARBOL UE CAE A LA VIA TAPONANDO MEDIO CARRIL | I110: * | J110: 4 | K110: B-3
A111: OTROS | B111: CAÍDA / CORTES DE ARBOL | D111: 45786 | E111: 6 HORAS | F111: EL TIGRE | G111: VEREDA EL TIGRE | H111: SE REALIZA CORTE DE ARBOL QUE HABIA CAIDO SOBRE LA QUEBRADA, APOYO A GESTION DE RIESGO | I111: . | J111: 4 | K111: L-1
A112: RESCATES | B112: RESCATE DE ANIMAL | D112: 45787 | E112: 49 MNTOS | F112: CRA15 19DN 19 63 | G112: LA CAMPESINA | H112: RECUPERACION DE SERPIENTE EN UNA VIVIENDA, SIN TENER RESULTADOS POSITIVOS | I112: * | J112: 2 | K112: L-2
A113: OTROS | B113: LABORES DE PREVENCION O ACOMPAÑAMIENTO EN GESTION DEL RIESGO | D113: 45787 | E113: 3 HORAS | F113: PARADOR GRAJALES | G113: VIA PANAORAMA KL 0.5 | H113: ACOMPAÑAMIENTO A LA COOPERATIVA COOTRAUNION | I113: * | J113: 5 | K113: L-2
A114: RESCATES | B114: CONTROL DE ABEJAS | D114: 45818 | E114: 2 HORAS | F114: EL PRADO | G114: EL PRADO | H114: VERIFICAR ABEJAS EN UNA VIVIENDA | I114: . | J114: 2 | K114: L-1
...

Sheet 2024
A1: TIPO DE INCIDENTE | B1: INCIDENTES Y ACTIVIDADES | C1: CANTIDAD DE | D1: DÍA DEL EVENTO | E1: DURACIÓN DEL EVENTO | F1: DIRECCIÓN O LUGAR DE REFERENCIA | G1: BARRIO CORREGIMIENTO O VEREDA | H1: DESCRIPCIÓN DEL EVENTO | I1: AREA AFECTADA (SOLO SI APLICA) | J1: N° DE UNIDADES QUE ASISTIERON | K1: VEHÍCULO | L1: COORDENADAS
C2: ='DETALLADO X MES 2026'!J2 -> INCENDIO FORESTAL
A3: ENERO
A4: OTROS | B4: FUGA DE GAS NATURAL | C4: =COUNTIF(B4:B49,$C$2) -> 15 | D4: 45295 | E4: UNA HORA Y TREINTA MINUTOS | F4: CAMPESINA PARTE BAJA | G4: LA CAMPESINA | H4: FUGA DE GAS POR RUTURA EN ESCABACION | I4: NO APLICA | J4: 3 | K4: B-4
A5: OTROS | B5: CONTROL DE ABEJAS | D5: 45295 | E5: UNA HORA | F5: CARRERA 15 CON CALLE | G5: CENTRO | H5: SE REALIZA RERCUPERACION DE ABEJAS EN EL ANDEN DEL BANCO DE DAVIVIENDA SON LIBERADAS POR LA BALASTRERA LLENDO PARA VERSALLES | I5: 0 | J5: 2 | K5: L-2
A6: FALSA ALARMA | B6: RESCATE DE PERSONA / PARAPENTE | D6: 45295 | E6: DOS HORAS | F6: VIA LA UNION LA VICTORIA | G6: LA ISLA | H6: INFORMAN DE UN PARAPENTE QUE PIERDE CONTROL SE PRESIPITA AL SUELO SE BUSCOO POR LOS LADOS DE LA SEGUNDA CANAL NO ENCONTRARON NADA | I6: 0 | J6: 3 | K6: L-2
A7: INCENDIOS | B7: INCENDIO FORESTAL | D7: 45296 | E7: CUARENTA MINUTOS | F7: CALLE 24 13 38 | G7: SAN PEDRO | H7: SE REALIZA LIQUIDACION DEL FUEGO A UN CONTROL DE QUE CONTROLADA QUE ESTABA AFETANDO LOS VECINOS CON EL HUMO | I7: 100 METROS CUADRADOS | J7: 3 | K7: B-4
A8: INCENDIOS | B8: INCENDIO FORESTAL | D8: 45297 | E8: MEDIA HORA | F8: PEDREGAL | G8: EL ESPINAL | H8: AL LLEGAR AL SITIO ES UNA QUEMA CONTROLADA A LA ORRILLA DE LA CANAL POR UN TRABAJOR DE LA FINCA | I8: 100 MTROS LINEALES | J8: 6 | K8: B-4, L-2
A9: INCENDIOS | B9: INCENDIO VEHICULAR | D9: 45296 | E9: TREINTA MINUTOS | F9: VIA LA UNION LA VICTORIA | G9: VIA LA UNION LA VICTORIA | H9: MOTOCICLETA INCENDIADA | I9: NO APLICA | J9: 4 | K9: B-4
A10: INCENDIOS | B10: INCENDIO FORESTAL | D10: 45299 | E10: VEINTE MINUTOS | F10: PARTE TRACERA EMPRESA GRAJALES | G10: LAS CINTAS | H10: QUEMA CONTROLADA | I10: NO APLICA | J10: 3 | K10: B-4
A11: INCENDIOS | B11: INCENDIO ESTRUCTURAL | D11: 45300 | E11: 0.052083333 | F11: CALLE 16 # 2-55 | G11: LAS LAJAS | H11: INCENDO COSINA FOGON DE LEÑA DEL RESTAURANTE EL SANCOCHASO | I11: N/A | J11: 8 | K11: B-4, L-2, L-3
A12: INCENDIOS | B12: INCENDIO FORESTAL | D12: 45300 | E12: TRES HORAS CON VEINTE MINUTOS | F12: MIRADOR DE LAS BRISAS | G12: MIRADOR DE LAS BRISAS | H12: MIRADOR DE LA BRISAS | I12: NO APLICA | J12: 7 | K12: B-1, B-4, L-2
A13: INCENDIOS | B13: INCENDIO FORESTAL | D13: 45300 | E13: TRES HORAS Y MEDIA | F13: FRENTE A LA URB LAS BRISAS | G13: LAS BRISAS | H13: SE REALIZA CONTROL DE INCENDIO DE MADERA DESTROZADA QUE HABIAN AMONTONADO DESE VARIOS DIAS ATRAS | I13: UNA PLAZA | J13: 12 | K13: B-1, B-3, B-4, L-2
A14: OTROS | B14: CONTROL DE ABEJAS | D14: 45300 | E14: MEDIA HORA | F14: CALLE 14 # 13 44 | G14: BELEN | H14: SE REALIZA CONTROL DE ABEJAS POR AFETACION A UNA VIVIENDA SIENDO CATURADAS Y LIBERADAS EN LAS AFUERA DEL MUNICIPIO | I14: 0 | J14: 2 | K14: L-2
A15: INCENDIOS | B15: INCENDIO FORESTAL | D15: 45301 | E15: VEINTE MINUTOS | F15: KR 10#7-27 | G15: EL GUASIMO | H15: QUEMA CONTROLADA POR EL DUEÑO DEL PREVIO | I15: NO APLICA | J15: 3 | K15: B-4
A16: RESCATES | B16: EXTRICACIÓN VEHICULAR | D16: 45301 | E16: DOS HORAS | F16: VIA TORO ANSERMANUEVO | G16: SANPACHO | H16: PERSONA ATRAPADA POR ACCIDENTE DE TRANSITO | I16: NO APLICA | J16: 4 | K16: L-2
A17: RESCATES | B17: RESCATE DE ANIMAL | D17: 45301 | E17: UNA HORA Y SEIS MINUTOS | F17: HOSPITAL GONZALO CONTRERAS | G17: SAN PEDRO | H17: RESCATE ANIMAL ATRAPADO EN EL AREA DE LAVANDERIA | I17: NO APLICA | J17: 3 | K17: L-2
A18: RESCATES | B18: CONTROL DE ABEJAS | D18: 45292 | E18: UNA HORA Y QUINCE MINUTOS | F18: MZ F CS 3 | G18: PRADOS DEL NORTE | H18: SE ENCUENTRA ENJAMBRE DE ABEJAS A LA ENTRADA DE UNA VIVIENDA | I18: VIVIENDA | J18: 4 | K18: B-4, L-2
A19: RESCATES | B19: CONTROL DE ABEJAS | D19: 45302 | E19: 2 HORAS | F19: SECTOR ESCOMBRERA | G19: GUASIMO | H19: ATAQUE DE ABEJAS, ENJAMBRE NO ENCONTRADO | I19: CASAS ALEDAÑAS | J19: 8 | K19: B-3, L-2
A20: RESCATES | B20: CONTROL DE ABEJAS | D20: 45302 | E20: DOS HORAS Y VEINTE MINUTOS | F20: CARRERA 10#3-122 | G20: EL GUASIMO | H20: ATAUE DE ABEJAS | I20: NO APLICA | J20: 8 | K20: B-3, L-2
A21: INCENDIOS | B21: INCENDIO FORESTAL | D21: 45302 | E21: UNA HORA Y 20 MINUTOS | F21: SECTOR LA ISLA | G21: LA ISLA | H21: QUEMA QUE SE SALE DE CONTROL | I21: 2 PLAZAS | J21: 5 | K21: B-4, L-2
A22: RESCATES | B22: CONTROL DE ABEJAS | D22: 45304 | E22: TRES HORAS | F22: SECTOR EL GUASIMO | G22: EL GUASIMO | H22: ATAQUE DE ABEJAS | I22: CARRETERA | J22: 5 | K22: B-3, L-2
A23: OTROS | B23: MATERIALES PELIGROSOS / DERRAMES | D23: 45305 | E23: 2 HORAS 20 MINUTOS | F23: SABANAZO | G23: SABANAZO | H23: CHOQUE DE DOS VEHICULOS CON DERRAME DE COMBUSTIBLE | I23: 0 | J23: 5 | K23: B-4, L-2
A24: OTROS | B24: CONTROL DE ABEJAS | D24: 45305 | E24: UNA HORA . | F24: CALL 15 # 12 48 | G24: CENTRO | H24: SE REALIZA CONTROL DE ABEJAS REALIZANDO CATURA Y LIBERANDOLAS A LAS AFUERAS DEL MUNICIPIO | I24: 0 | J24: 3 | K24: B-4
A25: RESCATES | B25: RESCATE DE PERSONA / PARAPENTE | D25: 45306 | E25: DOS HORAS Y MEDIA | F25: FINCA DE GUSTAVO RAMIREZ | G25: EL RINCON | H25: SE REALIZA RESCATE DE PERSONA DE SETENTA AÑOS QUE CAE DE UN PALO DE MANGO Y RUEDA APROXIMADAMNTE 6 METROS Y SE SACO HASTA LA CARRETERA DONDE LLEGAN LOS VEHICULOS EN CAMILLA Y SE TRASLADO EN LA AMBULANCIA DE SUDSALUD AL HOSPITAL GONZALO CONTRERAS | I25: 0 | J25: 5 | K25: L-1, L-2
A26: OTROS | B26: FUGA DE GAS NATURAL | D26: 45307 | E26: HORA Y MEDIA | F26: CALE 16 5 32 | G26: LAS LAJAS | H26: SE AHCE ACORDONAMIENTO Y PRENVENCIO HASTA QUE LLEGA EL TECNICO DE GASES DE OCCIDENTE PARA SU DEBIDO CONTROL | I26: 0 | J26: 3 | K26: B-4
A27: RESCATES | B27: RESCATE DE PERSONA / PARAPENTE | D27: 45306 | E27: 2.25 HORAS | F27: VEREDA EL RINCON | G27: VEREDA EL RINCON | H27: PERSONA QUE CAE DESDE UN ARBOL,RODANDO 6 MT APROX, SE RECIBE APOYO DEAMBULANCIA DE SUB SALUD | I27: * | J27: 5 | K27: L-2, OTROS
A28: OTROS | B28: SUMINISTROS DE AGUA | D28: 45308 | E28: DOS HORAS | F28: PARQUE DE SAN LUIS | G28: SAN LUIS | H28: SE RIEGA EL PRADO DE SAN LUIS POR EXEQUIA | I28: 0 | J28: 2 | K28: B-1
A29: INCENDIOS | B29: INCENDIO FORESTAL | D29: 45308 | E29: MEDIA HORA | F29: LA ESCOMBRERA | G29: GUASIMO | H29: AL LLEGAR AL SITIO SE OBSERBA A UN SEÑOR QUE ESTA QUEMANDO UN COBRE SE LE DAN RECOMENDACIONES Y SE REGRESA ALA CUARTEL | I29: 0 | J29: 3 | K29: B-4
A30: INCENDIOS | B30: INCENDIO FORESTAL | D30: 45309 | E30: 7 MIN | F30: PEDREGAL, CIA TORO - LA UNIÓN | H30: INCENDI FORESTAL QUE CONTROLA LA COMUNIDAD | I30: N/A | J30: 3 | K30: B-4
A31: INSPECCIONES DE SEGURIDAD | B31: LABORES DE PREVENCION O ACOMPAÑAMIENTO EN GESTION DEL RIESGO | D31: 45310 | E31: 1 HORA | F31: VEREDA MARTINDOZA | H31: INSPECCIONES POR MOVIMIENTO TELURICO | I31: N/A | J31: 2 | K31: L-2
A32: OTROS | B32: CONTROL DE ABEJAS | D32: 45310 | E32: UNA HORA | F32: KARRERA 9 VIA LAS PALMAS | G32: LAS PALAMAS | H32: ATAQE DE ABEJAS | I32: NO APLICA | J32: 5 | K32: L-2
A33: INSPECCIONES DE SEGURIDAD | B33: LABORES DE PREVENCION O ACOMPAÑAMIENTO EN GESTION DEL RIESGO | D33: 45310 | E33: UNA HORA CON TREINTA | F33: COLEGIO SANJOSE YIGLESIA SANJOSE | G33: CENTRO | H33: REVICION POR TEMBLOR | I33: NO APLICA | J33: 2 | K33: L-2
A34: INCENDIOS | B34: RESCATE DE PERSONA / PARAPENTE | D34: 45312 | E34: 0.10277778 | F34: VIA A SABANAZO POR LA CRUZ BLANCA | G34: SANPEDRO | H34: INCENDIO FORESTAL | I34: NO ESPECIFICA | J34: 7 | K34: B-1, B-4
A35: BUSQUEDA Y RESCATE | B35: RESCATE DE PERSONA / PARAPENTE | D35: 45313 | E35: CUATRO HORAS CON DIEZ MINUTOS | F35: BASE MILITAR LA FLORIDA TORO | G35: TORO VALLE | H35: APOYO RESCATE PARAPENTISTA EN TORO | I35: NO APLICA | J35: 5 | K35: L-2
A36: INCENDIOS | B36: INCENDIO FORESTAL | D36: 45313 | E36: UNA HORA | F36: INCENDIO FORESTAL VIA TORO | G36: PEDREGAL | H36: INCENDIO FORESTAL POR PEDREGAL | I36: 45323 | J36: 2 | K36: B-4
A37: OTROS | B37: CONTROL DE ABEJAS | D37: 45313 | E37: VEINTE MINUTOS | F37: DROGUERIA SUPER DROGAS EN LA CALLE 14 | G37: CENTRO | H37: ABEJAS EN LA PARTE EXTERNA DE LA DROGUERIA | I37: NO APLICA | J37: 4 | K37: B-3
A38: INCENDIOS | B38: INCENDIO FORESTAL | D38: 45314 | E38: DOS HORAS CON CINCO MINUTOS | F38: PAJARO DE ORO | G38: PAJARO DE ORO VIA EL TIGRE | H38: INCENDIO FORESTAL EN PAJARO DE ORO VIA EL TIGRE | I38: 500 MTS | J38: 6 | K38: L-1, L-2
A39: INCENDIOS | B39: INCENDIO FORESTAL | D39: 45314 | E39: VEINTIDOS MUNUTOS | F39: KR 19 CON CALLE 21 | G39: SANPEDRO | H39: QUEMA CONTROLADA | I39: NO ESPECIFICA | J39: 3 | K39: B-4
A40: INCENDIOS | B40: INCENDIO FORESTAL | D40: 45314 | E40: CUATRO HORAS CON VEINTE MINUTOS | F40: EL PICACHO | G40: VIA LA UNION ROLDANILLO | H40: QUEMA FORESTAL VIA LA UNION ROLDANILLO POR EL PICACHO | I40: 37.771 MTS | J40: 14 | K40: B-1, B-4, L-1, L-2
A41: MATERIALES PELIGROSOS | B41: FUGA DE GAS NATURAL | D41: 45315 | E41: UNA HORA | F41: MANZANA E CACA 24 | G41: BARRIO EL AMPARO | H41: FUGA DE GAS POR ROTURA EN ESCAVACION | I41: NO APLICA | J41: 4 | K41: B-4, L-2
A42: INSPECCIONES DE SEGURIDAD | B42: VISITAS DE SEGURIDAD | D42: 45315 | E42: UNA HORA Y DIEZ MINUTOS | F42: CALLE 14#13-82 | G42: BARRIO BELEN | H42: INSPECCION DE SEGURIDAD | I42: NO APLICA | J42: 1 | K42: L-3
A43: INCENDIOS | B43: INCENDIO FORESTAL | D43: 45318 | E43: CUATRO HORAS CON VEINTE MINUTOS | F43: CORCEGA | G43: CORCEGA | H43: QUEMA FORESTAL EN EL CORREGIMIENTO DE CORCEGA | I43: NO ESPECIFICA | J43: 6 | K43: B-1, B-4
A44: BUSQUEDA Y RESCATE | B44: RESCATE DE PERSONA / PARAPENTE | D44: 45319 | E44: UNA HORA QUINCE MINUTOS | F44: PAJARO DE ORO | G44: FINCA LAS MARGARITAS | H44: RESCATE PARAPENTISTA | I44: N/P | J44: 7 | K44: B-3, L-1
A45: INCENDIOS | B45: INCENDIO FORESTAL | D45: 45319 | E45: UNA HORA Y CINCOMINUTOS | F45: BARRIO LAS BRISAS LFRENTE DE LA GUARDERIA GRANDE | G45: LAS BRISAS | H45: QUEMA DE PASTIZAL EN LOTE | I45: NO ESPECIFICA | J45: 2 | K45: B-4
A46: INSPECCIONES DE SEGURIDAD | B46: VISITAS DE SEGURIDAD | D46: 45320 | E46: TRESHORAS | F46: CENTRO DE ACOPIO RECICLAJE Y COFI BAR | G46: LAS LAJAS | H46: INSPECCIONES DE SEGURIDAD | I46: N/P | J46: 1 | K46: L-3
A47: RESCATES | B47: RESCATE DE PERSONA / PARAPENTE | D47: 45320 | E47: UNA HORA | F47: ESTADIO MUNICIPAL | G47: LAS LAJAS | H47: RESCATE PARAPENTISTA EN EL ESTADIO | I47: N/P | J47: 3 | K47: L-2
A48: MATERIALES PELIGROSOS | B48: FUGA DE GAS NATURAL | D48: 45321 | E48: UNA HORA Y SIETE MINUTOS | F48: EL MATADERO MUNICIPAL | G48: LAS BRISAS | H48: FUGA DE GAS POR ROTURA DE TUBO | I48: N/P | J48: 6 | K48: B-4, L-2
A49: OTROS | B49: CONTROL DE ABEJAS | D49: 45322 | E49: 45 MINUTOS | F49: CR 9 VIA LAS PALMAS | G49: LAS PALMAS | H49: REUBICACION DE ABEJAS | I49: N/A | J49: 2 | K49: L-2
A50: FEBRERO
A51: INSPECCIONES DE SEGURIDAD | B51: VISITAS DE SEGURIDAD | C51: =COUNTIF(B51:B105,C2) -> 6 | D51: 45324 | E51: DOS HORAS CON VEINTE MINUTOS | F51: KR 13#13-80 | G51: BELEN | H51: INSPECCION DE SEGURIDAD | I51: N/P | J51: 1 | K51: L-3
A52: INSPECCIONES DE SEGURIDAD | B52: VISITAS DE SEGURIDAD | D52: 45324 | E52: UNA HORA QUINCE MUNUTOS | F52: CALLE 16# 5-45 | G52: LAS LAJAS | H52: INSPECCION DE SUGURIDAD | I52: N/P | J52: 1 | K52: L-3
A53: INSPECCIONES DE SEGURIDAD | B53: VISITAS DE SEGURIDAD | D53: 45324 | E53: UNA HORA | F53: KR 20# 18-48 | G53: EL JARDIN | H53: INSPECCION DE SEGURIDAD | I53: N/P | J53: 1 | K53: L-3
A54: RESCATES, OTROS | B54: CONTROL DE ABEJAS | D54: 45326 | E54: UNA HORA | F54: CALLE 23 20 88 | G54: SAN PEDRO | H54: SE REALIZA CATURA DE ABEJAS ETSABAN UN PALO Y ESTABAN PICANDO LA COMUNIDAD SE LIBERARON A LAS AFUERA DEL MUNICIPIO | I54: 0 | J54: 4 | K54: B-3
A55: OTROS | B55: CONTROL DE ABEJAS | D55: 45326 | E55: UNA HORA Y DIEZ MINUTOS | F55: CALLE 23#20-90 | G55: SAN PEDRO | H55: CONTROL DE ABEJAS | I55: N/P | J55: 3 | K55: B-3
A56: RESCATES | B56: RESCATE DE PERSONA / PARAPENTE | D56: 45327 | E56: 5 HORAS | F56: VIA SABANAZO | H56: VEHICULO QUE SE SALIO DE LA VIA | I56: N/A | J56: 13 | K56: B-3, B-4, L-1, L-2
A57: OTROS | B57: CAÍDA / CORTES DE ARBOL | D57: 45327 | E57: 1 HORA | F57: QUEBRADA PAJARO DE ORO | G57: PAJARO DE ORO | H57: ARBOL QUE CAE SOBRE EL CUSE DE LA QUEBRADA | I57: N/A | J57: 3 | K57: L-1
A58: RESCATES | B58: RESCATE DE PERSONA / PARAPENTE | D58: 45328 | E58: 30 MINUTOS | F58: CANCA DE EL CARMEN | G58: EL CARMEN | H58: PARAPENTE QUE ESTABA COLGADO DE UN ARBOL | I58: N/A | J58: 4 | K58: L-2
A59: OTROS | B59: LABORES DE PREVENCION O ACOMPAÑAMIENTO EN GESTION DEL RIESGO | D59: 45329 | E59: 2 HORAS | F59: QUEBRADAS | H59: REVICION DE CAIDA DE ARBOLES | I59: N/A | J59: 2 | K59: L-1
A60: INCENDIOS | B60: INCENDIO FORESTAL | D60: 45329 | E60: 2 HORAS | F60: LAS BRISAS | G60: LAS BRISAS | H60: INCENDIO QUE SE PRESENTA EN UNA CERCA AFETANDO DOS PREDIOS Y AMENZANDO UN CULTIVO DE GUAYABA SE LOGRA CONTROLAR EL INCENDIO | I60: 20 METROS DE CERCO EN SIGWLA | J60: 5 | K60: B-1, B-4
A61: INSPECCIONES DE SEGURIDAD | B61: VISITAS DE SEGURIDAD | D61: 45330 | E61: HORA TREINTA Y CINCO MINUTOS | F61: CL 18 # 15-73 | H61: VISITA DE SEGURIDAD | I61: N/A | J61: 1 | K61: L-3
A62: INSPECCIONES DE SEGURIDAD | B62: VISITAS DE SEGURIDAD | D62: 45330 | E62: HORA TREINTA Y CINCO MINUTOS | F62: CL 14 # 36-06 | H62: VISITA DE SEGURIDAD | I62: N/A | J62: 1 | K62: L-3
A63: OTROS | B63: CONTROL DE ABEJAS | D63: 45330 | E63: MEDIA HORA | F63: CALLE 25 # 15-12 | G63: SAN PEDRO | H63: AL LLEGAR AL SITIO VERIFICAN QUE SON ABEJAS PASAJERAS Y DEJAN RECOMENDACIONES MIENTRAS SE VAN | I63: 0 | J63: 3 | K63: L-2
A64: OTROS | B64: CONTROL DE ABEJAS | D64: 45331 | E64: 1 HORA | F64: CR 17 # 28-00 | G64: CAMPESINA ALTA | H64: ATAQUE DE ABEJAS | I64: N/A | J64: 8 | K64: B-3, L-2
A65: OTROS | B65: CONTROL DE ABEJAS | D65: 45332 | E65: UNA HORA | F65: PAN UVA | G65: VIA LA VICTORIA | H65: SE REALIZA CONTROL DE ABEJAS EN EL APRQUE NACIONAL DE LA UVA | I65: 0 | J65: 4 | K65: B-3
A66: OTROS | B66: CONTROL DE ABEJAS | D66: 45332 | E66: UNA HORA | F66: CALLE 22 CON CARR 24 | G66: SAN PEDRO | H66: SE REALIZA CONTROL DE ABEJAS | I66: 0 | J66: 4 | K66: B-3
A67: INCENDIOS | B67: INCENDIO FORESTAL | D67: 45332 | E67: 1 HORA | F67: PIMPOLLO | H67: INCENDIO FORESTAL EN LOTE VALDIO ALEDAÑO A PIMPOLLO | I67: 300 MT2 | J67: 2 | K67: B-4
A68: INSPECCIONES DE SEGURIDAD | B68: VISITAS DE SEGURIDAD | D68: 45334 | E68: UNA HORA Y CINCO MINUTOS | F68: CALLE 16#4-61 | G68: BARRIO LAS LAJAS | H68: INSPECCION DE SEGURIDAD | I68: N/P | J68: 1 | K68: L-3
A69: OTROS | B69: CONTROL DE ABEJAS | D69: 45331 | E69: UNA HORA | F69: PAN UVA | G69: VIA LA VICTORIA | H69: VERIFICACION DE ABEJAS | I69: 0 | J69: 3 | K69: L-2
A70: OTROS | B70: CONTROL DE ABEJAS | D70: 45335 | E70: HORA Y MEDIA | F70: CR 13 # 21 46 | G70: SAN PEDRO | H70: SE REALIZA CONTROL DE ABEJAS EN UN TERCER PISO | I70: 0 | J70: 3 | K70: B-4
A71: OTROS | B71: CONTROL DE ABEJAS | D71: 45335 | E71: HORA Y MEDIA | F71: VIA LA UNION TORO PEDREGAL | G71: EL ESPINAL | H71: SE REALIZA CONTROL DE ABEJAS EN VIVIENDA | I71: 0 | J71: 3 | K71: B-4
A72: OTROS | B72: LABORES DE PREVENCION O ACOMPAÑAMIENTO EN GESTION DEL RIESGO | D72: 45336 | E72: HORA Y MEDIA | F72: CARRERA 11 CON 8 | G72: EL PARAISO | H72: SE REALIZA ACORDONONAMIENTO DEL AREA POR CAIDA DE POSTE SONBRE UNA CAMIONETA MIENTRAS LLEGAN FUNCIONARIOS DE CELCIA | I72: 0 | J72: 5 | K72: B-4, L-2
A73: OTROS | B73: CONTROL DE ABEJAS | D73: 45337 | E73: UNA HORA | F73: CALLE 25# 15 12 | G73: SAN PEDRO | H73: SE REALIZA CONTROL DE ABEJAS HACIENDO CATURA Y SIENDO LIBERADAS EN LAS AFUERAS DEL MUNICIPIO | I73: 0 | J73: 2 | K73: B-4
A74: OTROS | B74: FUGA DE GAS NATURAL | D74: 45337 | E74: 50 MINUTOS | F74: CALLE 18 # 20 - 40 | G74: BELLAVISTA | H74: ROPTURA DE TUBO DEL GAS NATURAL POR TRABAJO DE CONSTRUCCIÓN EN EL LUGAR | I74: VIVIENDAS ALEDAÑAS | J74: 3 | K74: B-4
A75: INSPECCIONES DE SEGURIDAD | B75: VISITAS DE SEGURIDAD | D75: 45337 | E75: UNA HORA | F75: CALLE1#15-75 | G75: EL JARDIN | H75: INSPECCION DE SEGURIDAD | I75: N/P | J75: 1 | K75: L-1
A76: INSPECCIONES DE SEGURIDAD | B76: VISITAS DE SEGURIDAD | D76: 45337 | E76: UNA HORA | F76: CALLE 14#13-13 | G76: BELEN | H76: INSPECCION DE SEGURIDAD | I76: N/P | J76: 1 | K76: L-3
A77: OTROS | B77: CONTROL DE ABEJAS | D77: 45338 | E77: MEDIA HORA | F77: ENTRADA A LA VEREDA CORSEGA | G77: CORSEGA | H77: LA LLEGAR AL SITIO INFORMA EL SEÑOR DE LA FINCA QUE YA HABIAN EMIGRADO | I77: 0 | J77: 2 | K77: L-1
A78: OTROS | B78: RESCATE DE ANIMAL | D78: 45338 | E78: MEDIA HORA | F78: CALLE 14 # 12 10 | G78: BELEN | H78: SE REALIZA RECUPERACION DE UNA HIGUANA QUE SE ENCONTRABA DENTRO DE UNA VIVIENDA Y SE LIBERA EN LOS ARBOLES DE LA PARTE DE ATRAS DE LAS INSTALACIONES DE BOMBEROS | I78: 0 | J78: 3 | K78: L-1
A79: OTROS | B79: CONTROL DE ABEJAS | D79: 45339 | E79: MEDIA HORA | F79: CALLE 20 # 16 21 | G79: SAN PEDRO | H79: SEE REALIZA RECUPERACION DE UN PANAL DE ABEJAS QUE SE ENCONTRABA EN PATIO DE UNA CASA Y S ELIBERAN EN LAS AFUERAS DEL MUNICIPIO | I79: 0 | J79: 2 | K79: B-3
A80: OTROS | B80: LABORES DE PREVENCION O ACOMPAÑAMIENTO EN GESTION DEL RIESGO | D80: 45339 | E80: CUATRO HORAS | F80: VEREDA HOYO HONDO | G80: HOYO HONDO | H80: VERIFICACION Y RECOLECION DE DATOS Y FUENTES HIDRICAS PARA ABASTECIMIENTOS DE AGUA EN CASO DE EMERGENCIA Y VERIFICACION DE VIAS DE ZONA RURAL | I80: 0 | J80: 2 | K80: L-2
A81: OTROS | B81: CONTROL DE ABEJAS | D81: 45339 | E81: CUARENTE Y CINCO MINUTOS | F81: KR 18#17-22 | G81: EL JARDIN | H81: CONTROL DE ABEJAS | I81: N/P | J81: 4 | K81: B-3
A82: OTROS | B82: CONTROL DE ABEJAS | D82: 45339 | E82: CUARENTA MINUTOS | F82: KR 20#13-28 | G82: LA CRUZ | H82: CONTROL DE ABEJAS | I82: N/P | J82: 4 | K82: B-3
A83: INCENDIOS | B83: INCENDIO FORESTAL | D83: 45340 | E83: 30 MINUTOS | F83: CAMPESINA BAJA POR LA FINCA LOS CORRALES | G83: CAMPESINA | H83: SE RECIBE LLAMADA DEL PATRULLERO TASCON QUIEN INFORMA DE UNA QUEMA | I83: DESHECHOS | J83: 3 | K83: B-2
A84: OTROS | B84: CONTROL DE ABEJAS | D84: 45340 | E84: 6 HORAS | F84: CR 20 # 13-28 | G84: LA CRUZ | H84: ABEJAS DENTRO DE VIVIENDA | I84: N/A | J84: 3 | K84: B-2
A85: OTROS | B85: CONTROL DE ABEJAS | D85: 45341 | E85: 2 HORAS | F85: FINCA LOS CACHORROS | G85: CORCEGA | H85: CONTROL DE ABEJAS | I85: N/A | J85: 3 | K85: B-3
A86: INCENDIOS | B86: INCENDIO FORESTAL | D86: 45341 | E86: 41 MINUTOS | F86: VIA LA UNION SAN LUIS | G86: MARTINDOSA | H86: ARBOL QUE ESTABA PRENDIDO | I86: N/A | J86: 2 | K86: B-4
A87: MATERIALES PELIGROSOS | B87: FUGA DE GAS NATURAL | D87: 45342 | E87: UNA HORA | F87: KR 19#12-27 | G87: LA CRUZ | H87: FUGA DE GAS POR ESCAVACION | I87: N/P | J87: 4 | K87: B-2
A88: OTROS | B88: CONTROL DE ABEJAS | D88: 45342 | E88: CUARENTA MINUTOS | F88: EL PARDO M E CASA 5 Y 6 | G88: URB EL PRADO | H88: SE REALIZA CATURA Y LIBERACION EN LAS AFURERA DEL PUEBLO | I88: 0 | J88: 2 | K88: L-2
A89: INSPECCIONES DE SEGURIDAD | B89: VISITAS DE SEGURIDAD | D89: 45343 | E89: UNA HORA Y VEINTE MINUTOS | F89: FINCA LA BRASILERA | G89: MARTINDOZA | H89: INSPECCION DE SEGURIDAD | I89: N/P | J89: 1 | K89: L-3
A90: INSPECCIONES DE SEGURIDAD | B90: VISITAS DE SEGURIDAD | D90: 45343 | E90: UNA HORA | F90: SALSA MENTARIA LOS ATEÑOS | H90: INSPECCION DE SEGURIDAD | I90: N/P | J90: 1 | K90: L-3
A91: OTROS | B91: CONTROL DE ABEJAS | D91: 45344 | E91: 2 HORAS | F91: CASA CURAL | G91: SAN LUIS | H91: PANAL DE ABEJAS | I91: N/A | J91: 2 | K91: B-3
A92: OTROS | B92: CONTROL DE ABEJAS | D92: 45344 | E92: 40 MINUTOS | F92: CL 22 # 20-64 | H92: ABEJAS | I92: N/A | J92: 2 | K92: B-3
A93: RESCATES | B93: RESCATE DE ANIMAL | D93: 45345 | E93: 1 HORA | F93: CRR 12B # 8-14 | G93: CIUDADELA | H93: RESCATE DE UN FELINO | I93: N/A | J93: 2 | K93: B-4
A94: FALSA ALARMA | B94: INCENDIO FORESTAL | D94: 45345 | E94: 2 HORAS | F94: DESPENSA | H94: POSIBLE INCENDIO FORESTAL | I94: N/A | J94: 7 | K94: L-1, L-2
A95: INCENDIOS | B95: INCENDIO FORESTAL | D95: 45346 | E95: 1 HORA | F95: PAJARO DE ORO | H95: QUEMA QUE SE SALIO DE CONTROL | I95: 0.32 HECTAREAS | J95: 4 | K95: B-2, B-4
A96: OTROS | B96: CAÍDA / CORTES DE ARBOL | D96: 45347 | E96: 30 MINUTOS | F96: CALLE 14 # 18 - 30 | G96: LA CRUZ | H96: ARBOL DE MAMONCILLO QUE SE DESGAJA Y CAE SOBRE UN TECHO | I96: NO | J96: 2 | K96: L-2
A97: OTROS | B97: CONTROL DE ABEJAS | D97: 45347 | E97: 30 MINUTOS | F97: CARRERA 14 # 7A - 33 | G97: CIUDADELA | H97: ABEJAS DENTRO DE UNA VIVIENDA | I97: NO | J97: 2 | K97: L-2
A98: OTROS | B98: CONTROL DE ABEJAS | D98: 45348 | E98: DOS HORAS | F98: FINCA PRECEOS EN CERVALLE | G98: CORSEGA | H98: SE REALIZA CONTRO DE ABEJAS QU ESTABAN EN UN PALO DE MATARATON EN UN POTRERO | I98: NO | J98: 2 | K98: L-1
A99: INSPECCIONES DE SEGURIDAD | B99: VISITAS DE SEGURIDAD | D99: 45349 | E99: 1 HORA | F99: CL 13 # 14-11 | G99: EL AMPARO | H99: VISITA DE SEGURIDAD | I99: N/A | J99: 1 | K99: L-3
A100: INSPECCIONES DE SEGURIDAD | B100: VISITAS DE SEGURIDAD | D100: 45349 | E100: 1 HORA | F100: CR 15 # 11-44 | H100: VISITA DE SEGURIDAD | I100: N/A | J100: 1 | K100: L-3
...

Sheet 2023
A1: TIPO DE INCIDENTE | B1: INCIDENTES Y ACTIVIDADES | C1: CANTIDAD DE | D1: DÍA DEL EVENTO | E1: DURACIÓN DEL EVENTO | F1: DIRECCIÓN O LUGAR DE REFERENCIA | G1: BARRIO CORREGIMIENTO O VEREDA | H1: DESCRIPCIÓN DEL EVENTO | I1: N° DE UNIDADES QUE ASISTIERON | J1: VEHÍCULO | U1: COLAPSO DE ESTRUCTURAS | V1: COLAPSO DE TECHOS | W1: CAPACITACIONES | X1: DERRAME DE COMBUSTIBLE O ACEITES | Y1: ENTRENOS | Z1: FUGA DE GAS NATURAL | AA1: FUGA DE GAS GLP | AB1: INCENDIO FORESTAL | AC1: INCENDIO ESTRUCTURAL | AD1: INCENDIO VEHICULAR | AE1: INUNDACIÓN | AF1: LABORES DE PREVENCION | AG1: MATERIALES PELIGROSOS | AH1: PRIMEROS AUXILIOS | AI1: RESCATE DE PERSONA | AJ1: RECATE DE PARAPENTE | AK1: RESCATE DE ANIMAL | AL1: REUNIÓN EN LA ALCALDÍA | AM1: REUNIÓN DE CMGRD | AN1: REUNIÓN DE OFICIALES | AO1: REUNIONES DE SERVICIO SOCIAL | AP1: SUMINISTROS DE AGUA | AQ1: SUMINISTRO DE AGUA O LABORES COVID-19 | AR1: VISITAS DE ANÁLISIS DE RIESGOS | AS1: VISITAS DE SEGURIDAD
C2: ='DETALLADO X MES 2026'!J2 -> INCENDIO FORESTAL
A3: ENERO
A4: OTROS | B4: FUGA DE GAS NATURAL | C4: =COUNTIF(B4:B38,$C$2) -> 6 | D4: 44928 | E4: HORA Y VEINTE | F4: URB LAS PALMAS | G4: LAS PALMAS | H4: SE REALIZA CONTROL DE FUGA POR ROTURA DE TUBO EN ESCABACION | I4: 3 | J4: B-2
A5: INSPECCIONES DE SEGURIDAD | B5: VISITAS DE SEGURIDAD | D5: 44930 | E5: HORA Y MEDIA | F5: LATORRE BARBE SHOP | G5: EL JARDIN | H5: ANALICES DE RIESGO A ESTABLECIMIENTO | I5: 1 | J5: L-3
A6: INSPECCIONES DE SEGURIDAD | B6: VISITAS DE SEGURIDAD | D6: 44931 | E6: 1:30 MINUTOS | F6: CL 15 # 14-70 | G6: CENTRO | H6: VISITA DE SEGURIDAD | I6: 1 | J6: OTROS
A7: OTROS | B7: CONTROL DE ABEJAS | D7: 44932 | E7: HORA Y CUARTO | F7: CRR 15 VIA AL LUCERO | G7: EL LUCERO | H7: SE REALIZA RECUPERACION DE ABEJAS EN LA URBANIZACION MORADA DEL VIENTO | I7: 3 | J7: B-3
A8: RESCATES | B8: RESCATE DE PERSONA / PARAPENTE | D8: 44941 | E8: UNA HORA | F8: FINCA GRAJALES | G8: BARRIO LAS LAJAS | H8: PERSONA QUE CAE EN SU PARAPENTE | I8: 8 | J8: B-3, L-2
A9: INSPECCIONES DE SEGURIDAD | B9: VISITAS DE SEGURIDAD | D9: 44942 | E9: 1 HORA | F9: TIENDA D1 | G9: CENTRO | H9: INSPECCION DE SEGURIDAD POR SEGUNDA VEZ, VERIFICACION DE LOS REQUISITOS SOLICITADOS EN LA 1RA INSPECCION | I9: 1 | J9: OTROS
A10: RESCATES, OTROS | B10: CONTROL DE ABEJAS | D10: 18/01/0023 | E10: 40 MNTOS | F10: CRA 20 16-37 | G10: EL JARDIN | H10: VERIFICACION CONTROL ABEJAS | I10: 2 | J10: L-2
A11: OTROS | B11: CONTROL DE ABEJAS | D11: 44945 | E11: 29 MNTOS | F11: ZONA ROSA DISCOTK SEVEN | G11: CALLE 15 CRA 5 ESQ | H11: VERIFICACION ENJAMBRE DE ABEJAS | I11: 3 | J11: L-2
A12: INSPECCIONES DE SEGURIDAD | B12: VISITAS DE SEGURIDAD | D12: 44945 | E12: 1 HORA 30 MINUTOS | F12: COMERCIO DEL MUNICIPIO | H12: INSPECCION DE SEGURIDAD AL COMERCIO DEL MUNICIPIO | I12: 1 | J12: L-3
A13: INSPECCIONES DE SEGURIDAD | B13: VISITAS DE SEGURIDAD | D13: 44946 | E13: 2 HORAS | F13: COMERCIO DEL MUNICIPIO | H13: DOS INSPECCIONES DE SEGURIDAD AL COMERCIO DEL MUNICIPIO | I13: 1 | J13: L-2
A14: INCENDIOS | B14: INCENDIO FORESTAL | D14: 44946 | E14: 1 HORA 30 MINUTOS | F14: EL GUASIMO VIA SANTA ELENA | G14: SANTA ELENA | H14: INCENDIO EN RESIDUOS DE MATERA LATERAL A LA VIA, QUE GENERABA RIESGO DE PROPAGARSE POR LA LADERA | I14: 6 | J14: B-2, L-2
A15: OTROS | B15: CONTROL DE ABEJAS | D15: 44946 | E15: 29 MNTOS | F15: DISCOTEK SEVEN | G15: LAS LAJAS | H15: DESPLAZAMIENTO NO SE PUDO REALIZAR EL CONTROL | I15: 3 | J15: L-2
A16: INCENDIOS | B16: INCENDIO FORESTAL | D16: 44947 | E16: 1 HORA | F16: LUCERO ALTO | H16: QUEMA DE PASTIZAL Y SINGLA CON AFECTACION DE CULTIVO DE UVA | I16: 7 | J16: B-2, B-4
A17: OTROS | B17: CAÍDA / CORTES DE ARBOL | D17: 44948 | E17: 2.20HORAS | F17: VIA SABANAZO | G17: VIA SABANAZO | H17: RAMA DE UN ARBOL QUE ESTA SOBRE LA VIA | I17: 3 | J17: L-2
A18: OTROS | B18: CONTROL DE AVISPAS | D18: 44949 | E18: UNA HORA Y QUINCE MINUTOS | F18: CRR 16 9 43 | G18: CAMPO ALEGRE | H18: SE HACE RECUPERACION DE AVISPAS Y SE LIBERAN EN UN LUGAR FUERA DEL MUNICIPIO | I18: 3 | J18: B-2
A19: OTROS | B19: CONTROL DE ABEJAS | D19: 44949 | E19: DOS HORAS Y MEDIA | F19: MARTINDOZA | G19: MARTINDOZA | H19: SE REALIZA RECUPERACION DE LAS ABEJAS Y SE LLEVAN A LAS AFUERA DEL MUNICIPIO | I19: 2 | J19: L-2
A20: INSPECCIONES DE SEGURIDAD | B20: VISITAS DE SEGURIDAD | D20: 44950 | E20: 2 HORAS | F20: COMERCIO DEL MUNICIPIO | H20: 3 VISITAS DE ANALISI DE RIESGOS COMERCIO DEL MUNICIPIO | I20: 1 | J20: OTROS
A21: INSPECCIONES DE SEGURIDAD | B21: VISITAS DE SEGURIDAD | D21: 44950 | E21: 1.15 HORAS | F21: CALLE16 3-51 | G21: LAS LAJAS | H21: VISITA DE SEGURIDAD LICORES BAR EL CHAPO | I21: 1 | J21: L-1
A22: INSPECCIONES DE SEGURIDAD | B22: VISITAS DE SEGURIDAD | D22: 44950 | E22: 1 HORA | F22: CALLE 16 4-14 | G22: LAS LAJAS | H22: VISITA DE SEGURIDAD LICORES PUNTO CLAVE | I22: 1 | J22: L-1
A23: INSPECCIONES DE SEGURIDAD | B23: VISITAS DE SEGURIDAD | D23: 44950 | E23: 1 .20 HORAS | F23: CRA 3 14-13 | G23: LAS LAJAS | H23: VISITA DE SEGURIDAD ALMACEN AGRODISTRIBUIDORA EL CAMPO | I23: 1 | J23: L-1
A24: INSPECCIONES DE SEGURIDAD | B24: VISITAS DE SEGURIDAD | D24: 44951 | E24: 1 HORA | F24: CALLE 14 13 82 | G24: BELEN | H24: VISITA DE SEGURIDAD ALMACEN UNICELL | I24: 1 | J24: OTROS
A25: INSPECCIONES DE SEGURIDAD | B25: VISITAS DE SEGURIDAD | D25: 44951 | E25: 1.30HORAS | F25: CRA 15 19 154 | G25: BELEN | H25: VISITA DE SEGURIDAD TIENDA MEDICA LA UNION | I25: 1 | J25: OTROS
A26: INSPECCIONES DE SEGURIDAD | B26: VISITAS DE SEGURIDAD | D26: 44951 | E26: 1 HORA 30 MINUTOS | F26: COMERCIO DEL MUNICIPIO | H26: 2 INSPECCIONES DE SEGURIDAD Y ANALISIS DE RIESGOS AL COMERCIO | I26: 1 | J26: L-1
A27: INCENDIOS | B27: INCENDIO FORESTAL | D27: 44953 | E27: 30 MINUTOS | F27: CR 16 CON CALLE 2 FRENTE A LA ESTACION LAS LAJAS | H27: INCENDIO FORESTAL EN UN POTRERO | I27: 4 | J27: B-2
A28: INSPECCIONES DE SEGURIDAD | B28: VISITAS DE SEGURIDAD | D28: 44953 | E28: 1 HORA 30 MINUTOS | F28: SAN PEDRO | G28: SAN PEDRO | H28: VISITA DE SEGURIDAD | I28: 1 | J28: L-1
A29: RESCATES | B29: RESCATE DE PERSONA / PARAPENTE | D29: 44954 | E29: 30 MINUTOS | F29: POR EL CARMEN | G29: EL RINCON | H29: PARAPENTE QUE CAE AL SUELO PERO SALE POR SU PROPIOS MEDIOS | I29: 7 | J29: L-1, L-2
A30: INCENDIOS | B30: INCENDIO FORESTAL | D30: 44954 | E30: 2 HORAS | F30: TEJEDA | G30: TEJEDA | H30: INCENDIO RESIDUOS DE CAÑA | I30: 9 | J30: B-2, B-4, L-2
A31: INCENDIOS | B31: INCENDIO FORESTAL | D31: 44954 | E31: 1 HORA | F31: TEJEDA | G31: TEJEDA | H31: SE REATIVO EL INCENDIO | I31: 4 | J31: B-2
A32: INCENDIOS | B32: INCENDIO FORESTAL | D32: 44954 | E32: 1.37 HORAS | F32: BODEGAS DE EDUARDO JIMENEZ | G32: CORSEGA | H32: REFRIGERACION DE FOCOS DE UNA QUEMA DE DESECHOS AGRICOLAS CAÑA QUE SE REINICIAN NUEVAMENTE | I32: 4 | J32: B-2
A33: OTROS | B33: CONTROL DE AVISPAS | D33: 44955 | E33: 30 MNTOS | F33: CALLE 16 CRA 13 ESQ | G33: POPULAR | H33: DESPLAZAMIENTO AL SITIO A VERIFICAR | I33: 2 | J33: B-3
A34: OTROS | B34: FUGA DE GAS NATURAL | D34: 44956 | E34: MEDIA HORA | F34: CARRERA 15 # 22 72 | G34: SAN PEDRO | H34: AL LLEGAR AL SITIO SE ENCUENTRA ROTURA DE TUBO DE GAS NATURAL SE HACE PREVENCION MIENTRAS LLEGA EL FUNCIONARIO DE GASES DE OCCIDENTE | I34: 4 | J34: B-2
A35: OTROS | B35: CONTROL DE ABEJAS | D35: 44956 | E35: 2 HORAS | F35: COLEGIO ITDG | G35: URB EL AMPARO | H35: ENJAMBRE DE ABEJAS QUE LLEGA A UN ARBOL EN LA CANCHA DEL COLEGIO | I35: 3 | J35: L-2
A36: OTROS | B36: CONTROL DE ABEJAS | D36: 44956 | E36: 40 MNTOS | F36: CRA 14 6 01 | G36: BELEN | H36: TRASLADO DE ENJAMBRE QUE ESTABA EN LA ESTACION DE BOMBEROS AL SECTOR DE LA ISLA | I36: 3 | J36: L-2
A37: OTROS | B37: LABORES DE PREVENCION O ACOMPAÑAMIENTO EN GESTION DEL RIESGO | D37: 44937 | E37: 24 MNTOS | F37: LA CAMPESINA BAJA | G37: CAMPESINA BAJA | H37: MONOTOREO QUEBRADA SAN PEDRO SECTOR LA CAMPESINA | I37: 4 | J37: L-2
A38: OTROS | B38: LABORES DE PREVENCION O ACOMPAÑAMIENTO EN GESTION DEL RIESGO | D38: 44937 | E38: 20 MNTOS | F38: PUENTE CRA 15 | G38: LA CIUDADELA | H38: MONITOREO QUEBRADA LA UNION | I38: 4 | J38: L-2
A39: FEBRERO
A40: INSPECCIONES DE SEGURIDAD | B40: VISITAS DE SEGURIDAD | C40: =COUNTIF(B40:B99,$C$2) -> 4 | D40: 44958 | E40: 2.30 HORAS | F40: CRA 15 CALLE 17 ESQ | G40: POPULAR | H40: VISITA DE SEGURIDAD | I40: 1 | J40: L-1
A41: OTROS | B41: CONTROL DE ABEJAS | D41: 44959 | E41: CUATRO HORAS | F41: PORTACHUELO | G41: LA ISLA | H41: AUXILIO A PERSONA POR ATAQUE DE ABEJAS Y SE PROCEDE A VERIFICAR EL PANAL | I41: 5 | J41: L-2
A42: RESCATES | B42: RESCATE DE ANIMAL | D42: 44987 | E42: 1.06 HORAS | F42: SAN LUIS | G42: SAN LUIS | H42: RESCATE DE UN PATO QUE ESTABA ENREDADO EN UN COSTAL | I42: 3 | J42: L-2
A43: OTROS | B43: PRIMEROS AUXILIOS | D43: 44960 | E43: una hora | F43: via a sabanazo | G43: via a sabanazo | H43: persona que se sale de la via en moto siendo trasladado en la ambulancia de sudsalud al hospital gonzalo contreras | I43: 2 | J43: L-2
A44: INSPECCIONES DE SEGURIDAD | B44: VISITAS DE SEGURIDAD | D44: 44960 | E44: 1 HORA | F44: ZONA CENTRO | G44: CENTRO | H44: NO SE REALIZAN LAS VISITAS PROGRAMADAS POR FALTA DE DOCUMENTACION QUEDANDO PENDIENTE PARA EL DIA LUNES 6 DE FEBRERO | I44: 1 | J44: L-3
A45: MATERIALES PELIGROSOS | B45: FUGA DE GAS GLP | D45: 44960 | E45: 50MNTOS | F45: CR 18 9 10 PARQUE EL PRADO | G45: EL PRADO | H45: FUGA DE GAS GLP | I45: 4 | J45: B-2
A46: OTROS | B46: CONTROL DE ABEJAS | D46: 44962 | E46: 1 | F46: FRENTE A TIENDAS D1 | H46: CONTROL DE ABEJAS | I46: 3 | J46: L-2
A47: OTROS | B47: PRIMEROS AUXILIOS | D47: 44963 | E47: 50 MNTOS | F47: LA CENAGUETA | G47: MARTINDOZA | H47: SE LE PRESTAN PRIMEROS AUXILIOS A PERSONA QUE CAE DE UNA MOTOCICLETA | I47: 4 | J47: L-2
A48: RESCATES | B48: RESCATE DE ANIMAL | D48: 44963 | E48: 1 HORA 30 MINUTOS | F48: CRA 24 # 12-59 | G48: PASOANCHO | H48: SEMOVIENTE QUE CAE A UNA SANJA | I48: 3 | J48: B-2
A49: BUSQUEDA Y RESCATE | B49: RESCATE DE PERSONA / PARAPENTE | D49: 44963 | E49: 2.50 HORAS | F49: ZONA MONTAÑOSA DE SAN LIS | G49: SAN LUIS | H49: INFORMAN DE UN PARAPENTISTA QUE CAE EN LA ZONA ALTA DE SAN LUIS | I49: 7 | J49: L-1, L-2
A50: OTROS | B50: REUNIONES DE SERVICIO SOCIAL | D50: 44963 | E50: 3 HORAS | F50: CALLE 14 # 6-01 | H50: REUNION ADULTO MAYOR | I50: 39 | J50: N/A
A51: INCENDIOS | B51: INCENDIO FORESTAL | D51: 44963 | E51: 35 min | F51: CRA19 20 38 | G51: SAN PEDRO | H51: QUEMA DE PASTO, SELE SALE DE CONTROL AL PERSONAL QUE LA REALIZABA | I51: 4 | J51: B-2
A52: OTROS | B52: LABORES DE PREVENCION O ACOMPAÑAMIENTO EN GESTION DEL RIESGO | D52: 44964 | E52: 54 MNTOS | F52: SEGUNDO PASO QUEBRADA LA UNION | G52: PAJARO DE ORO | H52: SE REALIZA INSPECCION A UNA FUGA QUE HAY SOBRE EL CAUCE DE LA QUEBRADA, SE DETERMINA QUE ES UN TUBO DEL ACUEDUCTO D LA VEREDA PAJARO DE ORO | I52: 3 | J52: L-1
A53: INCENDIOS, INSPECCIONES DE SEGURIDAD | B53: VISITAS DE SEGURIDAD | D53: 44964 | E53: 1.20 HORAS | F53: CALLE 18 15 73 | G53: SECTOR GALERIA | H53: VISITA DE SEGURIDAD AL BAR LOS PINOS | I53: 1 | J53: L-1
A54: OTROS | B54: LABORES DE PREVENCION O ACOMPAÑAMIENTO EN GESTION DEL RIESGO | D54: 44964 | E54: 45 MNTOS | F54: CRA 16 25-137 | G54: LA CAMPESINA BAJA | H54: VERIFICACION DE UN ARBOL QUE CAE SOBRE EL CAUCE DE LA QUEBRADA, CAUSANDO DAÑOS EN UN CERCO DE PROPIEDAD DEL SEÑOR ALBERTO REYES | I54: 1 | J54: L-3
A55: OTROS | B55: REUNIONES DE SERVICIO SOCIAL | D55: 44964 | E55: 2 HORA 30 MINUTOS | F55: CLL 14 # 6-01 | H55: REUNION ADULTO MAYOR | I55: 39 | J55: N/A
A56: INSPECCIONES DE SEGURIDAD | B56: VISITAS DE SEGURIDAD | D56: 44964 | E56: 1 HORA 30 MINUTOS | F56: CALLE 18 CON CR 16 ESQUINA | H56: VISITA DE SEGURIDAD | I56: 1 | J56: L-3
A57: INSPECCIONES DE SEGURIDAD | B57: VISITAS DE SEGURIDAD | D57: 44964 | E57: 1 HORA 30 MINUTOS | F57: CLL 14 # 5-70 | H57: VISITA DE SEGURIDAD | I57: 1 | J57: N/A
A58: OTROS | B58: SUMINISTROS DE AGUA | D58: 44964 | E58: 1 HORA | F58: LA CAMPESINA | G58: LA CAMPESINA ALTA | H58: SUMINISTRO DE AGUA | I58: 2 | J58: B-4
A59: OTROS | B59: LABORES DE PREVENCION O ACOMPAÑAMIENTO EN GESTION DEL RIESGO | D59: 44964 | E59: 3 HORAS | F59: HIGUERON | H59: ACOMPAÑAMIENTO A UN PARTIDO DE FOOBALL | I59: 2 | J59: L-2
A60: INSPECCIONES DE SEGURIDAD | B60: VISITAS DE SEGURIDAD | D60: 44965 | E60: 1h y 20min | F60: CRA 14 13-22 | G60: ZONA CENTRO | H60: VISITA DE SEGURIDAD EN DROGUERIA AUDIFARMA | I60: 1 | J60: L-3
A61: OTROS | B61: CAÍDA / CORTES DE ARBOL | D61: 44966 | E61: 2.30 HORAS | F61: QUEBRADA LA UNION POR VILLA BETEL | G61: URB VILLA BETEL | H61: CORTE DE UN ARBOL QUE ESTA SOBRE EL CAUCE DE LA QUEBRADA LA UNION | I61: 2 | J61: L-1
A62: OTROS | B62: CAÍDA / CORTES DE ARBOL | D62: 44966 | E62: 2.30 HORAS | F62: QUEBRADA LA UNION CAMPESINA BAJA | G62: LA CAMPESINA BAJA | H62: CORTE DE UN ARBOL QUE ESTA SOBRE EL CAUCE DE LA QUEBRADA LA UNION SECTOR DE LA CAMPESINA BAJA | I62: 2 | J62: L-1
A63: INCENDIOS | B63: INCENDIO FORESTAL | D63: 44966 | E63: UNA HORA Y CUARENTA MINUTOS | F63: BARRIO LAS BRISAS FRENTE AL COLEGIO SANTA CLARA | G63: BARRIO LAS BRISAS | H63: QUEMA FORESTAL EN UN LOTE BALDIO | I63: 4 | J63: B-2
A64: OTROS | B64: CONTROL DE ABEJAS | D64: 44966 | E64: 15 MNTOS | F64: TRAS 13 8-77 | G64: LAS PALMAS VIA LAS CINTAS | H64: VERIFICACION ENJAMBRE DE ABEJAS | I64: 1 | J64: OTROS
A65: OTROS | B65: CONTROL DE ABEJAS | D65: 44967 | E65: 1.38 HORAS | F65: URB EL AMPARO,LAS PALMAS .EL CARMEN | G65: EL AMPARO ,LAS PALMAS ,EL CARMEN | H65: SE REALIZARON VISITAS EN LOS SITIOS DONDE ESTABAN LOS ENJAMBRES EL DIA 9/2/2023, | I65: 1 | J65: L-3
A66: INCENDIOS | B66: INCENDIO FORESTAL | D66: 44967 | E66: 4 HORAS | F66: HACIENDA LA CASTELLANA | G66: CORCEGA | H66: INCENDIO EN RESUDUO DE CAÑA QUE AFECTA 8 HECTAREAS Y SE PASA A UNA SUERTE DONDE SE AFECTAN 1/2 HECTAREA SE CONTROLA Y SE LIQUIDA | I66: 12 | J66: B-2, B-3, L-2, OTROS
A67: INCENDIOS | B67: INCENDIO FORESTAL | D67: 44968 | E67: 4h y 30min | F67: FINCA DIVISA - VIA SABANAZO | G67: SABANAZO | H67: QUEMA NO CONTROLADA DE COBERTURA VEGETAL- SE PIDE APOYO A BOMBEROS LA VICTORIA CON 6 UNIDADES Y 1 MAQUINA EXTINTORA | I67: 8 | J67: B-2, L-2
A68: OTROS | B68: CONTROL DE ABEJAS | D68: 1/12/0023 | E68: 50 MNTOS | F68: FINCA DE OVIDIO GRANADA | G68: CORSEGA 2DA CANAL | H68: CONTROL ABEJAS | I68: 2 | J68: L-2
A69: OTROS | B69: PRIMEROS AUXILIOS | D69: 44970 | E69: 1 HORA 30 MINUTOS | F69: ENTRE LA CR 11 Y 10 | H69: PERSONA QUE SE LASTIMA LA PARTE LUMBAR EN UN GINNACIO | I69: 4 | J69: L-2
A70: INSPECCIONES DE SEGURIDAD | B70: VISITAS DE SEGURIDAD | D70: 44970 | E70: UNA HORA | F70: CR 15 14 75 | G70: CENTRO | H70: SE REALIZA VISITA DE SEGURIDAD AL ESTABLECIMIENTO TIENDA ARA | I70: 1 | J70: L-3
A71: OTROS | B71: REUNIONES DE SERVICIO SOCIAL | D71: 44970 | E71: TRES HORAS Y VEINTE MINUTOS | F71: SALON # 3 CUERPO DE BOMBEROS | G71: LAS LAJAS | H71: REUNION DEL ADULTO MAYOR DE 35 PERSONAS | I71: 35 | J71: OTROS
A72: OTROS | B72: CONTROL DE ABEJAS | D72: 44971 | E72: 1.47 HORAS | F72: FINCA LEÑO VERDE | G72: VIA SAN LUIS --- TORO | H72: CONTROL DE AVEJAS EN LA FINCA LEÑO VERDE | I72: 4 | J72: B-3
A73: OTROS | B73: FUGA DE GAS NATURAL | D73: 44972 | E73: UNA HORA | F73: EL PAPAYAL | G73: SAN LUIS | H73: AL LLEGAR AL SITIO SE ENCUENTRAN CON ROTURA DE TUBERIA DE GAS POR ESCABACION SE PROCEDE HACER ACORDONAMIENMTO Y ESTEN LINEAS DE SEGURIADAD MIENTRAS LLEGA EL TECNICO Y SE LE HACE ENTRA DE LA ESCENA | I73: 6 | J73: B-2, L-2
A74: OTROS | B74: CORTO CIRCUITO | D74: 44972 | E74: UNA HORA | F74: CALLE 14 ENTRE 11 Y 12 | G74: BELEN | H74: CORTO CIRCUITO EN LA COMITIVA DE LA CASA SE HACE ACORDONAMIENTO Y CIEERE DE LA VIA HASTA QUE LLEGUE EL TECNICO DE CELCIA | I74: 3 | J74: B-2
A75: INSPECCIONES DE SEGURIDAD | B75: VISITAS DE SEGURIDAD | D75: 44973 | E75: UNA HORA | F75: BAR EL REY DEL DESPECHO | G75: GALERIA | H75: SE REALIZA VISTA DE SEGURIDAD AL ESTABLECIMIENTO | I75: 1 | J75: L-3
A76: INSPECCIONES DE SEGURIDAD | B76: VISITAS DE SEGURIDAD | D76: 44973 | E76: UNA HORA | F76: BAR EL DIAMANTE | G76: GALERIA | H76: SE REALIZA VISITA DE SEGURIDAD AL ESTABLECIMIENTO BAR EL DIAMANTE | I76: 1 | J76: L-3
A77: INSPECCIONES DE SEGURIDAD | B77: VISITAS DE SEGURIDAD | D77: 44973 | E77: UNA HORA | F77: VIEJOTECA BAR CARRETERO | G77: GALERIA | H77: SE RELAIZA VISTA DE SEGURIDA AL ESTABLECIMIENTO VIEJOTECA BAR CARRETERO | I77: 1 | J77: L-3
A78: INSPECCIONES DE SEGURIDAD | B78: VISITAS DE SEGURIDAD | D78: 44973 | E78: UNA HORA | F78: VIEJOTECA BAR CARRETEO | G78: GALERIA | H78: SE REALIZA VISITA DE SEGURIDAD AL ESTABLECIOMIENTO VIEJOTECA BAR CARRETERO | I78: 1 | J78: L-3
A79: INSPECCIONES DE SEGURIDAD | B79: VISITAS DE SEGURIDAD | D79: 44973 | E79: UNA HORA | F79: LA CANTALETA POPULAR | G79: GALERIA | H79: SE RELAIZA VISITA DE SEGURIDAD LA CANTAELTA POPULAR | I79: 1 | J79: L-3
A80: INSPECCIONES DE SEGURIDAD | B80: VISITAS DE SEGURIDAD | D80: 44973 | E80: UNA HORA | F80: GATO PARDO | G80: GALERIA | H80: SE REALIZA VISITA DE SEGURIDAD AL BAR GATO PARDO | I80: 1 | J80: L-3
A81: OTROS | B81: CAÍDA / CORTES DE ARBOL | D81: 44974 | E81: OCHO HORAS | F81: VEREDA VIOLETAS | G81: VIOLETAS | H81: SE HACE CORTE DE ARBOL POR AMENNAZA DE CAICA EN UNA VIVIENDA | I81: 4 | J81: B-3
... A83: OTROS | B83: CAÍDA / CORTES DE ARBOL | D83: 44977 | E83: 30 MNTOS | F83: VIA LA UNION LA VICTORIA | G83: CORCEGA | H83: RAMA DE UN ARBOL QUE ESTA QUEBRADA AMENAZANDO CON CAER SOBRE LA VIA PROVOCANDO UN POSIBLE ACCIDENTE | I83: 2 | J83: B-3
A84: OTROS | B84: REUNIONES DE SERVICIO SOCIAL | D84: 20/02/0232 | E84: 2 HORAS | F84: CALLE 14 6 01 CBV | G84: LAS LAJAS | H84: REUNION DEL GRUPO ADULTO MAYOR SIEMPRE UNIDO DE LA SEÑORA ROXANA AGUIRRE | I84: 24 | J84: OTROS
A85: OTROS | B85: LABORES DE PREVENCION O ACOMPAÑAMIENTO EN GESTION DEL RIESGO | D85: 44978 | E85: UNA HORA | F85: CASA CONCISTORIAL | G85: CENTRO | H85: SE HACE VERIFICACION DE ABEJAS EN LA CASA CONSISTORIAL EL CUAL REPORTAN DOS PANALES DE ABEJAS | I85: 2 | J85: L-1
A86: OTROS | B86: LABORES DE PREVENCION O ACOMPAÑAMIENTO EN GESTION DEL RIESGO | D86: 44978 | E86: UNA HORA | F86: VIA A LA PLANTA | G86: EL CARMEN | H86: SE REALIZA VERIFICACION DE ARBOL SECO QUE ESTA EN RIESGO EN UNA VIVIENDA | I86: 2 | J86: L-1
A87: OTROS | B87: REUNIONES DE SERVICIO SOCIAL | D87: 44978 | E87: 3.10 HORAS | F87: CALLE 14 6 01 CBV LA UNION | G87: LAS LAJAS | H87: REUNION DEL GRUPO DEL ADULTO MAYOR SEMILLAS DE AMOR | I87: 49 | J87: OTROS
A88: INSPECCIONES DE SEGURIDAD | B88: VISITAS DE SEGURIDAD | D88: 44978 | E88: 1.20 HORAS | F88: ESTANQUILLO LA 16 | G88: POPULAR | H88: SE RECOGE PLAN DE EMERGENCIA EN EL ESTANQUILLO LA 16 | I88: 1 | J88: L-3
A89: OTROS | B89: CONTROL DE ABEJAS | D89: 44978 | E89: 1.10 HORAS | F89: CASA CONSISTORIAL | G89: CENTRO | H89: SE COORDINA CON LA SEÑORA PATRICIA TAMAYO EL ALQUILER DE ANDAMIOS PARA REALIZAR LA UBICACION EXACTA DE UN ENJAMBRE DE ABEJAS | I89: 1 | J89: L-3
A90: OTROS | B90: CONTROL DE ABEJAS | D90: 44979 | E90: 7.26 HORAS | F90: FINCA EL TOPACIO | G90: EL MORAL | H90: SE REALIZA UN CONTROL DE ABEJAS EN EL CORREGIMIENTO EL MORAL | I90: 3 | J90: L-1
A91: OTROS | B91: CONTROL DE AVISPAS | D91: 44980 | E91: 3.40 HORAS | F91: CRA 15 CALLES 14 Y 15 CASA CONSISTORIAL | G91: CENTRO | H91: RECUPERACION DE COLMENA DE ABEJAS Y RETIRO DE ENJANDRE DE AVISPAS QUE ESTABA DE GRAN TAMAÑO EN UN ARBOL DE MANGO,PONIENDO EN RIESGO A LOS NIÑOS QUE PRACTICAN ACTIVIDADES EN EL SITIO | I91: 2 | J91: L-2
A92: OTROS | B92: CONTROL DE ABEJAS | D92: 44981 | E92: 42 MNTOS SIN TERMINAR | F92: BALASTRERA | G92: VIA LA UNION QUEBRADA GRANDE | H92: ATAQUE DE ABEJAS DEJANDO COMO SALDO DO PERSONAS PICADAS,QUEDANDO PENDIENTE PÓR CONCLUIR EL TRABAJO DE RECUPERACION DE LOS INSECTOS | I92: 6 | J92: B-3, L-2
A93: OTROS | B93: CONTROL DE ABEJAS | D93: 44981 | E93: DOS HORAS | F93: LA BALASTRERA | G93: GUASIMO | H93: SE REALIZA RECUPERACION DE UN EMJAMBRE DE ABEJAS Y SE LIBERAN EN EL GUASIMO | I93: 3 | J93: L-1
A94: OTROS | B94: CONTROL DE ABEJAS | D94: 44981 | E94: 2 HORAS | F94: VIA A QUEBRADA LA BALASTRERA | G94: VIA A QUEBRADA | H94: RECUPERACION DE ENJAMBRE DE ABEJAS,LAS CUALES ESTABAAN PENDIENTES DESDE LAS HORAS DE LA MAÑANA | I94: 3 | J94: L-1
A95: OTROS | B95: REUNIÓN EN LA ALCALDÍA | D95: 44984 | E95: 2.30 HORAS | F95: CASA DE LA CULTURA | G95: BELEN | H95: REUNION DE GESTION AMBIENTAL | I95: 1 | J95: OTROS
A96: OTROS | B96: REUNIONES DE SERVICIO SOCIAL | D96: 44984 | E96: 3 HORAS | F96: CALLE 14 # 6-01 | G96: LAS LAJAS | H96: REUNION GRUPO ADULTO MAYOR | I96: 27 | J96: N/A
A97: OTROS | B97: SUMINISTROS DE AGUA | D97: 44984 | E97: 1 HORA | F97: LA CAMPESINA | H97: SUMINISTRO DE AGUA | I97: 2 | J97: B-4
A98: OTROS | B98: CAÍDA / CORTES DE ARBOL | D98: 44985 | E98: 23 MNTOS | F98: CALLE14 CRA 9 ESQUINA | G98: LAS LAJAS | H98: CORTE DE UNA RAMA QUE SE DESGAJOPRESENTANDO RIESGO PARA LA COMUNIDAD | I98: 2 | J98: B-4
A99: OTROS | B99: CONTROL DE AVISPAS | D99: 44985 | E99: 30 MNTOS | F99: CRA 9 #16 12 | G99: LAS LAJAS | H99: SALEN A VERIFICAR ENJAMBRE DE ABEJAS | I99: 2 | J99: L-2
A100: MARZO
A101: INCENDIOS | B101: INCENDIO FORESTAL | C101: =COUNTIF(B101:B133,$C$2) -> 1 | D101: 44986 | E101: 1.20 HORAS | F101: EL GALLINERO DE TABARES | G101: CORCEGA | H101: QUEMA AGRICOLA QUE SE SALE DE CONTROL | I101: 5 | J101: B-2
...

Sheet 2022
A1: TIPO DE INCIDENTE | B1: INCIDENTES Y ACTIVIDADES | C1: CANTIDAD DE | D1: DÍA DEL EVENTO | E1: DURACIÓN DEL EVENTO | F1: DIRECCIÓN O LUGAR DE REFERENCIA | G1: BARRIO CORREGIMIENTO O VEREDA | H1: DESCRIPCIÓN DEL EVENTO | I1: N° DE UNIDADES QUE ASISTIERON | J1: VEHÍCULO
C2: ='DETALLADO X MES 2026'!J2 -> INCENDIO FORESTAL
A3: ENERO
A4: INCENDIOS | B4: INCENDIO ESTRUCTURAL | C4: =COUNTIF(B4:B22,C2) -> 3 | D4: 44567 | E4: 1 | F4: CLL 13 | G4: V | H4: Simulación | I4: 1 | J4: M-1
A5: OTROS | B5: CONTROL DE AVISPAS | D5: 08/01/0022 | E5: 2 H | F5: PARQUE PRINCIPAL | G5: CENTRO | H5: CONTROL DE AVISPAS | I5: 5 | J5: M-2, M-3
A6: RESCATES | B6: RESCATE DE ANIMAL | D6: 44571 | E6: 30 minutos | F6: GALERIA EN EL ALMACEN EL VAQUERO | H6: GATO QUE SE ENCUENTRA EN UN TEJADO | I6: 3 | J6: M-2
A7: RESCATES | B7: RESCATE DE ANIMAL | D7: 44572 | E7: 30 MINUTOS | F7: GALERIA - ALMACEN EL VAQUERO | H7: GATO EN UN TEJADO PERO POR SE MUR ARISCO NO SE DEJO COJER | I7: 2 | J7: M-2
A8: INCENDIOS | B8: INCENDIO FORESTAL | D8: 44577 | E8: 1 H | F8: SANTAELENA | H8: INFORMAN LA PRESENCIA DE FOCOS DE INCENDIOS EN LA MONTAÑA | I8: 6 | J8: M-2
A9: MATERIALES PELIGROSOS | B9: FUGA DE GAS NATURAL | D9: 44583 | E9: UNA HORA | F9: CALLE 13 # 20-198 | G9: LA CRUZ | H9: FUGA DE GAS EN VIA PUBLICA | I9: 3 | J9: M-2
A10: OTROS | B10: CONTROL DE AVISPAS | D10: 44586 | E10: 5 H | F10: PARQUE PRINCIPAL | H10: CONTROL DE AVISPAS | I10: 6 | J10: M-3, M-6
A11: OTROS | B11: CAÍDA / CORTES DE ARBOL | D11: 44590 | E11: 4 H | F11: VIA LA VICTORIA | H11: CORTE DE ARBOL | I11: 5 | J11: M-2, M-6
A12: INCENDIOS | B12: INCENDIO FORESTAL | D12: 44591 | E12: 1 H | F12: VIA SABANAZO A LA ALTURA DE LA BALASTRERA | H12: INCENDIO A CAUSA DE LA QUEMA DE BASURAS | I12: 4 | J12: M-2
A13: OTROS | B13: CAÍDA / CORTES DE ARBOL | D13: 44592 | E13: CUARENTA MINUTOS | F13: FRENTE AL PARQUEADERO LAS LAJAS | G13: LAS LAJAS | H13: RAMA DE ARBOL QUE CAE SOBRE LA VIA PUBLICA ENTRADA AL MUNICIPIO | I13: 2 | J13: M-4
A14: OTROS | B14: PRIMEROS AUXILIOS | D14: 44570 | E14: 3 HORAS | F14: VIA SABANAZO | H14: MOTOCICLISTAQUE SE SALIO DE LA VIA | I14: 11 | J14: M-3, M-5
A15: RESCATES, OTROS | B15: RESCATE DE PERSONA / PARAPENTE | D15: 44580 | E15: 1 HORA | F15: FINCA LAS CAMELIAS | G15: PAJARO DE ORO | H15: PARAPENTE QUE QUEDO ATRAPADO EN UN ARBOL | I15: 11 | J15: M-3, M-4
A16: INSPECCIONES DE SEGURIDAD | B16: VISITAS DE SEGURIDAD | D16: 44580 | E16: 2 HORAS | F16: ESTANQUILLO JJ | H16: VISITA DE SEGURIDAD | I16: 2 | J16: M-4
A17: INSPECCIONES DE SEGURIDAD | B17: VISITAS DE SEGURIDAD | D17: 44580 | E17: 2 HORAS | F17: ESTANQUILLO LA 16 | H17: VISITA DE SEGURIDAD | I17: 2 | J17: M-4
A18: BUSQUEDA Y RESCATE | B18: RESCATE DE PERSONA / PARAPENTE | D18: 44582 | E18: 1 HORA | F18: SANTA ELENA | G18: HIGUERONCITO | H18: RESCATE DE PARAPENTE EN LA PARTE ALTA DE LA MONTAÑA | I18: 8 | J18: M-3, M-4
A19: INCENDIOS | B19: LABORES DE PREVENCION O ACOMPAÑAMIENTO EN GESTION DEL RIESGO | D19: 44588 | E19: 1 HORA | F19: SANTA ELENA | G19: HIGUERONCITO | H19: SALE UNA CUADRILLA PARA VERIFICAR-- DE DEVUELVEN POR QUE SE EXTINGUIO SOLO | I19: 5 | J19: M-4
A20: INCENDIOS | B20: INCENDIO FORESTAL | D20: 44592 | E20: 1 HORA | F20: VIA SABANAZO | H20: QUEMA DE UN BASURERO QUE FUE CONTROLADO Y LIQUIDADO | I20: 4 | J20: M-2
A21: OTROS | B21: CAÍDA / CORTES DE ARBOL | D21: 44592 | E21: 40 MINUTOS | F21: CALLE 16 ENTRADA AL MUNICIPIO | H21: RAMA QUE CAE A LA VIA OSTACULIZA EL PASO VEHICULAR | I21: 2 | J21: M-4
A22: INSPECCIONES DE SEGURIDAD | B22: VISITAS DE SEGURIDAD | D22: 44576 | E22: 3 H | F22: AUDIFARMA SAS CR 14 # 13 - 22 | H22: VISITA DE SEGURIDAD | I22: 1 | J22: M-6
A23: FEBRERO
A24: MATERIALES PELIGROSOS | B24: MATERIALES PELIGROSOS / DERRAMES | C24: =COUNTIF(B24:B54,C2) -> 3 | D24: 44594 | E24: 30 MINUTOS | F24: CALLE 14 CON CARRERA 13 | G24: BELEN | H24: REGUERO DE COMBUSTIBLE EN LA VIA PUBLICA | I24: 6 | J24: M-3
A25: INCENDIOS | B25: INCENDIO FORESTAL | D25: 44595 | E25: MEDIA HORA | F25: CALL 18 # 12 09 | G25: URBANIZACION TRAS ANDINA | H25: QUE MA DE PASTIZAL EN LOTE VALDIO | I25: 5 | J25: M-2
A26: INCENDIOS | B26: INCENDIO FORESTAL | D26: 44596 | E26: UNA HORA | F26: SOBRE LA PANORAMA PASANDO EL PUENTE DE SAN LUIS | G26: CORREGIMIENTO DE SAN LUIS | H26: INCENDIO EN UN LOTE ESTABAN ASIENDO QUEMA CONTROLADA AFETANDO LAS VIENDAS CON EL HUMO | I26: 6 | J26: M-2
A27: OTROS | B27: INUNDACIÓN | D27: 44597 | E27: 30 minutos | F27: calle 13 # 8-33 | H27: vivienda inundad | I27: 3 | J27: M-2
A28: BUSQUEDA Y RESCATE | B28: RESCATE DE ANIMAL | D28: 44599 | E28: 30 MIN | F28: CLL 19 # 17 - 84 | H28: Se recibe llamado solicitando ayuda para la recuperacion de una zarigeya atrapada en el baño de una vivienda. | I28: 3 | J28: M-2
A29: INCENDIOS | B29: INCENDIO FORESTAL | D29: 44604 | E29: DOS HORAS Y MEDIA | F29: EL LUCERO | G29: FINCA EL PLACER | H29: QUEMA CONTROLADA QUE SE SALIO DEL CONTROL | I29: 6 | J29: M-2, M-4
A30: INSPECCIONES DE SEGURIDAD | B30: VISITAS DE SEGURIDAD | D30: 44600 | E30: 1 H | F30: DROGUERIA AUDIFARMA | H30: VISITA DE SEGURIDAD | I30: 1 | J30: M-4
A31: INSPECCIONES DE SEGURIDAD | B31: VISITAS DE SEGURIDAD | D31: 44600 | E31: 1 H | F31: MEGA HOGAR | H31: VISITA DE SEGURIDAD | I31: 2 | J31: M-4
A32: INSPECCIONES DE SEGURIDAD | B32: VISITAS DE SEGURIDAD | D32: 44603 | E32: 5 H | F32: STAY HIGH | H32: VISITA DE SEGURIDAD | I32: 1 | J32: M-6
A33: INSPECCIONES DE SEGURIDAD | B33: VISITAS DE SEGURIDAD | D33: 11/02/0003 | E33: 5 H | F33: CASA SHOW LOS CRISTALES | H33: VISITA DE SEGURIDAD | I33: 1 | J33: M-6
A34: INSPECCIONES DE SEGURIDAD | B34: VISITAS DE SEGURIDAD | D34: 44603 | E34: 5 H | F34: ESTANQUILLO LOS COCHOSOS PLAZA | H34: VISITA DE SEGURIDAD | I34: 1 | J34: M-6
A35: INSPECCIONES DE SEGURIDAD | B35: VISITAS DE SEGURIDAD | D35: 44599 | E35: 2 H | F35: REMATES KANUTO | H35: VISITAS DE SEGURIDAD | I35: 1 | J35: M-6
A36: INSPECCIONES DE SEGURIDAD | B36: VISITAS DE SEGURIDAD | D36: 44599 | E36: 2 H | F36: BANCO AGRARIO | H36: VISITA DE SEGURIDAD | I36: 1 | J36: M-6
A37: INSPECCIONES DE SEGURIDAD | B37: VISITAS DE SEGURIDAD | D37: 44607 | E37: 3 H | F37: COOPSER CRA 13 # 13 - 24 | H37: VISITA DE SEGURIDAD | I37: 1 | J37: M-6
A38: INSPECCIONES DE SEGURIDAD | B38: VISITAS DE SEGURIDAD | D38: 44607 | E38: 3 H | F38: CIC LABORATORIO CRA 12 # 13 - 34 | H38: VISITA DE SEGURIDAD | I38: 1 | J38: M-6
A39: INSPECCIONES DE SEGURIDAD | B39: VISITAS DE SEGURIDAD | D39: 44607 | E39: 3 H | F39: TIENDA MIXTA LICORES DEL VALLE CLL 18 #15 - 50 | H39: VISITA DE SEGURDAD | I39: 1 | J39: M-6
A40: RESCATES | B40: RESCATE DE ANIMAL | D40: 44608 | E40: 2 HORAS | F40: PARQUE PRINCIPAL | G40: PARQUE PRINCIPAL | H40: ANIMAL QUE SE ENCUENTRA EN LUGAR PUBLICO EL CUAL FUE CAPTURADO Y REHUBICADO EN SU HABITAD | I40: 4 | J40: M-3
A41: MATERIALES PELIGROSOS | B41: FUGA DE GAS NATURAL | D41: 44614 | E41: DOS HORAS Y VEINTE MINUTOS | F41: CALLE 12# 20-220 | G41: PASOANCHO | H41: FUGA DE GAS POR ESCABACION DONDE SE HACE PRENVENCION HASTA QUE LOS TECNICOS HAGAN SU REPARACION | I41: 5 | J41: M-2
A42: RESCATES | B42: RESCATE DE PERSONA / PARAPENTE | D42: 44595 | E42: 0 | F42: ZONA MONTAÑOSA DE LA CANCHA BARRIO EL CARMEN | H42: REPORTAN CAIDA DE PARAPENTE, SE SUSPENDE LA SALIDA PUES NO ES NECESARIO EL RESCATE, E INFORMAN QUE LA PERSONA FALLECIO CON EL IMPACTO. | I42: 1 | J42: N/A
A43: INSPECCIONES DE SEGURIDAD | B43: VISITAS DE SEGURIDAD | D43: 44595 | E43: 2 H | F43: DISTRIBUIDORA F Y C CLL 18 # 15 - 17 | H43: VISITA DE SEGURIDAD | I43: 1 | J43: M-6
A44: INSPECCIONES DE SEGURIDAD | B44: VISITAS DE SEGURIDAD | D44: 44595 | E44: 2 H | F44: TIENDA BELEN CLL 11 # 12 - 06 | H44: VISITA DE SEGURIDAD | I44: 1 | J44: M-6
A45: RESCATES | B45: RESCATE DE ANIMAL | D45: 44601 | E45: 1H | F45: CLL 14 # 12 - 25 | H45: SE RECIBE INFORMACION SOBRE UN FELINO QUE NO PUEDE BAJAR DEL TECHO DE UNA VIVIENDA, DEBIDO AL DIFICIL ACCESO SE SUSPENDEN LABORES Y NO SE PROCEDE A BAJAR AL ANIMAL | I45: 5 | J45: M-2
A46: INSPECCIONES DE SEGURIDAD | B46: VISITAS DE SEGURIDAD | D46: 44606 | E46: 3 H | F46: TIENDAS ARA | H46: VISITA DE SEGURIDAD | I46: 1 | J46: M-6
A47: INSPECCIONES DE SEGURIDAD | B47: VISITAS DE SEGURIDAD | D47: 44606 | E47: 3 H | F47: COBA COLOMBIA SAS | H47: VISITA DE SEGURIDAD | I47: 1 | J47: M-6
A48: INSPECCIONES DE SEGURIDAD | B48: VISITAS DE SEGURIDAD | D48: 44606 | E48: 3 H | F48: JORDANELLY PIZZA | H48: VISITA DE SEGURIDAD | I48: 1 | J48: M-6
A49: RESCATES | B49: VISITAS DE SEGURIDAD | D49: 44607 | E49: 1 H | F49: CRA 14 # 13 - 50 | H49: FELINO ATRAPADO AL CUAL SE DESPACHA PERSONAL PARA EL RESCATE XITOSO DEL MISMO | I49: 2 | J49: M-2
A50: OTROS | B50: CONTROL DE ABEJAS | D50: 44610 | E50: 3 H | F50: FINCA VILLA CRUCITA | H50: SE REALIZA CONTROL DE ABEJAS EN EL SITIO | I50: 3 | J50: M-4
A51: RESCATES | B51: RESCATE DE PERSONA / PARAPENTE | D51: 44612 | E51: 3 H | F51: VIA TORO - PEAJE | H51: SOLICITA BOMBEROS TORO APOYO CON EXTRICACION VEHICULAR, PARA RECUPERAR LOS CUERPOS DE 2 PERSONAS ATRAPADAS DENTRO DEL VEHICULO DEL ACCIDENTE EN EL CUAL FALLECEN 5 PERSONAS | I51: 11 | J51: M-3, M-5
A52: OTROS | B52: REUNIÓN EN LA ALCALDÍA | D52: 44614 | E52: 2 H | F52: ALCALDIA DE LA UNION VALLE | H52: REUNION | I52: 1 | J52: OTROS
A53: OTROS | B53: CONTROL DE ABEJAS | D53: 44615 | E53: 1 H | F53: ESCUELA SAN MARTIN | H53: VERIFICACION DE ABEJAS | I53: 2 | J53: M-4
A54: OTROS | B54: LABORES DE PREVENCION O ACOMPAÑAMIENTO EN GESTION DEL RIESGO | D54: 44616 | E54: 1 H | F54: CRA 16 # 15 - 55 | H54: REPORTAN LA CAIDA DE UN TECHO Y LA CAIDA DE UNAS CUERDAS, A LO QUE SE DESPACHA PERSONAL PARA EL SITIO, AL NO PRESENTAR MAYOR RIESGO SE ACORDONA EL AREA Y SE PROCEDE A REGRESAR A LA INSTITUCION | I54: 3 | J54: M-2
A55: MARZO
A56: INCENDIOS | B56: FUGA DE GAS NATURAL | C56: =COUNTIF(B56:B87,C2) -> 1 | D56: 44627 | E56: 30 MINUTOS | F56: CALLE 23 # 15-60 | G56: PARQUE SAN PEDRO | H56: FUGA DE GAS NATURAL RUPTURA DE TUBERIA POR ESCAVACION | I56: 2 | J56: M-2
A57: INCENDIOS | B57: INCENDIO FORESTAL | D57: 44636 | E57: dos horas y 40 minutos | F57: finca el mirador | G57: las palmas | H57: incendio forestal en pasto y rastrojo se que una plaza aproxiamda mente | I57: 7 | J57: M-2, M-3
A58: RESCATES | B58: RESCATE DE ANIMAL | D58: 44636 | E58: hora y venticinco minutos | F58: lagos los samanes | G58: san luis | H58: llegua que se va a la canal siendo rescatada con vida | I58: 6 | J58: M-3, M-4
A59: OTROS | B59: CONTROL DE ABEJAS | D59: 44636 | E59: una hora | F59: frente a la estacion de policia | G59: centro | H59: se hace catura de las abejas y se liberan a las afuera del municipio | I59: 4 | J59: M-5
A60: INCENDIOS | B60: INCENDIO ESTRUCTURAL | D60: 44635 | E60: UNA HORA CON VEINTE MINUTOS | F60: HODSPITAL GONZALO CONTRERAS | G60: SAN PEDRO SECTOR GALERIA | H60: INFORMAN DE UN INCENDIO EN LA PARTE DE ATRAS DEL HOSPITAL LOCAL POR LA SALA DE ESTERILIZACION Y SALA DE PARTOS | I60: 9 | J60: M-1, M-2
A61: RESCATES | B61: RESCATE DE ANIMAL | D61: 44635 | E61: 19.06 A 20.31 | F61: LAGOS DE PESCA LOS SAMANES | G61: VIA LA UNION TORO | H61: SEMOVIENTE QUE CAE A LA CANAL DE RIEGO POR EL SECTOR DEL RODEO.POR LOS LAGOS DE PESCA LOS SAMANES | I61: 4 | J61: M-3
A62: OTROS | B62: INUNDACIÓN | D62: 44637 | E62: 04.28 HASTA 06.20 | F62: SE ATIENDEN VARIOS LLAMADOS DE LA COMUNIDAD POR REBOSAMIENTO DE LA RED DE ALCANTARILLADODE LAS VIAS PUBLICAS | G62: CRA 21 SECTOR DE LA CRUZ | H62: INUNDACIONES DE VIVIENDAS POR REBOSAMIENTO DE LA RED DEL ALCANTARILLADO | I62: 3 | J62: M-2
A63: OTROS | B63: CONTROL DE ABEJAS | D63: 44643 | E63: UNA HORA | F63: CALLE 21 # 17-19 | G63: SAN PEDRO | H63: CONTROL DE ABEJAS EN COCINA | I63: 2 | J63: M-3
A64: OTROS | B64: INUNDACIÓN | D64: 44648 | E64: 30 MINUTOS | F64: CRA 16 # 19-159 | G64: SAN PEDRO | H64: VIVIENDA QUE SUFRE REPRESAMIENTO DE AGUA LLUVIA EN EL PATIO GENERANDO INUNDACION EN LA VIVIENDA | I64: 3 | J64: M-5
A65: INSPECCIONES DE SEGURIDAD | B65: VISITAS DE SEGURIDAD | D65: 44622 | E65: 3 HORAS | F65: OPTICA CRISTIAN DIOR | H65: INSPECCION DE SEGURIDAD HUMANA Y CONTRA INCENDIOS A ESTABLECIEMIENTO COMERCIAL | I65: 1 | J65: M-6
A66: INSPECCIONES DE SEGURIDAD | B66: VISITAS DE SEGURIDAD | D66: 44624 | E66: 1 HORA 30 MINUTOS | F66: CIRCO COKIS | H66: INSPECCION DE SEGURIDA HUMANA Y CONTRA INCENDIOS A ESTABLECIMIENTO PUBLICO | I66: 1 | J66: M-6
A67: INSPECCIONES DE SEGURIDAD | B67: VISITAS DE SEGURIDAD | D67: 44624 | E67: 1 HORA | F67: GIORDANELLY PIZZA | H67: INSPECCION DE SEGURIDAD HUMANA Y CONTRA INCENDIOS ESTABLECIMIENTO COMECIAL | I67: 1 | J67: M-6
A68: OTROS | B68: LABORES DE PREVENCION O ACOMPAÑAMIENTO EN GESTION DEL RIESGO | D68: 44625 | E68: 3 HORAS | F68: RIO CAUCA | G68: LINDEROS, EL BANCO, CORSEGA Y LA CALLETANA | H68: MONITOREO DEL CAUSE DEL RIO POR CRESIENTE | I68: 4 | J68: M-3
A69: BUSQUEDA Y RESCATE | B69: RESCATE DE ANIMAL | D69: 44628 | E69: 3 HORAS | F69: VEREDA EL TIGRE | H69: RESCATE DE SEMOVIENTE QUE CAE A UN BARRANCO Y ES ATACADO POR ABEJAS LAS CUALES CAUSAN SU DESESO Y SE PROCEDE A RETIRAR DELSITIO AL TERNERO PARA SU ENTREGA A LOS DUEÑOS | I69: 5 | J69: M-3
A70: OTROS | B70: INUNDACIÓN | D70: 44627 | E70: 4 HORAS | F70: VEREDA CORSEGA | H70: REVISION Y APOYO REHUBICACION DE FAMILIA INUNDADA EN LA RIVERA DEL RIO CAUCA | I70: 7 | J70: M-3, M-4
A71: OTROS | B71: INUNDACIÓN | D71: 44648 | E71: 1 HORA | F71: CARRERA 16 # 19-159 | H71: INUNDACION EN VIVIENDA POR OBSTRUCCION DE TUBERIA DE AGUAS LLUVIAS | I71: 3 | J71: M-5
A72: RESCATES | B72: RESCATE DE PERSONA / PARAPENTE | D72: 44651 | E72: 1 HORA | F72: ESTADIO MUNICIPAL | H72: RESCATE DE EQUIPO DE PARAPENTE DE AEROMODELISMO QUE QUEDA ATRAPADO EN UNA RAMA DE UN ARBOL | I72: 2 | J72: M-2
A73: INCENDIOS | B73: CORTO CIRCUITO | D73: 44647 | E73: 1 HORA | F73: SAN LUIS DETRAS DE LA IGLESIA | H73: CORTO E INCENDIO EN CONTADOR ZONA RURAL DETRAS DE LA IGLESIA DE SAN LUIS | I73: 2 | J73: OTROS
A74: OTROS | B74: CONTROL DE ABEJAS | D74: 44631 | E74: MEDIA HORA | F74: FINCA EL PAPAYAL | G74: SAN LUIS | H74: NO SE REALIZO CONTROL ACORDARON CON LA DUEÑA DEL PREDIO REGRESAR AL OTRO DIA HACER CONTROL | I74: 3 | J74: M-3
A75: OTROS | B75: LABORES DE PREVENCION O ACOMPAÑAMIENTO EN GESTION DEL RIESGO | D75: 44628 | E75: 5 H | F75: RIVERA DEL RIOCAUCA | H75: SALEN UNDADES A REALIZAR CENSO A LOS HABITANDES AFECTADOS, UBICADOS A LAS RIVERAS DEL RIO CAUCA | I75: 5 | J75: M-4
A76: RESCATES | B76: RESCATE DE PERSONA / PARAPENTE | D76: 44634 | E76: 2 H | F76: SEGUNDA CANAL DE RIEGO | H76: INFORMAN DE ACCIDENTE DE TRANSITO EL CUAL CAE UNA PERSONA A LA CANAL DE RIEGO A LO QUE SE DESPACHA PERSONAL PARA SU RESCATE | I76: 4 | J76: M-3
A77: INCENDIOS | B77: INCENDIO ESTRUCTURAL | D77: 44635 | E77: 2 H | F77: HOSPITAL MUNICIPAL | H77: INFORMAN DE INCENDIO EN EL HOSPITAL GONZALO CONTRERAS A LO QUE SE DESPACHA PERSONAL | I77: 11 | J77: M-1, M-2
A78: OTROS | B78: CAÍDA DE CUERDAS | D78: 44640 | E78: 30 MIN | F78: PANADERIA PAN TOLIMA | H78: REPORTAN CAIDA DE CUERDA, SE DESPACHA PERSONAL, VERIFICANDO LA SITUACION SE OBSERVA QUE ES UNA CUERDA DE TELEFONIA Y QUE NO REPRESENTA MAYOR RIESGO | I78: 2 | J78: M-2
A79: OTROS | B79: CAÍDA / CORTES DE ARBOL | D79: 44643 | E79: 2 H | F79: VEREDA EL BANCO | G79: VEREDA EL BANCO | H79: REPORTAN CAIDA DE UN ARBOL QUE OBSTACULIZ LA VIA | I79: 5 | J79: M-2
A80: OTROS | B80: CAPACITACIONES | D80: 44645 | E80: 1 H 30 MIN | F80: GUARDERIA PRINCIPAL | H80: CAPACITACION | I80: 1 | J80: M-6
A81: OTROS | B81: FUGA DE GAS NATURAL | D81: 44645 | E81: 2 H | F81: CLL 14 # 3 - 12 | H81: FUGA DE GAS EN UN ESTABLECIMIENTO COMERCIAL | I81: 3 | J81: M-2
A82: OTROS | B82: INUNDACIÓN | D82: 44647 | E82: 30 MIN | F82: VIVIENDA CERCA A LA ESTACION DE SERVICIO TRASANDINA | H82: VIVIENDA INUDADA | I82: 3 | J82: M-2
A83: OTROS | B83: INUNDACIÓN | D83: 44647 | E83: 2 H | F83: URBANIZACION EL AMPARO | H83: INFORMAN DE VIVIENDAS AFECTADAS EN LA URBANIZACION | I83: 2 | J83: M-2
A84: OTROS | B84: INUNDACIÓN | D84: 44647 | E84: 1 H | F84: CLL 12 CEDE NORTE | H84: INUNDACION | I84: 3 | J84: M-2
A85: OTROS | B85: CORTO CIRCUITO | D85: 44647 | E85: 30 MIN | F85: SAN LUIS | H85: INCENDIO EN ACOMETIDA POR CORTO CIRCUITO, AL LLEGAR AL SITIO SE VERIFICA SITUACION Y SE OBSERVA QUE YA ESTA CONTROLADO, SE INFORMA A CELCIA | I85: 5 | J85: OTROS
A86: RESCATES | B86: RESCATE DE PERSONA / PARAPENTE | D86: 44647 | E86: 1 H 30 MIN | F86: EL RODEO VIA TORO | H86: INFORMAN DE VEHICULO CON PERSONAS ADENTRO ARRASTRADO POR LAS FUERTES CORRIENTES DE ESCORRENTIAS | I86: 7 | J86: M-2
A87: OTROS | B87: INUNDACIÓN | D87: 44647 | E87: 40 MIN | F87: VEREDA MARINDOZA | G87: VEREDA MARINDOZA | H87: VIVIENDA INUNDAD POR LA CRECIENTE SUBITA DEL CANAL DE RIEGO A CAUSA DE LAS FUERTES LLUVIAS Y EL AUMENTO DEL NIVEL DEL RIO CAUCA | I87: 4 | J87: M-4
A88: ABRIL
A89: OTROS | B89: FUGA DE GAS NATURAL | C89: =COUNTIF(B89:B128,C2) -> 0 | D89: 44655 | E89: TRES HORAS | F89: SABANAZO | G89: VEREDA SABANAZO | H89: SE PRESENTA FUGA DE GAS POR OBREROS EN LA VIA PUBLICA QUE ROPEN TUBO SE REALIZO PRENSADO Y ACOMAPAÑAMIENTO HASTA QUE ELÑ TECNICO REPARO EL DAÑO | I89: 4 | J89: M-2
A90: OTROS | B90: CONTROL DE AVISPAS | D90: 44656 | E90: HORA Y VEINTE MINUTOS | F90: CR 9# 9 49 | G90: BELEN | H90: SE HACE RECUPERACION DE UNAS AVSIPAS QUE SE ENCONTRABAN EN UN BAÑO SE LIBERARON LLENDO PARA SANTA ELENA | I90: 3 | J90: M-5
A91: OTROS | B91: LABORES DE PREVENCION O ACOMPAÑAMIENTO EN GESTION DEL RIESGO | D91: 44656 | E91: DOS HORAS | F91: CENTRO | G91: CENTRO | H91: SE HACE ACOMPAÑAMIENTO DESFILE DE CARROZAS CELEBRACION A LOS SESENTA Y CINCO AÑOS DEL COLEGIO ARGEMIRO ESCOBAR CARDONA | I91: 4 | J91: M-5
A92: OTROS | B92: CAÍDA / CORTES DE ARBOL | D92: 44657 | E92: 1 HORA | F92: VIA LA UNION LA VICTORIA | H92: CORTE, RETIRO Y DESPEJE DE ARBOL QUE CAE SOBRE LA VIA LA UNION - LA VICTORIA A LA ALTURA DE LA ESCUELA SAN RAFAEL | I92: 3 | J92: M-2
A93: OTROS | B93: CAÍDA / CORTES DE ARBOL | D93: 44657 | E93: 3 HORAS Y MEDIA | F93: VEREDA EL BANCO | H93: CORTE DE ARBOL PROGRAMADO QUE SE ENCONTRABA OBSTACULIZANDO EL PASO A LA ZONA DE LA VEREDA EL BANCO | I93: 2 | J93: M-4
A94: INSPECCIONES DE SEGURIDAD | B94: VISITAS DE SEGURIDAD | D94: 44660 | E94: 3 HORAS | F94: CENTRO NATURISTA CASA VERDE, FUNDACION DE LA MUJER, PAPELERIA PAPERMANIA, CASINO EL TESORO | G94: ESTABLECIMEITOS COMERCIALES | H94: CUATRO 4 INSPECIONES DE SEGURIDAD A ESTABLECIMIENTOS COMERCIALES | I94: 1 | J94: M-3
A95: OTROS | B95: SUMINISTROS DE AGUA | D95: 44663 | E95: 4 HORAS | F95: PARQUE PRINCIPAL | G95: CENTRO | H95: LAVADO DE PARQUE PRINCIPÁL | I95: 8 | J95: M-1, M-3, M-4
A96: OTROS | B96: LABORES DE PREVENCION O ACOMPAÑAMIENTO EN GESTION DEL RIESGO | D96: 44663 | E96: 4 H 30 MIN | F96: PARQUE PRINCIPAL | H96: LAVADO DEL PARQUE | I96: 8 | J96: M-1, M-5, OTROS
A97: OTROS | B97: LABORES DE PREVENCION O ACOMPAÑAMIENTO EN GESTION DEL RIESGO | D97: 44666 | E97: CINCO HORAS | F97: RONBOY AL PARQUE | G97: LAS LAJAS AL CENTRO | H97: PROCESION SANTO VIACRUCIS | I97: 14 | J97: M-2, M-3
A98: OTROS | B98: LABORES DE PREVENCION O ACOMPAÑAMIENTO EN GESTION DEL RIESGO | D98: 44665 | E98: 3 H | F98: PARQUE PRINCIPAL | H98: PROCESION DE EMPRENDIMIENTO Y PRESTADA DE GUARDIA | I98: 14 | J98: M-2, M-3, M-5
A99: INSPECCIONES DE SEGURIDAD | B99: VISITAS DE SEGURIDAD | D99: 44664 | E99: 2 H | F99: PASAJE BELEN | H99: VISITA DE SEGURIDAD | I99: 1 | J99: M-6
A100: INSPECCIONES DE SEGURIDAD | B100: VISITAS DE SEGURIDAD | D100: 44666 | E100: 2 H | F100: FOTOGRAFIA EMILY SAS | H100: VISITA DE SEGURIDAD | I100: 1 | J100: M-6
...

Sheet 2021
A1: TIPO DE INCIDENTE | B1: INCIDENTES Y ACTIVIDADES | C1: CANTIDAD DE | D1: DÍA DEL EVENTO | E1: DURACIÓN DEL EVENTO | F1: DIRECCIÓN O LUGAR DE REFERENCIA | G1: BARRIO CORREGIMIENTO O VEREDA | H1: DESCRIPCIÓN DEL EVENTO | I1: N° DE UNIDADES QUE ASISTIERON | J1: VEHÍCULO
C2: ='DETALLADO X MES 2026'!J2 -> INCENDIO FORESTAL
A3: ENERO
A4: OTROS | B4: LABORES DE PREVENCION O ACOMPAÑAMIENTO EN GESTION DEL RIESGO | C4: =COUNTIF(B4:B27,C2) -> 4 | D4: 44197 | E4: 48 MINUTOS | F4: CALLE 13 #20-08 | G4: LA CRUZ | H4: SE LE COLABORA AL SEÑOR EVER HUMBERTO GOMEZ PARA ABRIR UNA PUERTA YA QUE QUE SE LE PARTIERON LAS LLAVES Y HUBO QUE ENTRAR POR LA PARTE DEL SEGUNDO PISO | I4: 2 | J4: M-2
A5: OTROS | B5: INUNDACIÓN | D5: 44197 | E5: 1 HORA 33 MINUTOS | F5: CALLE 12 A #23A 04 | G5: PASOANCHO | H5: SE PRESTA EL AUXULIO DE LAVADO EN LA CASA DE LA SEÑORA MARCELA MONSALVE VELASQUEZ YA QUE POR FUERTE AGUACERO HUBO REVOSE DE LAS ALCANTARILLAS | I5: 3 | J5: M-2
A6: INSPECCIONES DE SEGURIDAD | B6: VISITAS DE SEGURIDAD | D6: 44200 | E6: 1 HORA | F6: CENTRO | H6: SE HACE INSPECION EL ALMACEN F Y O NUTRICION CELULAR DEL VALLE | I6: 1 | J6: M-6
A7: INSPECCIONES DE SEGURIDAD | B7: VISITAS DE SEGURIDAD | D7: 44202 | E7: DOS HORAS | F7: PARQUE PRINCIPAL | H7: INSPECION DE SEGURIDAD | I7: 1 | J7: M-6
A8: INSPECCIONES DE SEGURIDAD | B8: VISITAS DE SEGURIDAD | D8: 44202 | E8: 1 HORA 10 MINUTOS | F8: CENTRO | H8: SE HACE INSPECION EN EL ESTABLECIMIENTO COFINCAFE | I8: 1 | J8: M-6
A9: INSPECCIONES DE SEGURIDAD | B9: VISITAS DE SEGURIDAD | D9: 44202 | E9: 1 HORA 10 MIUTOS | F9: CENTRO | H9: SE HACE INSPECION EN EL PIQUETEADERO MILLAN | I9: 1 | J9: M-6
A10: INSPECCIONES DE SEGURIDAD | B10: VISITAS DE SEGURIDAD | D10: 44203 | E10: DOS HORAS | F10: CENTRO | H10: VISITA DE SEGURIDAD | I10: 1 | J10: M-6
A11: OTROS | B11: LABORES DE PREVENCION O ACOMPAÑAMIENTO EN GESTION DEL RIESGO | D11: 44203 | E11: DOS HORS CON CUARENTA Y CINCO | F11: PARQUE PRINCIPAL LA UNION VALLE | G11: PARQUE PRINCIPAL | H11: PREVENCION CON TRANSITO Y CONVIVENCIA CIUDADANA SOBRE USO DE TAPABOCAS | I11: 1 | J11: OTROS
A12: OTROS | B12: LABORES DE PREVENCION O ACOMPAÑAMIENTO EN GESTION DEL RIESGO | D12: 44204 | E12: DOS HORAS CON TREINTA MINUTOS | F12: PARQUE PRINCIPAL | H12: PREVENCION SOBRE COVID 19 | I12: 1 | J12: M-6
A13: OTROS | B13: LABORES DE PREVENCION O ACOMPAÑAMIENTO EN GESTION DEL RIESGO | D13: 44204 | E13: 2 HORAS | F13: CENTRO | H13: SE HACE ACOMPAÑAMIENTO EN LAVORES DE PREVENCION COVID CON LA ALCALDIA EN EL PARQUE | I13: 1 | J13: OTROS
A14: INSPECCIONES DE SEGURIDAD | B14: VISITAS DE SEGURIDAD | D14: 44208 | E14: 2 horas | F14: FINCA LA ISABELA | G14: KL 1 VIA SAN LUIS | H14: VISITA DE SEGURIDAD | I14: 1 | J14: M-6
A15: INSPECCIONES DE SEGURIDAD | B15: VISITAS DE SEGURIDAD | D15: 44208 | E15: 2 HORAS | F15: KOBA COLOMBIA SAS | G15: KL 1 VIA LA UNION SANLUIS | H15: VISITA DE SEGURIDAD | I15: 1 | J15: M-6
A16: INSPECCIONES DE SEGURIDAD | B16: VISITAS DE SEGURIDAD | D16: 44208 | E16: 30 MINUTOS | F16: ALMACEN RANA | G16: CLL 16 CON CR 7 | H16: VISITA DE SEGURIDAD | I16: 1 | J16: M-6
A17: INCENDIOS | B17: INCENDIO FORESTAL | D17: 44209 | E17: 2 HORAS | F17: FINCA LA LLAVE AMARILLA | G17: CAMPESINA BAJA | H17: INCENDIO FORESTAL | I17: 7 | J17: M-2, M-3
A18: MATERIALES PELIGROSOS | B18: FUGA DE GAS NATURAL | D18: 44210 | E18: 1 HORA | F18: CRA 12 CON CALLE 16 | G18: POPULAR | H18: SE PRESENTA FUGA DE GAS NATURAL POR TRABAJOS EN LA VIA ,SE HACE LAVORES DE PREVENCION MIENTRAS LLEGA EL TECNICO DE GASES DE OCCIDENTE | I18: 6 | J18: M-2
A19: MATERIALES PELIGROSOS | B19: FUGA DE GAS NATURAL | D19: 44210 | E19: 1 HORA | F19: URBANIZACION PRADOS DEL NORTE | G19: PRADOS DEL NORTE | H19: SE HACEN LAVORES DE PREVENCION EN EL SITIO MIENTRAS LLEGABA EL TECNICO DE GASES DE OCCIDENTE ROPTURA PRESENTADA POR TRABAJOS EN LA VIA | I19: 6 | J19: M-2, M-3
A20: INSPECCIONES DE SEGURIDAD | B20: VISITAS DE SEGURIDAD | D20: 44210 | E20: 1 HORA | F20: AUDIFARMA | H20: VISITA DE SEGURIDAD | I20: 1 | J20: M-6
A21: INCENDIOS | B21: INCENDIO FORESTAL | D21: 44211 | E21: 2 HORAS | F21: FINCAS LAS MARIAS | G21: CAMPESINA BAJA | H21: INCENDIO FORESTAL DE MATERIAL VEJETAL | I21: 5 | J21: M-2
A22: INSPECCIONES DE SEGURIDAD | B22: VISITAS DE SEGURIDAD | D22: 44215 | E22: UNA HORA | F22: PARQUE PRINCIPAL | H22: INSPECION DE SEGURIDAD | I22: 1 | J22: M-6
A23: INSPECCIONES DE SEGURIDAD | B23: VISITAS DE SEGURIDAD | D23: 44215 | E23: UNA HORA | F23: (C I C ) LABORATORIO CENTRO | H23: INSPECION DE SEGURIDAD | I23: 1 | J23: M-6
A24: RESCATES | B24: RESCATE DE PERSONA / PARAPENTE | D24: 44221 | E24: UNA HORA | F24: CANCHA AUXILIAR DEL ESTADIO | G24: BARRIO BELEN | H24: PARAPENTISTA QUE QUEDA ENREDADO EN UN ARBOL | I24: 6 | J24: M-2
A25: INSPECCIONES DE SEGURIDAD | B25: VISITAS DE SEGURIDAD | D25: 44225 | E25: UNA HORA CUARENTE MINUTOS | F25: PARQUE PRINCIPAL CENTRO | H25: INSPECION DE SEGURIDAD EN ALMACEN DE ELECTRODOMESTICOS | I25: 1 | J25: M-6
A26: OTROS | B26: INCENDIO FORESTAL | D26: 44226 | E26: 33 MINUT | F26: CHALET ELAMPARO | G26: VIA A TORO | H26: INCENDIO QUEMA DE PASTIZAL | I26: 4 | J26: M-2
A27: INCENDIOS | B27: INCENDIO FORESTAL | D27: 44227 | E27: 1 HORA | F27: FINCA EL ESPINAL | G27: VIA LA UNION TORO POR PEDREGAL | H27: INCENDIO A ORILLAS DE LA CANAL SIN CONOCERSE LAS CAUSAS | I27: 6 | J27: M-2
A28: FEBRERO
A29: INSPECCIONES DE SEGURIDAD | B29: VISITAS DE SEGURIDAD | C29: =COUNTIF(B29:B65,C2) -> 4 | D29: 44229 | E29: UNA HORA CON CUARENTA MINUTOS | F29: CENTRO | H29: VISITA DE SEGURIDAD HOTEL TURQUESA | I29: 1 | J29: M-6
A30: FALSA ALARMA | B30: INCENDIO ESTRUCTURAL | D30: 44228 | E30: 30 MINUTOS | F30: CALLE 22 CON CRA 16 | G30: SAN PEDRO | H30: SE HACE VERIFICACION Y ERA FALSA ALARMA | I30: 6 | J30: M-2
A31: FALSA ALARMA | B31: INCENDIO VEHICULAR | D31: 44229 | E31: 10 MINUTOS | F31: CALLE 12 CON CRA 19 | G31: BELEN | H31: SE ACUDE AL SITIO Y NO SE ENCUENTRAN NADA | I31: 3 | J31: M - 2
A32: INCENDIOS | B32: LABORES DE PREVENCION O ACOMPAÑAMIENTO EN GESTION DEL RIESGO | D32: 44232 | E32: 20 MINUTOS | F32: CALLE 12 CON CRA 20 | G32: CAMPO ALEGRE | H32: SE ATIENDE EL LLAMADO DE UNA QUEMA POR EL BARRIO FATIMA, SE LLEGA AL SITIO Y SE OBSERVA UNA QUEMA DE BASURA LA CUAL ESTABA CONTROLADA EN SI ESTABA GENERANDO MUCHO HUMO | I32: 2 | J32: M-2
A33: INCENDIOS | B33: INCENDIO ESTRUCTURAL | D33: 44232 | E33: 1 HORA 30 MINUTOS | F33: FINCA LA PLAYITA | G33: EL CARMEN | H33: INCENDIO EN UNA CASA DE BAREQUE Y FIQUE | I33: 8 | J33: M - 2
A34: OTROS | B34: VISITAS DE SEGURIDAD | D34: 44235 | E34: DOS HORAS | F34: CASA VERDE PARQUE PRINCIPAL | G34: BARRIO JARDIN | H34: INSPECION DE SEGURIDAD | I34: 1 | J34: M - 6
A35: OTROS | B35: VISITAS DE SEGURIDAD | D35: 44235 | E35: UNA HORA | F35: FINCA EL REFUJIO | G35: MARTINDOZA | H35: INSPECION DE SEGURIDAD | I35: 1 | J35: M - 6
A36: INSPECCIONES DE SEGURIDAD | B36: VISITAS DE SEGURIDAD | D36: 44236 | E36: 1 HORA | F36: FINCA LA BRACILERA | H36: VISITA DE SEGURIDAD | I36: 1 | J36: M - 6
A37: FALSA ALARMA | B37: RESCATE DE PERSONA / PARAPENTE | D37: 44237 | E37: 1 HORA | F37: VIA LA UNION VERSALLES | H37: VEHICULO QUE SE SALIO DEL CAMINO | I37: 4 | J37: M - 3
A38: OTROS | B38: CAÍDA / CORTES DE ARBOL | D38: 44238 | E38: TRES HORAS Y MEDIA | F38: VIA LA UION TORO | G38: EL AMPARO | H38: ARBOL QUE CAE SOBRE CUERDAS ELECTRICAS | I38: 10 | J38: M - 2
A39: INCENDIOS | B39: INCENDIO ESTRUCTURAL | D39: 44239 | E39: CUATRO HORAS | F39: LA VICTORIA VALLE | H39: QUEMA DE TRAPICHE- APOLLO AL CBV DE LA VICTORIA VALLE | I39: 4 | J39: M-1
A40: INCENDIOS | B40: INCENDIO FORESTAL | D40: 44240 | E40: 30 MINUTOS | F40: CALLE 15 ENTRE CARERA 19 Y 20 | G40: LA CRUZ | H40: INCENDIO EN UN POTRERO | I40: 7 | J40: M - 2
A41: INSPECCIONES DE SEGURIDAD | B41: VISITAS DE SEGURIDAD | D41: 44243 | E41: TRES HORAS CON QUINCE MINUTOS | F41: PARQUE PRINCIPAL | H41: VISITA DE SEGURIDAD ESTABLECIMIENTO LA CASA VERDE | I41: 1 | J41: M-6
A42: OTROS | B42: CAÍDA / CORTES DE ARBOL | D42: 44243 | E42: TRES HORAS CON QUINCE MINUTOS | F42: VIA LA UNION LA VICTORIA | H42: CORTE DE ARBOL POR RIESGO DE CAIDA | I42: 2 | J42: M - 3
A43: OTROS | B43: VISITAS DE SEGURIDAD | D43: 44243 | E43: DOS HORAS VEINTE MINUTOS | F43: LOCAL LA CASA VERDE | G43: PARQUE PRINCIPAL | H43: INSPECION DE SEGURIDAD | I43: 1 | J43: M-6
A44: RESCATES | B44: RESCATE DE PERSONA / PARAPENTE | D44: 44243 | E44: DOS HORAS CON CUARENTA Y CINCI MINUTOS | F44: SEGUNDA CANAL VIA TORO POR L FARILLON | G44: CORCEGA | H44: PERSON QUE QUEDA ATRAPADA DEBAJO DE UNA VOLQUETA LA CUAL PIERDE LA VIDA | I44: 8 | J44: M- 3
A45: RESCATES | B45: RESCATE DE ANIMAL | D45: 44244 | E45: CINCO HORAS CON DIEZ MIUTOS | F45: BARRIO PAJARO DE ORO | G45: PAJARO DE ORO | H45: TERNERO QUE CAE A UN POSSO 14 MTS DE PROFUNDIDAD | I45: 8 | J45: M-2 Y M- 3
A46: OTROS | B46: CAÍDA / CORTES DE ARBOL | D46: 44244 | E46: CUATRO HORAS CON TREINTE MINUTOS | F46: VIA LA UNION LA VICTORIA | G46: EL AMPARO | H46: CORTE DE ARBOL POR RIESGO | I46: 2 | J46: M- 3
A47: RESCATES | B47: RESCATE DE ANIMAL | D47: 44245 | E47: 8 HORAS | F47: CALLE 29 N° 17-50 | G47: LA CAMPESINA | H47: RESCATE DE SEMOVIENTE ADULTO QUE CAE A UN POZO | I47: 8 | J47: M-2 Y M- 3
A48: INSPECCIONES DE SEGURIDAD | B48: VISITAS DE SEGURIDAD | D48: 44246 | E48: UNA HORA Y CURENTA Y CINCO MINUTOS | F48: PARQUE PRINCIPAL | G48: CENTRO | H48: VISITA DE SEGURIDAD | I48: 1 | J48: M- 6
A49: INCENDIOS | B49: INCENDIO FORESTAL | D49: 44248 | E49: 1 HORA 30 MINUTOS | F49: SAN RAFAEL | G49: LINDEROS | H49: QUEMA QUE SE SALIO DE CONTROL | I49: 8 | J49: M - 2
A50: INSPECCIONES DE SEGURIDAD | B50: VISITAS DE SEGURIDAD | D50: 44249 | E50: UNA HORA | F50: COOPSER | H50: VISITA DE SEGURIDAD | I50: 1 | J50: M-6
A51: RESCATES | B51: RESCATE DE PERSONA / PARAPENTE | D51: 44250 | E51: 6 HORAS | F51: MONTAÑA ALTA SAN LUIS | G51: SAN LUIS | H51: PARAPENTE QUE PIERDE EL CONTROL Y CAE EN LA PARTE MEDIA ALTA DE LA MONTAÑA | I51: 16 | J51: M - 2 , M - 3 Y M - 5
A52: OTROS | B52: VISITAS DE SEGURIDAD | D52: 44252 | E52: 5 HORAS 30 MINUTOS | F52: EL RINCON | G52: VEREDA EL RINCON | H52: SE HACE PRESENCIA EN EL ANALISIS DE RIESGO DE UNA FALLA GEOLOGICA EN COMPAÑIA DE GESTION DE RIESGO Y FDEFENSA CIVIL | I52: 3 | J52: M - 3
A53: OTROS | B53: SUMINISTROS DE AGUA | D53: 44252 | E53: 8 HORAS 30 MINUTOS | F53: COLICEO ANGELINO GARZON Y PATINODROMO | G53: BARRIO BELEN | H53: SE HACE ASISTENCIA EN EL SITIO PARA LAVADO, SE UTILIZAN 5 VIAJES DE AGUA DE 1000 GALONES | I53: 1 | J53: M - 1
A54: INCENDIOS | B54: INCENDIO FORESTAL | D54: 44252 | E54: 1 HORA 10 MINUTOS | F54: FINCA DE NAVARRO | G54: LA CIUDADELA | H54: SE ASISTE AL SITIO PARA CONTROL DE UN INCENDIO FORESTAL ,SE QUEMA APROXIMADAMENTE MEDIA PLAZA DE PASTIZAL , SE UTILISAN 1000 GALONES PARA CONTROLAR Y LIQUIDAR EL INCENDIO | I54: 4 | J54: M - 2
A55: OTROS | B55: INUNDACIÓN | D55: 44252 | E55: 3 HORAS 40 MINUTOS | F55: BARRIOBELEN , BARRIO BELLA VISTA, SECTOR F DE FRUTIVALLE VIA LA UNION LA VICTORIA | G55: BEN ,BELLA VISTA,CORCEGA | H55: SE ASISTE A LAS SITIOS ANTES MENCIONADOS PARA COLABORACION DE SACADO DE AGUA DE LAS CASAS Y LAVADO ,TAMBIEN SE ASISTIO PARA CORTE DE RAMAS EN LA VIA LA UNION LAS VICTORIA | I55: 12 | J55: M -1 ,M-2, M- 3 Y M-5
A56: OTROS | B56: CORTO CIRCUITO | D56: 44254 | E56: MEDIA HORA | F56: CHALET REAL | G56: CORREJIMIENTO SAN LUIS | H56: SE HACEN LAVORES DE PREVENCION MIENTRAS LLEGABAN LOS TECNICOS DE CELSIA | I56: 3 | J56: M - 2
A57: INCENDIOS | B57: CORTO CIRCUITO | D57: 44254 | E57: MEDIA HORA | F57: MANZANA E CASA 16 | G57: URBANIZACION EL PRADO | H57: SE ATIENDE EL LLAMADO Y SE LLEGA AL LUGAR OBSERVANDO FUEGO POR CORTO CIRCUITO DENTRO DE LAS REDES DE ENERGIA SEW CONTROLA Y LIQUIDA | I57: 4 | J57: M- 2
A58: RESCATES | B58: CAÍDA / CORTES DE ARBOL | D58: 44255 | E58: CUATRO HORAS CON QUINCE MINUTOS | F58: VIA LA UNION ROLDANILLO | G58: HIGUERONCITO | H58: ARBOL QUE CAE SOBRE UNA MOTO CICLETA Y UNA BUSETA | I58: 11 | J58: M - 2 , Y M- 3
A59: INSPECCIONES DE SEGURIDAD | B59: VISITAS DE SEGURIDAD | D59: 44229 | E59: UNA HORA CON CUARENTA MINUTOS | F59: CENTRO | H59: VISITA DE SEGURIDAD HOTEL TURQUESA | I59: 1 | J59: M-6
A60: INCENDIOS | B60: INCENDIO ESTRUCTURAL | D60: 44239 | E60: CUATRO HORAS | F60: LA VICTORIA VALLE | H60: QUEMA DE TRAPICHE- APOLLO AL CBV DE LA VICTORIA VALLE | I60: 4 | J60: M-1
A61: INCENDIOS | B61: INCENDIO FORESTAL | D61: 44240 | E61: UNA HORA | F61: CLLE 15 ENTRE CERRERA 19 Y 20 | G61: LA CRUZ | H61: QUEMA DE PASTIZAL | I61: 9 | J61: M-2, M-3
A62: INSPECCIONES DE SEGURIDAD | B62: VISITAS DE SEGURIDAD | D62: 44243 | E62: TRES HORAS CON QUINCE MINUTOS | F62: PARQUE PRINCIPAL | H62: VISITA DE SEGURIDAD ESTABLECIMIENTO LA CASA VERDE | I62: 1 | J62: M-6
A63: BUSQUEDA Y RESCATE | B63: PRIMEROS AUXILIOS | D63: 44243 | E63: TRS HORAS CON DIEZ MINUTOS | F63: VIA LA UNION LA VICTORIA | G63: TEJEDAS | H63: MOTO CICLETA VS VOLQUETA LA CUAL EL MOTO CICLISTA PIERDE L VIDA | I63: 8 | J63: M-2, M-3
A64: INSPECCIONES DE SEGURIDAD | B64: VISITAS DE SEGURIDAD | D64: 44249 | E64: UNA HORA | F64: COOPSER | H64: VISITA DE SEGURIDAD | I64: 1 | J64: M-6
A65: OTROS | B65: CAÍDA / CORTES DE ARBOL | D65: 44243 | E65: TRES HORAS CON QUINCE MINUTOS | F65: VIA LA UNION LA VICTORIA | H65: CORTE DE ARBOL POR RIESGO DE CAIDA | I65: 3 | J65: M-3
A66: MARZO
A67: INSPECCIONES DE SEGURIDAD | B67: VISITAS DE SEGURIDAD | C67: =COUNTIF(B67:B95,C2) -> 0 | D67: 44256 | E67: DOS HORAS CON QUINCE MINUTOS | F67: CENTRO | H67: VISITA DE SEGURIDAD | I67: 1 | J67: M - 6
A68: OTROS | B68: SUMINISTROS DE AGUA | D68: 44257 | E68: SEIS HORAS CON DIEZ MINUTOS | F68: PLAZA DE MERCAO | H68: LAVADO DE PLAZA DE MERCADO | I68: 2 | J68: M-1
A69: INSPECCIONES DE SEGURIDAD | B69: VISITAS DE SEGURIDAD | D69: 44260 | E69: 2 HORAS | F69: CR 15 # 16-55 | H69: VISITA DE SEGURIDAD | I69: 1 | J69: M-6
A70: INSPECCIONES DE SEGURIDAD | B70: VISITAS DE SEGURIDAD | D70: 44260 | E70: 2 HORAS | F70: CR 16 # 16-84 | H70: VISITA DE SEGURIDAD | I70: 1 | J70: M-6
A71: OTROS | B71: CONTROL DE ABEJAS | D71: 44260 | E71: UNA HORA CON CUARENTA MINUTOS | F71: BARRIO EL LUCERO PARTE ALTA | H71: ABEJAS QUE LLEGAN A VIVIENDA Y TOCA DESALOJAR ALAS PERSONAS | I71: 3 | J71: M-5
A72: OTROS | B72: FUGA DE GAS NATURAL | D72: 44260 | E72: UNA HORA | F72: CALLE 16 CON 20 | H72: FUGA DE GAS NATURAL EN VIVIENDA | I72: 3 | J72: M-2
A73: OTROS | B73: INUNDACIÓN | D73: 44260 | E73: 1 hora 6 minutos | F73: CARRERA 11 # 11 44 | G73: EL LUCERO BAJO | H73: CRECIENTE DE LA QUEBRADA LUCERO BAJO E INUNDACION DE VIVENDAS | I73: 9 | J73: M-2, M-3
A74: INCENDIOS | B74: INCENDIO VEHICULAR | D74: 44263 | E74: 56 MINUTOS | F74: CBV ROLDANILLO | G74: CORREGIMIENTO SANTA RITA | H74: SE ATIENDE EL LLAMADO DE APOYO ,PERO CUANDO LLEGARON AL SITIO YA LA SITUACION ESTABA CONTROLADA | I74: 3 | J74: M-1
A75: INSPECCIONES DE SEGURIDAD | B75: VISITAS DE SEGURIDAD | D75: 44264 | E75: 1 HORA 40 MINUTOS | F75: ESTANQUILLO LICORES EL BARRIL | G75: CRA 16 #16-84 | H75: SE HACE LA VISITA DE SEGURIDAD | I75: 1 | J75: M-6
A76: OTROS | B76: CORTO CIRCUITO | D76: 44265 | E76: UNA HORA TREINTA MINUTOS | F76: VIA LA UNION LA VICTORIA | G76: EL AMPARO | H76: CUERDA DE ALTA TENCION QUE SE REVIENTA POR CAIDA DE RAMA | I76: 2 | J76: M-2
A77: INCENDIOS | B77: INCENDIO VEHICULAR | D77: 44269 | E77: 30 MINUTOS | F77: CLL 14 CON CR 14 EQUINA | G77: CENTRO | H77: VEHICULO QUE ESTABA ENCENDIDO PERO FUE CONTROLADO CON EXTINTORES | I77: 3 | J77: M-2
A78: OTROS | B78: LABORES DE PREVENCION O ACOMPAÑAMIENTO EN GESTION DEL RIESGO | D78: 44270 | E78: VIA TORO-LA UNION-ROLDANILLO | F78: VIA PANORAMA | H78: MONITOREO DE POSIBLES CAIDAS DE ARBOLES EN LA VIA | I78: 2 | J78: M-3
A79: OTROS | B79: LABORES DE PREVENCION O ACOMPAÑAMIENTO EN GESTION DEL RIESGO | D79: 44270 | E79: 5 HORAS 30 MINUTOS | F79: LA CALLETANA | H79: REVICION DEL FLUVIAL DEL RIO CAUCA | I79: 2 | J79: M-3
A80: OTROS | B80: LABORES DE PREVENCION O ACOMPAÑAMIENTO EN GESTION DEL RIESGO | D80: 44272 | E80: 7 HORAS | F80: ORILLA DEL RIO CAUCA | H80: MONITOREO DEL CAUDAL DEL RIO CAUCA | I80: 2 | J80: M-4
A81: RESCATES | B81: RESCATE DE PERSONA / PARAPENTE | D81: 44276 | E81: 1 HORA | F81: LA CIENAGUETA | G81: VEREDA MARTINDOZA | H81: RESCATE A PERSONA Y A VEHICULO PROXIMOS A CAER AL SANJON DE LOS MUERTOS | I81: 6 | J81: M-2, M-3
A82: RESCATES | B82: RESCATE DE PERSONA / PARAPENTE | D82: 44277 | E82: UNA HORA | F82: LAS TRES CRUZES | G82: LA CAMPESINA PARTE ALTA | H82: PERSONAS QUE SON ATACADAS POR ABEJAS EN UNA VIVIENDA | I82: 4 | J82: M-3
A83: INCENDIOS | B83: CORTO CIRCUITO | D83: 44278 | E83: UNA HORA | F83: EMPRESA CASA GRAJALES | G83: BARRIO LAS LAJAS | H83: IMFORMAN DE LA PORTERIA DE GRAJALES SOBRE UN CORTO CIRCUITO EN LA PARTE INTERIO DE LA COSINA EN EL RESTAURANTE | I83: 5 | J83: M-2
A84: OTROS | B84: LABORES DE PREVENCION O ACOMPAÑAMIENTO EN GESTION DEL RIESGO | D84: 44279 | E84: TRES HORAS | F84: RIO CAUCA | G84: VIA LA UNION LA VICTORIA | H84: MONITOREO NIVEL RIO CAUCA | I84: 3 | J84: M-4
A85: INSPECCIONES DE SEGURIDAD | B85: VISITAS DE SEGURIDAD | D85: 44256 | E85: DOS HORAS QUINCE MINUTOS | F85: PARQUE PRINCIPAL | G85: LA CRUZ | H85: INSPECION DE SEGURIDAD EN AMBULANCIAS BRIGADA + 44 SAS | I85: 1 | J85: M-6
A86: INCENDIOS | B86: CORTO CIRCUITO | D86: 44256 | E86: UNA HORA CON CUARENTE U CUATRO MINUTOS | F86: VIA LA UNION TORO | G86: EL AMPARO | H86: ARBOL QUE CAE SOBRE CUERDAS DE ALTA TENCION Y PRODUCE CHISPAS | I86: 3 | J86: M-2
A87: OTROS | B87: CONTROL DE ABEJAS | D87: 44263 | E87: VEINTI CINCO MINUTOS | F87: CALLE 14 | G87: BELLA VISTA | H87: CONTROL Y RECUPERACION DE ABEJAS | I87: 3 | J87: M-3
A88: OTROS | B88: CAÍDA DE CUERDAS | D88: 44265 | E88: UNA HORA YCUARENTA MINUTOS | F88: VIA LA UNION LA VICTORIA | G88: 300 MTS DE ROMPOY | H88: CUERDA QUE CAE SOBRE LA VIA | I88: 2 | J88: M-2
A89: INSPECCIONES DE SEGURIDAD | B89: VISITAS DE SEGURIDAD | D89: 44273 | E89: UNA HORA CON DIEZ MINUTOS | F89: CENTRO DIAGONAL AL COLEJIO DE LAS MONJAS | H89: VISITA DE SEGURIDAD | I89: 1 | J89: M-6
A90: OTROS | B90: LABORES DE PREVENCION O ACOMPAÑAMIENTO EN GESTION DEL RIESGO | D90: 44274 | E90: UNA HORA | F90: PARQUE PRINCIPAL | H90: APOLLO EN SEGURIDAD QUEMA DE CASTILLO | I90: 2 | J90: M-2
A91: OTROS | B91: RESCATE DE PERSONA / PARAPENTE | D91: 44277 | E91: CUARENTA MINUTOS | F91: LAS TRES CRUCES | G91: VIA ALA AGUADA | H91: ABEJAS QUE ATACAN A PERSONAS DE UNA VIVIENDA | I91: 4 | J91: M-3
A92: OTROS | B92: VISITAS DE SEGURIDAD | D92: 44285 | E92: TRES HORAS CON DIEZ | F92: HOTEL PRIMAVERAL Y FLORISTERIA | G92: CENTRO | H92: VISIT DE SEGURIDAD A DOS ESTABLECIMIENTOS | I92: 1 | J92: M-6
A93: RESCATES | B93: RESCATE DE ANIMAL | D93: 44286 | E93: TRES HORAS | F93: BARRIO LA CAMPESINA | H93: IMFORMA SEÑORA MONICA GONZALEZ DE UNA VACA QUE CAE A UN POSO | I93: 4 | J93: M-2
A94: OTROS | B94: VISITAS DE SEGURIDAD | D94: 44285 | E94: 3 HORAS | F94: HOTEL PRIMAVERAL DEL PARQUE Y HOTEL PRIMAVERAL | G94: CENTRO | H94: 3 | I94: 1 | J94: M-6
A95: OTROS | B95: VISITAS DE SEGURIDAD | D95: 44286 | E95: 3.30 HORAS | F95: HOTEL PRIMAVERAL | G95: CENTRO | H95: SE HIZO INSPECCION DEL CITIO Y SE COLOCO LAS SEÑALIZACIONES Y EXTINTORES EN SUS DEBIDOS PUESTOS | I95: 1 | J95: M-6
A96: ABRIL
A97: OTROS | B97: CAÍDA / CORTES DE ARBOL | C97: =COUNTIF(B97:B114,C2) -> 0 | D97: 44289 | E97: 2:40 | F97: CL 11 CR 19 | G97: EL PRADO | H97: ARBOL QUE TAPONA EL CAUCE DE LA QUEBRADA OCACIONANDO REPRESAMIENTO. | I97: 7 | J97: M-2, M-4
A98: RESCATES | B98: RESCATE DE PERSONA / PARAPENTE | D98: 44291 | E98: DOS HORAS CON QUINCE MINUTOS | F98: VIA LA UNION TORO POR EL FARILLON | H98: VEHICULO QUE CAE ALA CANAL | I98: 11 | J98: M-2, M-5
A99: OTROS | B99: INUNDACIÓN | D99: 44292 | E99: DOS HORAS | F99: KR 20#17-68 | G99: SANPEDRO | H99: VIVIENDA INUNDADA POR FUERTE AGUASERO | I99: 4 | J99: M-2
A100: OTROS | B100: INUNDACIÓN | D100: 44292 | E100: DON HORAS | F100: EL JARDIN | G100: EL JARDIN | H100: VIVIENDA INUNDADA POR FUERTE AGUASERO | I100: 4 | J100: M-2
...

Sheet 2020
A2: INFORME DE SINIESTRALIDAD PARA EL PERIODO DEL 01 DE ENERO AL 31 DE DICIEMBRE 2020
A3: CUERPO DE BOMBEROS VOLUNTARIOS DE LA UNION - VALLE DEL CAUCA
C5: PERIODO ( Enero 01 al 31 de Diciembre 2020 )
A6: ITEM | B6: INCIDENTE | C6: ENE | D6: FEB | E6: MAR | F6: ABR | G6: MAY | H6: JUN | I6: JUL | J6: AGO | K6: SEP | L6: OCT | M6: NOV | N6: DIC | O6: TOTAL
B7: GESTION DEL RIESGO DE INCENDIOS
A8: 1 | B8: Incendio estructural | D8: 4 | E8: 1 | G8: 2 | I8: 1 | K8: 1 | L8: 1 | M8: 1 | O8: =SUM(C8:N8) -> 11
A9: 2 | B9: Incendio forestal rural | C9: 4 | D9: 3 | E9: 3 | F9: 1 | G9: 2 | L9: 1 | M9: 1 | N9: 2 | O9: =SUM(C9:N9) -> 17
A10: 3 | B10: Incendio forestal urbano | C10: 2 | O10: =SUM(C10:N10) -> 2
A11: 4 | B11: Incendio Agrícola | D11: 1 | E11: 1 | K11: 2 | O11: =SUM(C11:N11) -> 4
A12: 5 | B12: Incendio vehicular | C12: 1 | I12: 1 | J12: 1 | N12: 1 | O12: =SUM(C12:N12) -> 4
A13: 6 | B13: Incendio de líquidos inflamables | O13: =SUM(C13:N13) -> 0
A14: 7 | B14: Incendio de Gases o Gas domiciliario | O14: =SUM(C14:N14) -> 0
A15: 8 | B15: Incendio en Cilindro de Gas Vehicular | O15: =SUM(C15:N15) -> 0
A16: 9 | B16: Incendio | O16: =SUM(C16:N16) -> 0
A17: 10 | B17: Incendio eléctrico | C17: 2 | F17: 1 | G17: 1 | K17: 1 | O17: =SUM(C17:N17) -> 5
A18: 11 | B18: Incendio Aéreo | O18: =SUM(C18:N18) -> 0
A19: 12 | B19: Fuegos aislados o basuras | D19: 1 | E19: 1 | H19: 1 | J19: 2 | N19: 1 | O19: =SUM(C19:N19) -> 6
B20: SUB-TOTALES | C20: =SUM(C8:C19) -> 9 | D20: =SUM(D8:D19) -> 9 | E20: =SUM(E8:E19) -> 6 | F20: =SUM(F8:F19) -> 2 | G20: =SUM(G8:G19) -> 5 | H20: =SUM(H8:H19) -> 1 | I20: =SUM(I8:I19) -> 2 | J20: =SUM(J8:J19) -> 3 | ... N20: =SUM(N8:N19) -> 4 | O20: =SUM(C20:N20) -> 49
B21: RESCATE EN TODAS SUS MODALIDADES
A22: 13 | B22: Rescates (Actividad) en Accidentes de tránsito | O22: =SUM(C22:N22) -> 0
A23: 14 | B23: Accidentes de tránsito atendidos sin la actividad de rescate | C23: 1 | K23: 1 | N23: 1 | O23: =SUM(C23:N23) -> 3
A24: 15 | B24: Otros Rescates de emergencias diferentes a accidente de tránsito | O24: =SUM(C24:N24) -> 0
A25: 16 | B25: Salvamento en mina | O25: =SUM(C25:N25) -> 0
A26: 17 | B26: Rescate de animal | C26: 2 | F26: 2 | J26: 1 | K26: 2 | L26: 1 | N26: 1 | O26: =SUM(C26:N26) -> 9
A27: 18 | B27: Auxilio a electrocutado | O27: =SUM(C27:N27) -> 0
A28: 19 | B28: Rescate en ascensor | O28: =SUM(C28:N28) -> 0
A29: 20 | B29: Rescate con apertura de puerta | O29: =SUM(C29:N29) -> 0
A30: 21 | B30: Rescate Acuático | D30: 1 | O30: =SUM(C30:N30) -> 1
A31: 22 | B31: Rescate en Estructura Colapsada | O31: =SUM(C31:N31) -> 0
A32: 23 | B32: Rescate en Altura | O32: =SUM(C32:N32) -> 0
A33: 24 | B33: Rescate en espacio confinado | O33: =SUM(C33:N33) -> 0
A34: 25 | B34: Rescate en Accidente Aéreo | O34: =SUM(C34:N34) -> 0
A35: 26 | B35: Rescate en media y alta Montaña | D35: 1 | E35: 2 | L35: 1 | O35: =SUM(C35:N35) -> 4
A36: 27 | B36: Rescate con exposición de Materiales peligrosos | O36: =SUM(C36:N36) -> 0
B37: SUB-TOTALES | C37: =SUM(C22:C36) -> 3 | D37: =SUM(D22:D36) -> 2 | E37: =SUM(E22:E36) -> 2 | F37: =SUM(F22:F36) -> 2 | G37: =SUM(G22:G36) -> 0 | H37: =SUM(H22:H36) -> 0 | I37: =SUM(I22:I36) -> 0 | J37: =SUM(J22:J36) -> 1 | ... N37: =SUM(N22:N36) -> 2 | O37: =SUM(C37:N37) -> 17
B38: ATENCION DE MATERIALES PELIGROSOS
A39: 28 | B39: Incidentes con materiales peligrosos en vehículos accidentados | O39: =SUM(C39:N39) -> 0
A40: 29 | B40: Incidente de materiales peligrosos (otros) | O40: =SUM(C40:N40) -> 0
A41: 30 | B41: Fuga de gas GLP | O41: =SUM(C41:N41) -> 0
A42: 31 | B42: Fuga de gas GN | C42: 3 | D42: 1 | E42: 1 | G42: 3 | I42: 4 | J42: 2 | K42: 3 | L42: 2 | O42: =SUM(C42:N42) -> 19
A43: 32 | B43: Derrames de combustible en vía pública | E43: 1 | H43: 1 | O43: =SUM(C43:N43) -> 2
B44: SUB-TOTALES | C44: =SUM(C39:C43) -> 3 | D44: =SUM(D39:D43) -> 1 | E44: =SUM(E39:E43) -> 2 | F44: =SUM(F39:F43) -> 0 | G44: =SUM(G39:G43) -> 3 | H44: =SUM(H39:H43) -> 1 | I44: =SUM(I39:I43) -> 4 | J44: =SUM(J39:J43) -> 2 | ... N44: =SUM(N39:N43) -> 0 | O44: =SUM(C44:N44) -> 21
B45: ATENCION DE OTROS INCIDENTES
A46: 33 | B46: Colapsos en estructura | G46: 1 | K46: 13 | O46: =SUM(C46:N46) -> 14
A47: 34 | B47: Derrumbes y deslizamientos (Completar cuadro anexo) | O47: =SUM(C47:N47) -> 0
A48: 35 | B48: Explosiones por pólvora | O48: =SUM(C48:N48) -> 0
A49: 36 | B49: Explosiones de ollas a presión | O49: =SUM(C49:N49) -> 0
A50: 37 | B50: Otras explosiones | O50: =SUM(C50:N50) -> 0
A51: 38 | B51: Inundaciones Atendidas (Completar cuadro anexo) | K51: 10 | O51: =SUM(C51:N51) -> 10
A52: 39 | B52: Caídas de árboles, postes de energía y otros | E52: 1 | J52: 1 | K52: 13 | L52: 3 | M52: 1 | N52: 1 | O52: =SUM(C52:N52) -> 20
A53: 40 | B53: Atención de abejas | C53: 1 | D53: 5 | E53: 8 | F53: 11 | G53: 10 | H53: 15 | I53: 9 | L53: 5 | M53: 2 | N53: 1 | O53: =SUM(C53:N53) -> 67
A54: 41 | B54: Recuperación de cadáver | O54: =SUM(C54:N54) -> 0
A55: 42 | B55: Vendaval | K55: 1 | O55: =SUM(C55:N55) -> 1
A56: 43 | B56: Otras emergencias atendidas no descritas | J56: 1 | K56: 1 | O56: =SUM(C56:N56) -> 2
B57: SUB-TOTALES | C57: =SUM(C46:C56) -> 1 | D57: =SUM(D46:D56) -> 5 | E57: =SUM(E46:E56) -> 9 | F57: =SUM(F46:F56) -> 11 | G57: =SUM(G46:G56) -> 11 | H57: =SUM(H46:H56) -> 15 | I57: =SUM(I46:I56) -> 9 | J57: =SUM(J46:J56) -> 2 | ... N57: =SUM(N46:N56) -> 2 | O57: =SUM(C57:N57) -> 114
B58: ATENCION PREHOSPITALARIA
A59: 44 | B59: Atención APH de heridos en accidente de transito (Sin transporte - No. De personas atendidas) | C59: 1 | O59: =SUM(C59:N59) -> 1
A60: 45 | B60: Transporte de heridos en accidente de transito. (No. de transportados en vehículos Institucionales de Bomberos) | O60: =SUM(C60:N60) -> 0
A61: 46 | B61: Atención APH de heridos diferente a accidente de tránsito | C61: 1 | D61: 1 | E61: 1 | O61: =SUM(C61:N61) -> 3
A62: 47 | B62: Transporte de heridos diferente a accidente de transito | K62: 1 | O62: =SUM(C62:N62) -> 1
A63: 48 | B63: Auxilio a enfermo | H63: 2 | O63: =SUM(C63:N63) -> 2
A64: 49 | B64: Trabajo de parto | K64: 1 | O64: =SUM(C64:N64) -> 1
B65: SUB-TOTALES | C65: =SUM(C59:C64) -> 2 | D65: =SUM(D59:D64) -> 1 | E65: =SUM(E59:E64) -> 1 | F65: =SUM(F59:F64) -> 0 | G65: =SUM(G59:G64) -> 0 | H65: =SUM(H59:H64) -> 2 | I65: =SUM(I59:I64) -> 0 | J65: =SUM(J59:J64) -> 0 | ... N65: =SUM(N59:N64) -> 0 | O65: =SUM(C65:N65) -> 8
B66: TOTAL DE INCIDENTES ATENDIDOS | C66: =SUM(C65+C57+C44+C37+C20) -> 18 | D66: =SUM(D65+D57+D44+D37+D20) -> 18 | E66: =SUM(E65+E57+E44+E37+E20) -> 20 | F66: =SUM(F65+F57+F44+F37+F20) -> 15 | G66: =SUM(G65+G57+G44+G37+G20) -> 19 | H66: =SUM(H65+H57+H44+H37+H20) -> 19 | I66: =SUM(I65+I57+I44+I37+I20) -> 15 | J66: =SUM(J65+J57+J44+J37+J20) -> 8 | ... N66: =SUM(N65+N57+N44+N37+N20) -> 8 | O66: =SUM(C66:N66) -> 209
B67: LABORES DE PREVENCION Y OTROS
A68: 1 | B68: Inspecciones de prevención y seguridad | C68: 22 | D68: 20 | E68: 20 | G68: 1 | H68: 7 | I68: 15 | J68: 9 | K68: 15 | L68: 10 | M68: 8 | N68: 20 | O68: =SUM(C68:N68) -> 147
A69: 2 | B69: Realización de Pruebas Hidráulicas | G69: 50 | H69: 9 | O69: =SUM(C69:N69) -> 59
A70: 3 | B70: Participación en Eventos masivos y no masivos | F70: 1 | O70: =SUM(C70:N70) -> 1
A71: 4 | B71: Participación en Eventos pirotécnicos | O71: =SUM(C71:N71) -> 0
A72: 5 | B72: Labores sociales | C72: 1 | D72: 10 | E72: 8 | F72: 2 | G72: 1 | H72: 1 | I72: 1 | J72: 2 | K72: 1 | L72: 1 | M72: 1 | N72: 2 | O72: =SUM(C72:N72) -> 31
A73: 6 | B73: Labores de prevención diversas | D73: 1 | F73: 7 | G73: 53 | H73: 14 | I73: 3 | K73: 27 | L73: 2 | N73: 3 | O73: =SUM(C73:N73) -> 110
A74: 7 | B74: Falsas alarmas por diversos casos | D74: 2 | H74: 3 | K74: 1 | M74: 1 | N74: 2 | O74: =SUM(C74:N74) -> 9
A75: 8 | B75: Actividades de Evacuaciones | L75: 1 | O75: =SUM(C75:N75) -> 1
A76: 9 | B76: Suministro de Agua a Comunidades u otros | E76: 14 | F76: 46 | G76: 54 | H76: 52 | I76: 23 | J76: 1 | K76: 1 | L76: 4 | O76: =SUM(C76:N76) -> 195
B77: TOTAL LABORES DE PREVENCIÓN Y OTROS | C77: =SUM(C68:C76) -> 23 | D77: =SUM(D68:D76) -> 33 | E77: =SUM(E68:E76) -> 42 | F77: =SUM(F68:F76) -> 56 | G77: =SUM(G68:G76) -> 159 | H77: =SUM(H68:H76) -> 86 | I77: =SUM(I68:I76) -> 42 | J77: =SUM(J68:J76) -> 12 | ... N77: =SUM(N68:N76) -> 27 | O77: =SUM(C77:N77) -> 553
B78: ACUMULADO TOTAL DE EMERGENCIAS EVENTOS Y LABORES DE PREVENCIÓN AÑO | C78: =SUM(C66+C77) -> 41 | D78: =SUM(D66+D77) -> 51 | E78: =SUM(E66+E77) -> 62 | F78: =SUM(F66+F77) -> 71 | G78: =SUM(G66+G77) -> 178 | H78: =SUM(H66+H77) -> 105 | I78: =SUM(I66+I77) -> 57 | J78: =SUM(J66+J77) -> 20 | ... N78: =SUM(N66+N77) -> 35 | O78: =SUM(C78:N78) -> 762
B80: CUADROS ANEXOS
B81: DERRUMBES O DESLIZAMIENTOS
A82: a | B82: Cobertura afectada metros2 o Hectáreas
A83: b | B83: Duración de la afectación por el movimiento en masa
A84: c | B84: Viviendas o Instalaciones afectadas
A85: d | B85: Metros Cúbicos de la afectación
A86: e | B86: No. De afectados por el movimiento en masa (No. PERSONAS o No. FAMILIAS)
B87: SUB-TOTALES | C87: =SUM(C82:C86) -> 0 | D87: =SUM(D82:D86) -> 0 | E87: =SUM(E82:E86) -> 0 | F87: =SUM(F82:F86) -> 0 | G87: =SUM(G82:G86) -> 0 | H87: =SUM(H82:H86) -> 0 | I87: =SUM(I82:I86) -> 0 | J87: =SUM(J82:J86) -> 0 | ... O87: =SUM(O82:O86) -> 0
B88: INUNDACIONES
A89: a | B89: Cobertura afectada metros2 o Hectáreas
A90: b | B90: Duración de la inundación | K90: 6
A91: c | B91: Viviendas o Instalaciones afectadas | K91: 10
A92: d | B92: No. De afectados por la inundación- (N° PERSONAS O N° FAMILIAS) | K92: 27
B93: SUB-TOTALES | C93: =SUM(C89:C92) -> 0 | D93: =SUM(D89:D92) -> 0 | E93: =SUM(E89:E92) -> 0 | F93: =SUM(F89:F92) -> 0 | G93: =SUM(G89:G92) -> 0 | H93: =SUM(H89:H92) -> 0 | I93: =SUM(I89:I92) -> 0 | J93: =SUM(J89:J92) -> 0 | ... O93: =SUM(O89:O92) -> 0

Sheet 2019
A2: INFORME DE SINIESTRALIDAD PARA EL PERIODO DEL 01 DE ENERO AL 31 DE DICIEMBRE 2019
A3: CUERPO DE BOMBEROS VOLUNTARIOS DE LA UNION - VALLE DEL CAUCA
C5: PERIODO ( Enero 01 al 31 de Diciembre 2019 )
A6: ITEM | B6: INCIDENTE | C6: ENE | D6: FEB | E6: MAR | F6: ABR | G6: MAY | H6: JUN | I6: JUL | J6: AGO | K6: SEP | L6: OCT | M6: NOV | N6: DIC | O6: TOTAL
B7: GESTION DEL RIESGO DE INCENDIOS
A8: 1 | B8: Incendio estructural | C8: 1 | E8: 1 | I8: 1 | K8: 1 | O8: =SUM(C8:N8) -> 4
A9: 2 | B9: Incendio forestal rural | C9: 9 | D9: 6 | J9: 6 | K9: 5 | M9: 1 | O9: =SUM(C9:N9) -> 27
A10: 3 | B10: Incendio forestal urbano | C10: 5 | D10: 4 | G10: 1 | J10: 2 | K10: 2 | O10: =SUM(C10:N10) -> 14
A11: 4 | B11: Incendio Agrícola | D11: 1 | E11: 1 | I11: 1 | J11: 2 | N11: 1 | O11: =SUM(C11:N11) -> 6
A12: 5 | B12: Incendio vehicular | I12: 1 | O12: =SUM(C12:N12) -> 1
A13: 6 | B13: Incendio de líquidos inflamables | O13: =SUM(C13:N13) -> 0
A14: 7 | B14: Incendio de Gases o Gas domiciliario | O14: =SUM(C14:N14) -> 0
A15: 8 | B15: Incendio en Cilindro de Gas Vehicular | O15: =SUM(C15:N15) -> 0
A16: 9 | B16: Incendio | O16: =SUM(C16:N16) -> 0
A17: 10 | B17: Incendio eléctrico | C17: 1 | D17: 2 | G17: 2 | H17: 1 | J17: 1 | O17: =SUM(C17:N17) -> 7
A18: 11 | B18: Incendio Aéreo | O18: =SUM(C18:N18) -> 0
A19: 12 | B19: Fuegos aislados o basuras | C19: 2 | D19: 3 | H19: 1 | I19: 1 | O19: =SUM(C19:N19) -> 7
B20: SUB-TOTALES | C20: =SUM(C8:C19) -> 18 | D20: =SUM(D8:D19) -> 16 | E20: =SUM(E8:E19) -> 2 | F20: =SUM(F8:F19) -> 0 | G20: =SUM(G8:G19) -> 3 | H20: =SUM(H8:H19) -> 2 | I20: =SUM(I8:I19) -> 4 | J20: =SUM(J8:J19) -> 11 | ... N20: =SUM(N8:N19) -> 1 | O20: =SUM(C20:N20) -> 66
B21: RESCATE EN TODAS SUS MODALIDADES
A22: 13 | B22: Rescates (Actividad) en Accidentes de tránsito | H22: 1 | O22: =SUM(C22:N22) -> 1
A23: 14 | B23: Accidentes de tránsito atendidos sin la actividad de rescate | C23: 2 | H23: 2 | O23: =SUM(C23:N23) -> 4
A24: 15 | B24: Otros Rescates de emergencias diferentes a accidente de tránsito | F24: 1 | H24: 1 | N24: 1 | O24: =SUM(C24:N24) -> 3
A25: 16 | B25: Salvamento en mina | O25: =SUM(C25:N25) -> 0
A26: 17 | B26: Rescate de animal | E26: 1 | G26: 4 | H26: 3 | I26: 2 | J26: 2 | K26: 3 | L26: 3 | M26: 1 | N26: 2 | O26: =SUM(C26:N26) -> 21
A27: 18 | B27: Auxilio a electrocutado | O27: =SUM(C27:N27) -> 0
A28: 19 | B28: Rescate en ascensor | O28: =SUM(C28:N28) -> 0
A29: 20 | B29: Rescate con apertura de puerta | O29: =SUM(C29:N29) -> 0
A30: 21 | B30: Rescate Acuático | O30: =SUM(C30:N30) -> 0
A31: 22 | B31: Rescate en Estructura Colapsada | O31: =SUM(C31:N31) -> 0
A32: 23 | B32: Rescate en Altura | M32: 1 | O32: =SUM(C32:N32) -> 1
A33: 24 | B33: Rescate en espacio confinado | O33: =SUM(C33:N33) -> 0
A34: 25 | B34: Rescate en Accidente Aéreo | O34: =SUM(C34:N34) -> 0
A35: 26 | B35: Rescate en media y alta Montaña | C35: 1 | O35: =SUM(C35:N35) -> 1
A36: 27 | B36: Rescate con exposición de Materiales peligrosos | O36: =SUM(C36:N36) -> 0
B37: SUB-TOTALES | C37: =SUM(C22:C36) -> 3 | D37: =SUM(D22:D36) -> 0 | E37: =SUM(E22:E36) -> 1 | F37: =SUM(F22:F36) -> 1 | G37: =SUM(G22:G36) -> 4 | H37: =SUM(H22:H36) -> 7 | I37: =SUM(I22:I36) -> 2 | J37: =SUM(J22:J36) -> 2 | ... N37: =SUM(N22:N36) -> 3 | O37: =SUM(C37:N37) -> 31
B38: ATENCION DE MATERIALES PELIGROSOS
A39: 28 | B39: Incidentes con materiales peligrosos en vehículos accidentados | O39: =SUM(C39:N39) -> 0
A40: 29 | B40: Incidente de materiales peligrosos (otros) | D40: 1 | O40: =SUM(C40:N40) -> 1
A41: 30 | B41: Fuga de gas GLP | O41: =SUM(C41:N41) -> 0
A42: 31 | B42: Fuga de gas GN | C42: 2 | D42: 1 | E42: 3 | F42: 3 | I42: 1 | K42: 1 | M42: 1 | N42: 3 | O42: =SUM(C42:N42) -> 15
A43: 32 | B43: Derrames de combustible en vía pública | G43: 1 | H43: 1 | O43: =SUM(C43:N43) -> 2
B44: SUB-TOTALES | C44: =SUM(C39:C43) -> 2 | D44: =SUM(D39:D43) -> 2 | E44: =SUM(E39:E43) -> 3 | F44: =SUM(F39:F43) -> 3 | G44: =SUM(G39:G43) -> 1 | H44: =SUM(H39:H43) -> 1 | I44: =SUM(I39:I43) -> 1 | J44: =SUM(J39:J43) -> 0 | ... N44: =SUM(N39:N43) -> 3 | O44: =SUM(C44:N44) -> 18
B45: ATENCION DE OTROS INCIDENTES
A46: 33 | B46: Colapsos en estructura | E46: 1 | O46: =SUM(C46:N46) -> 1
A47: 34 | B47: Derrumbes y deslizamientos (Completar cuadro anexo) | H47: 1 | O47: =SUM(C47:N47) -> 1
A48: 35 | B48: Explosiones por pólvora | O48: =SUM(C48:N48) -> 0
A49: 36 | B49: Explosiones de ollas a presión | O49: =SUM(C49:N49) -> 0
A50: 37 | B50: Otras explosiones | O50: =SUM(C50:N50) -> 0
A51: 38 | B51: Inundaciones Atendidas (Completar cuadro anexo) | E51: 4 | F51: 20 | G51: 1 | I51: 3 | L51: 8 | M51: 4 | O51: =SUM(C51:N51) -> 40
A52: 39 | B52: Caídas de árboles, postes de energía y otros | D52: 1 | E52: 4 | F52: 11 | G52: 3 | H52: 1 | I52: 11 | J52: 1 | K52: 2 | M52: 3 | O52: =SUM(C52:N52) -> 37
A53: 40 | B53: Atención de abejas | C53: 18 | D53: 16 | E53: 24 | F53: 4 | G53: 1 | H53: 3 | I53: 3 | J53: 2 | K53: 8 | L53: 10 | M53: 2 | N53: 3 | O53: =SUM(C53:N53) -> 94
A54: 41 | B54: Recuperación de cadáver | O54: =SUM(C54:N54) -> 0
A55: 42 | B55: Vendaval | I55: 3 | O55: =SUM(C55:N55) -> 3
A56: 43 | B56: Otras emergencias atendidas no descritas | E56: 1 | F56: 1 | H56: 1 | M56: 1 | N56: 1 | O56: =SUM(C56:N56) -> 5
B57: SUB-TOTALES | C57: =SUM(C46:C56) -> 18 | D57: =SUM(D46:D56) -> 17 | E57: =SUM(E46:E56) -> 34 | F57: =SUM(F46:F56) -> 36 | G57: =SUM(G46:G56) -> 5 | H57: =SUM(H46:H56) -> 6 | I57: =SUM(I46:I56) -> 20 | J57: =SUM(J46:J56) -> 3 | ... N57: =SUM(N46:N56) -> 4 | O57: =SUM(C57:N57) -> 181
B58: ATENCION PREHOSPITALARIA
A59: 44 | B59: Atención APH de heridos en accidente de transito (Sin transporte - No. De personas atendidas) | C59: 2 | E59: 2 | F59: 1 | H59: 3 | K59: 1 | O59: =SUM(C59:N59) -> 9
A60: 45 | B60: Transporte de heridos en accidente de transito. (No. de transportados en vehículos Institucionales de Bomberos) | F60: 1 | O60: =SUM(C60:N60) -> 1
A61: 46 | B61: Atención APH de heridos diferente a accidente de tránsito | C61: 1 | D61: 1 | F61: 3 | G61: 2 | H61: 4 | J61: 1 | L61: 1 | O61: =SUM(C61:N61) -> 13
A62: 47 | B62: Transporte de heridos diferente a accidente de transito | F62: 2 | H62: 2 | O62: =SUM(C62:N62) -> 4
A63: 48 | B63: Auxilio a enfermo | K63: 1 | O63: =SUM(C63:N63) -> 1
A64: 49 | B64: Trabajo de parto | O64: =SUM(C64:N64) -> 0
B65: SUB-TOTALES | C65: =SUM(C59:C64) -> 3 | D65: =SUM(D59:D64) -> 1 | E65: =SUM(E59:E64) -> 2 | F65: =SUM(F59:F64) -> 7 | G65: =SUM(G59:G64) -> 2 | H65: =SUM(H59:H64) -> 9 | I65: =SUM(I59:I64) -> 0 | J65: =SUM(J59:J64) -> 1 | ... N65: =SUM(N59:N64) -> 0 | O65: =SUM(C65:N65) -> 28
B66: TOTAL DE INCIDENTES ATENDIDOS | C66: =SUM(C65+C57+C44+C37+C20) -> 44 | D66: =SUM(D65+D57+D44+D37+D20) -> 36 | E66: =SUM(E65+E57+E44+E37+E20) -> 42 | F66: =SUM(F65+F57+F44+F37+F20) -> 47 | G66: =SUM(G65+G57+G44+G37+G20) -> 15 | H66: =SUM(H65+H57+H44+H37+H20) -> 25 | I66: =SUM(I65+I57+I44+I37+I20) -> 27 | J66: =SUM(J65+J57+J44+J37+J20) -> 17 | ... N66: =SUM(N65+N57+N44+N37+N20) -> 11 | O66: =SUM(C66:N66) -> 324
B67: LABORES DE PREVENCION Y OTROS
A68: 1 | B68: Inspecciones de prevención y seguridad | C68: 43 | D68: 72 | E68: 10 | F68: 10 | G68: 11 | H68: 27 | I68: 22 | J68: 34 | K68: 31 | L68: 28 | M68: 30 | N68: 16 | O68: =SUM(C68:N68) -> 334
A69: 2 | B69: Realización de Pruebas Hidráulicas | O69: =SUM(C69:N69) -> 0
A70: 3 | B70: Participación en Eventos masivos y no masivos | C70: 1 | D70: 1 | E70: 1 | F70: 3 | I70: 2 | K70: 1 | O70: =SUM(C70:N70) -> 9
A71: 4 | B71: Participación en Eventos pirotécnicos | F71: 1 | N71: 1 | O71: =SUM(C71:N71) -> 2
A72: 5 | B72: Labores sociales | C72: 2 | D72: 1 | F72: 8 | G72: 3 | H72: 4 | J72: 1 | K72: 4 | L72: 5 | O72: =SUM(C72:N72) -> 28
A73: 6 | B73: Labores de prevención diversas | C73: 3 | E73: 6 | F73: 2 | H73: 1 | I73: 1 | J73: 1 | K73: 10 | L73: 1 | M73: 1 | N73: 1 | O73: =SUM(C73:N73) -> 27
A74: 7 | B74: Falsas alarmas por diversos casos | C74: 1 | D74: 2 | J74: 3 | K74: 1 | L74: 3 | O74: =SUM(C74:N74) -> 10
A75: 8 | B75: Actividades de Evacuaciones | L75: 1 | O75: =SUM(C75:N75) -> 1
A76: 9 | B76: Suministro de Agua a Comunidades u otros | C76: 1 | F76: 1 | G76: 1 | O76: =SUM(C76:N76) -> 3
B77: TOTAL LABORES DE PREVENCIÓN Y OTROS | C77: =SUM(C68:C76) -> 51 | D77: =SUM(D68:D76) -> 76 | E77: =SUM(E68:E76) -> 17 | F77: =SUM(F68:F76) -> 25 | G77: =SUM(G68:G76) -> 15 | H77: =SUM(H68:H76) -> 32 | I77: =SUM(I68:I76) -> 25 | J77: =SUM(J68:J76) -> 39 | ... N77: =SUM(N68:N76) -> 18 | O77: =SUM(C77:N77) -> 414
B78: ACUMULADO TOTAL DE EMERGENCIAS EVENTOS Y LABORES DE PREVENCIÓN AÑO | C78: =SUM(C66+C77) -> 95 | D78: =SUM(D66+D77) -> 112 | E78: =SUM(E66+E77) -> 59 | F78: =SUM(F66+F77) -> 72 | G78: =SUM(G66+G77) -> 30 | H78: =SUM(H66+H77) -> 57 | I78: =SUM(I66+I77) -> 52 | J78: =SUM(J66+J77) -> 56 | ... N78: =SUM(N66+N77) -> 29 | O78: =SUM(C78:N78) -> 738
B80: CUADROS ANEXOS
B81: DERRUMBES O DESLIZAMIENTOS
A82: a | B82: Cobertura afectada metros2 o Hectáreas | H82: 180
A83: b | B83: Duración de la afectación por el movimiento en masa | H83: 7
A84: c | B84: Viviendas o Instalaciones afectadas | H84: 2
A85: d | B85: Metros Cúbicos de la afectación | H85: 14
A86: e | B86: No. De afectados por el movimiento en masa (No. PERSONAS o No. FAMILIAS) | H86: 8
B87: SUB-TOTALES | C87: =SUM(C82:C86) -> 0 | D87: =SUM(D82:D86) -> 0 | E87: =SUM(E82:E86) -> 0 | F87: =SUM(F82:F86) -> 0 | G87: =SUM(G82:G86) -> 0 | H87: =SUM(H82:H86) -> 211 | I87: =SUM(I82:I86) -> 0 | J87: =SUM(J82:J86) -> 0 | ... O87: =SUM(O82:O86) -> 0
B88: INUNDACIONES
A89: a | B89: Cobertura afectada metros2 o Hectáreas | F89: 1 | M89: 55
A90: b | B90: Duración de la inundación | E90: 4 | F90: 2 | I90: 1 | L90: 3 | M90: 4
A91: c | B91: Viviendas o Instalaciones afectadas | E91: 4 | F91: 1 | I91: 3 | L91: 8 | M91: 4
A92: d | B92: No. De afectados por la inundación- (N° PERSONAS O N° FAMILIAS) | E92: 15 | F92: 3 | I92: 7 | L92: 24 | M92: 12
B93: SUB-TOTALES | C93: =SUM(C89:C92) -> 0 | D93: =SUM(D89:D92) -> 0 | E93: =SUM(E89:E92) -> 23 | F93: =SUM(F89:F92) -> 7 | G93: =SUM(G89:G92) -> 0 | H93: =SUM(H89:H92) -> 0 | I93: =SUM(I89:I92) -> 11 | J93: =SUM(J89:J92) -> 0 | ... O93: =SUM(O89:O92) -> 0

Sheet 2018
B2: INFORME DE SINIESTRALIDAD DEPARTAMENTO DEL VALLE DEL CAUCA - AÑO 2018
C5: PERIODO ( Enero 01 al 31 de Diciembre 2018 ) | N5: CVB DE:
A6: ITEM | B6: INCIDENTE | C6: ENE | D6: FEB | E6: MAR | F6: ABR | G6: MAY | H6: JUN | I6: JUL | J6: AGO | K6: SEP | L6: OCT | M6: NOV | N6: DIC | O6: TOTAL
B7: GESTION DEL RIESGO DE INCENDIOS
A8: 1 | B8: Incendio estructural | D8: 1 | F8: 1 | L8: 2 | N8: 2 | O8: =SUM(C8:N8) -> 6
A9: 2 | B9: Incendio forestal rural | E9: 2 | H9: 1 | I9: 4 | J9: 3 | K9: 1 | L9: 1 | N9: 1 | O9: =SUM(C9:N9) -> 13
A10: 3 | B10: Incendio forestal urbano | E10: 2 | H10: 1 | I10: 6 | J10: 1 | K10: 3 | L10: 1 | N10: 3 | O10: =SUM(C10:N10) -> 17
A11: 4 | B11: Incendio Agrícola | E11: 2 | J11: 4 | K11: 2 | M11: 1 | O11: =SUM(C11:N11) -> 9
A12: 5 | B12: Incendio vehicular | C12: 1 | E12: 1 | F12: 1 | N12: 1 | O12: =SUM(C12:N12) -> 4
A13: 6 | B13: Incendio de líquidos inflamables | O13: =SUM(C13:N13) -> 0
A14: 7 | B14: Incendio de Gases o Gas domiciliario | N14: 1 | O14: =SUM(C14:N14) -> 1
A15: 8 | B15: Incendio en Cilindro de Gas Vehicular | O15: =SUM(C15:N15) -> 0
A16: 9 | B16: Incendio | O16: =SUM(C16:N16) -> 0
A17: 10 | B17: Incendio eléctrico | F17: 2 | G17: 2 | J17: 1 | O17: =SUM(C17:N17) -> 5
A18: 11 | B18: Incendio Aéreo | O18: =SUM(C18:N18) -> 0
A19: 12 | B19: Fuegos aislados o basuras | D19: 1 | E19: 1 | G19: 1 | J19: 2 | K19: 1 | O19: =SUM(C19:N19) -> 6
B20: SUB-TOTALES | C20: =SUM(C8:C19) -> 1 | D20: =SUM(D8:D19) -> 2 | E20: =SUM(E8:E19) -> 8 | F20: =SUM(F8:F19) -> 4 | G20: =SUM(G8:G19) -> 3 | H20: =SUM(H8:H19) -> 2 | I20: =SUM(I8:I19) -> 10 | J20: =SUM(J8:J19) -> 11 | ... N20: =SUM(N8:N19) -> 8 | O20: =SUM(C20:N20) -> 61
B21: RESCATE EN TODAS SUS MODALIDADES
A22: 13 | B22: Rescates (Actividad) en Accidentes de tránsito | O22: =SUM(C22:N22) -> 0
A23: 14 | B23: Accidentes de tránsito atendidos sin la actividad de rescate | L23: 1 | M23: 1 | O23: =SUM(C23:N23) -> 2
A24: 15 | B24: Otros Rescates de emergencias diferentes a accidente de tránsito | D24: 2 | E24: 2 | J24: 2 | O24: =SUM(C24:N24) -> 6
A25: 16 | B25: Salvamento en mina | O25: =SUM(C25:N25) -> 0
A26: 17 | B26: Rescate de animal | C26: 1 | D26: 1 | E26: 1 | G26: 1 | I26: 2 | K26: 1 | L26: 2 | M26: 1 | N26: 2 | O26: =SUM(C26:N26) -> 12
A27: 18 | B27: Auxilio a electrocutado | O27: =SUM(C27:N27) -> 0
A28: 19 | B28: Rescate en ascensor | O28: =SUM(C28:N28) -> 0
A29: 20 | B29: Rescate con apertura de puerta | O29: =SUM(C29:N29) -> 0
A30: 21 | B30: Rescate Acuático | E30: 1 | O30: =SUM(C30:N30) -> 1
A31: 22 | B31: Rescate en Estructura Colapsada | O31: =SUM(C31:N31) -> 0
A32: 23 | B32: Rescate en Altura | O32: =SUM(C32:N32) -> 0
A33: 24 | B33: Rescate en espacio confinado | O33: =SUM(C33:N33) -> 0
A34: 25 | B34: Rescate en Accidente Aéreo | O34: =SUM(C34:N34) -> 0
A35: 26 | B35: Rescate en media y alta Montaña | O35: =SUM(C35:N35) -> 0
A36: 27 | B36: Rescate con exposición de Materiales peligrosos | O36: =SUM(C36:N36) -> 0
B37: SUB-TOTALES | C37: =SUM(C22:C36) -> 1 | D37: =SUM(D22:D36) -> 3 | E37: =SUM(E22:E36) -> 4 | F37: =SUM(F22:F36) -> 0 | G37: =SUM(G22:G36) -> 1 | H37: =SUM(H22:H36) -> 0 | I37: =SUM(I22:I36) -> 2 | J37: =SUM(J22:J36) -> 2 | ... N37: =SUM(N22:N36) -> 2 | O37: =SUM(C37:N37) -> 21
B38: ATENCION DE MATERIALES PELIGROSOS
A39: 28 | B39: Incidentes con materiales peligrosos en vehículos accidentados | O39: =SUM(C39:N39) -> 0
A40: 29 | B40: Incidente de materiales peligrosos (otros) | J40: 1 | O40: =SUM(C40:N40) -> 1
A41: 30 | B41: Fuga de gas GLP | H41: 1 | O41: =SUM(C41:N41) -> 1
A42: 31 | B42: Fuga de gas GN | E42: 2 | F42: 1 | G42: 2 | K42: 2 | O42: =SUM(C42:N42) -> 7
A43: 32 | B43: Derrames de combustible en vía pública | C43: 1 | J43: 1 | O43: =SUM(C43:N43) -> 2
B44: SUB-TOTALES | C44: =SUM(C39:C43) -> 1 | D44: =SUM(D39:D43) -> 0 | E44: =SUM(E39:E43) -> 2 | F44: =SUM(F39:F43) -> 1 | G44: =SUM(G39:G43) -> 2 | H44: =SUM(H39:H43) -> 1 | I44: =SUM(I39:I43) -> 0 | J44: =SUM(J39:J43) -> 2 | ... N44: =SUM(N39:N43) -> 0 | O44: =SUM(C44:N44) -> 11
B45: ATENCION DE OTROS INCIDENTES
A46: 33 | B46: Colapsos en estructura | O46: =SUM(C46:N46) -> 0
A47: 34 | B47: Derrumbes y deslizamientos (Completar cuadro anexo) | O47: =SUM(C47:N47) -> 0
A48: 35 | B48: Explosiones por pólvora | O48: =SUM(C48:N48) -> 0
A49: 36 | B49: Explosiones de ollas a presión | O49: =SUM(C49:N49) -> 0
A50: 37 | B50: Otras explosiones | H50: 1 | M50: 1 | O50: =SUM(C50:N50) -> 2
A51: 38 | B51: Inundaciones Atendidas (Completar cuadro anexo) | G51: 1 | H51: 1 | L51: 1 | O51: =SUM(C51:N51) -> 3
A52: 39 | B52: Caídas de árboles, postes de energía y otros | E52: 1 | O52: =SUM(C52:N52) -> 1
A53: 40 | B53: Atención de abejas | C53: 6 | D53: 3 | E53: 8 | F53: 6 | G53: 3 | H53: 2 | I53: 2 | J53: 9 | K53: 2 | L53: 4 | M53: 4 | N53: 10 | O53: =SUM(C53:N53) -> 59
A54: 41 | B54: Recuperación de cadáver | C54: 1 | O54: =SUM(C54:N54) -> 1
A55: 42 | B55: Vendaval | O55: =SUM(C55:N55) -> 0
A56: 43 | B56: Otras emergencias atendidas no descritas | F56: 1 | I56: 3 | O56: =SUM(C56:N56) -> 4
B57: SUB-TOTALES | C57: =SUM(C46:C56) -> 7 | D57: =SUM(D46:D56) -> 3 | E57: =SUM(E46:E56) -> 9 | F57: =SUM(F46:F56) -> 7 | G57: =SUM(G46:G56) -> 4 | H57: =SUM(H46:H56) -> 4 | I57: =SUM(I46:I56) -> 5 | J57: =SUM(J46:J56) -> 9 | ... N57: =SUM(N46:N56) -> 10 | O57: =SUM(C57:N57) -> 70
B58: ATENCION PREHOSPITALARIA
A59: 44 | B59: Atención APH de heridos en accidente de transito (Sin transporte - No. De personas atendidas) | D59: 2 | E59: 4 | F59: 3 | G59: 5 | I59: 1 | K59: 1 | L59: 1 | M59: 3 | O59: =SUM(C59:N59) -> 20
A60: 45 | B60: Transporte de heridos en accidente de transito. (No. de transportados en vehículos Institucionales de Bomberos) | L60: 1 | O60: =SUM(C60:N60) -> 1
A61: 46 | B61: Atención APH de heridos diferente a accidente de tránsito | C61: 3 | H61: 1 | I61: 1 | K61: 1 | M61: 1 | N61: 1 | O61: =SUM(C61:N61) -> 8
A62: 47 | B62: Transporte de heridos diferente a accidente de transito | O62: =SUM(C62:N62) -> 0
A63: 48 | B63: Auxilio a enfermo | C63: 1 | G63: 1 | O63: =SUM(C63:N63) -> 2
A64: 49 | B64: Trabajo de parto | O64: =SUM(C64:N64) -> 0
B65: SUB-TOTALES | C65: =SUM(C59:C64) -> 4 | D65: =SUM(D59:D64) -> 2 | E65: =SUM(E59:E64) -> 4 | F65: =SUM(F59:F64) -> 3 | G65: =SUM(G59:G64) -> 6 | H65: =SUM(H59:H64) -> 1 | I65: =SUM(I59:I64) -> 2 | J65: =SUM(J59:J64) -> 0 | ... N65: =SUM(N59:N64) -> 1 | O65: =SUM(C65:N65) -> 31
B66: TOTAL DE INCIDENTES ATENDIDOS | C66: =SUM(C65+C57+C44+C37+C20) -> 14 | D66: =SUM(D65+D57+D44+D37+D20) -> 10 | E66: =SUM(E65+E57+E44+E37+E20) -> 27 | F66: =SUM(F65+F57+F44+F37+F20) -> 15 | G66: =SUM(G65+G57+G44+G37+G20) -> 16 | H66: =SUM(H65+H57+H44+H37+H20) -> 8 | I66: =SUM(I65+I57+I44+I37+I20) -> 19 | J66: =SUM(J65+J57+J44+J37+J20) -> 24 | ... N66: =SUM(N65+N57+N44+N37+N20) -> 21 | O66: =SUM(C66:N66) -> 194
B67: LABORES DE PREVENCION Y OTROS
A68: 1 | B68: Inspecciones de prevención y seguridad | C68: 26 | D68: 17 | E68: 14 | F68: 15 | G68: 19 | H68: 10 | I68: 11 | J68: 4 | K68: 6 | L68: 15 | M68: 9 | N68: 5 | O68: =SUM(C68:N68) -> 151
A69: 2 | B69: Realización de Pruebas Hidráulicas | O69: =SUM(C69:N69) -> 0
A70: 3 | B70: Participación en Eventos masivos y no masivos | D70: 1 | E70: 3 | F70: 1 | G70: 3 | H70: 2 | I70: 4 | J70: 2 | K70: 1 | L70: 2 | N70: 3 | O70: =SUM(C70:N70) -> 22
A71: 4 | B71: Participación en Eventos pirotécnicos | H71: 1 | O71: =SUM(C71:N71) -> 1
A72: 5 | B72: Labores sociales | C72: 2 | D72: 3 | E72: 1 | F72: 1 | G72: 4 | H72: 4 | I72: 2 | J72: 3 | K72: 1 | L72: 3 | M72: 1 | N72: 2 | O72: =SUM(C72:N72) -> 27
A73: 6 | B73: Labores de prevención diversas | E73: 7 | F73: 6 | G73: 1 | I73: 1 | L73: 3 | O73: =SUM(C73:N73) -> 18
A74: 7 | B74: Falsas alarmas por diversos casos | C74: 3 | D74: 1 | F74: 1 | G74: 1 | H74: 3 | I74: 2 | K74: 1 | O74: =SUM(C74:N74) -> 12
A75: 8 | B75: Actividades de Evacuaciones | L75: 1 | O75: =SUM(C75:N75) -> 1
A76: 9 | B76: Suministro de Agua a Comunidades u otros | I76: 5 | J76: 1 | K76: 2 | O76: =SUM(C76:N76) -> 8
B77: TOTAL LABORES DE PREVENCIÓN Y OTROS | C77: =SUM(C68:C76) -> 31 | D77: =SUM(D68:D76) -> 22 | E77: =SUM(E68:E76) -> 25 | F77: =SUM(F68:F76) -> 24 | G77: =SUM(G68:G76) -> 28 | H77: =SUM(H68:H76) -> 20 | I77: =SUM(I68:I76) -> 25 | J77: =SUM(J68:J76) -> 10 | ... N77: =SUM(N68:N76) -> 10 | O77: =SUM(C77:N77) -> 240
B78: ACUMULADO TOTAL DE EMERGENCIAS EVENTOS Y LABORES DE PREVENCIÓN AÑO | C78: =SUM(C66+C77) -> 45 | D78: =SUM(D66+D77) -> 32 | E78: =SUM(E66+E77) -> 52 | F78: =SUM(F66+F77) -> 39 | G78: =SUM(G66+G77) -> 44 | H78: =SUM(H66+H77) -> 28 | I78: =SUM(I66+I77) -> 44 | J78: =SUM(J66+J77) -> 34 | ... N78: =SUM(N66+N77) -> 31 | O78: =SUM(C78:N78) -> 434
B80: CUADROS ANEXOS
B81: DERRUMBES O DESLIZAMIENTOS
A82: a | B82: Cobertura afectada metros2 o Hectáreas
A83: b | B83: Duración de la afectación por el movimiento en masa
A84: c | B84: Viviendas o Instalaciones afectadas
A85: d | B85: Metros Cúbicos de la afectación
A86: e | B86: No. De afectados por el movimiento en masa (No. PERSONAS o No. FAMILIAS)
B87: SUB-TOTALES | C87: =SUM(C82:C86) -> 0 | D87: =SUM(D82:D86) -> 0 | E87: =SUM(E82:E86) -> 0 | F87: =SUM(F82:F86) -> 0 | G87: =SUM(G82:G86) -> 0 | H87: =SUM(H82:H86) -> 0 | I87: =SUM(I82:I86) -> 0 | J87: =SUM(J82:J86) -> 0 | ... O87: =SUM(O82:O86) -> 0
B88: INUNDACIONES
A89: a | B89: Cobertura afectada metros2 o Hectáreas | G89: 20 m2 | L89: 10 m2
A90: b | B90: Duración de la inundación
A91: c | B91: Viviendas o Instalaciones afectadas
A92: d | B92: No. De afectados por la inundación- (N° PERSONAS O N° FAMILIAS) | G92: 4 | L92: 2
B93: SUB-TOTALES | C93: =SUM(C89:C92) -> 0 | D93: =SUM(D89:D92) -> 0 | E93: =SUM(E89:E92) -> 0 | F93: =SUM(F89:F92) -> 0 | G93: =SUM(G89:G92) -> 4 | H93: =SUM(H89:H92) -> 0 | I93: =SUM(I89:I92) -> 0 | J93: =SUM(J89:J92) -> 0 | ... O93: =SUM(O89:O92) -> 0

Sheet 2017
A1: INFORME DE SINIESTRALIDAD DEPARTAMENTO DEL VALLE DEL CAUCA - AÑO 2017
A2: CUERPO DE BOMBEROS VOLUNTARIOS DE LA UNION
C3: PERIODO AÑO 2017 (Enero 1 al 31 de Diciembre)
A4: ITEM | B4: INCIDENTE | C4: ENERO | D4: FEBRERO | E4: MARZO | F4: ABRL | G4: MAYO | H4: JUNIO | I4: JULIO | J4: AGOSTO | K4: SEPTIEMBRE | L4: OCTUBRE | M4: NOMVIEMBRE | N4: DICIEMBRE | O4: TOTAL
A5: I. | B5: GESTION DEL RISGO DE INCENDIOS
A6: 1 | B6: Incendio estructural | C6: 2 | D6: 2 | E6: 1 | H6: 1 | I6: 3 | J6: 2 | K6: 2 | N6: 2 | O6: =SUM(C6:N6) -> 15
A7: 2 | B7: Incendio forestal rural | C7: 3 | D7: 5 | J7: 7 | L7: 1 | O7: =SUM(C7:N7) -> 16
A8: 3 | B8: Incendio forestal urbano | D8: 2 | H8: 1 | I8: 3 | J8: 4 | N8: 3 | O8: =SUM(C8:N8) -> 13
A9: 4 | B9: Incendio vehicular | D9: 1 | G9: 1 | I9: 1 | O9: =SUM(C9:N9) -> 3
A10: 5 | B10: Incendio de líquidos inflamables o gases | O10: =SUM(C10:N10) -> 0
A11: 6 | B11: Incendio Gas domiciliario | O11: =SUM(C11:N11) -> 0
A12: 7 | B12: Incendio en Cilindro de Gas | O12: =SUM(C12:N12) -> 0
A13: 8 | B13: Incendio eléctrico | E13: 1 | M13: 1 | O13: =SUM(C13:N13) -> 2
A14: 9 | B14: Incendio Agricola | H14: 1 | O14: =SUM(C14:N14) -> 1
A15: 10 | B15: Incendio Aereo | O15: =SUM(C15:N15) -> 0
A16: 11 | B16: Fuegos aislados o basuras | C16: 1 | M16: 1 | O16: =SUM(C16:N16) -> 2
B17: SUB-TOTALES | C17: =SUM(C6:C16) -> 6 | D17: =SUM(D6:D16) -> 10 | E17: =SUM(E6:E16) -> 2 | F17: =SUM(F6:F16) -> 0 | G17: =SUM(G6:G16) -> 1 | H17: =SUM(H6:H16) -> 3 | I17: =SUM(I6:I16) -> 7 | J17: =SUM(J6:J16) -> 13 | ... O17: =SUM(O6:O16) -> 52
A18: II. | B18: RESCATE EN TODAS SUS MODALIDADES
A19: 12 | B19: Rescate, atención y/o traslado de lesionado en Accidentes de tránsito | D19: 3 | F19: 1 | O19: =SUM(C19:N19) -> 4
A20: 13 | B20: Salvamento en mina | O20: =SUM(C20:N20) -> 0
A21: 14 | B21: Rescate de animal | D21: 2 | E21: 1 | J21: 1 | K21: 3 | O21: =SUM(C21:N21) -> 7
A22: 15 | B22: Auxilio a electrocutado | O22: =SUM(C22:N22) -> 0
A23: 16 | B23: Rescate en ascensor | O23: =SUM(C23:N23) -> 0
A24: 17 | B24: Rescate con apertura de puerta | E24: 1 | O24: =SUM(C24:N24) -> 1
A25: 18 | B25: Rescate Acuatico | O25: =SUM(C25:N25) -> 0
A26: 19 | B26: Rescate en Estructura Colapsada | E26: 1 | O26: =SUM(C26:N26) -> 1
A27: 20 | B27: Rescate en Altura | I27: 1 | O27: =SUM(C27:N27) -> 1
A28: 21 | B28: Rescate en espacio confinado | O28: =SUM(C28:N28) -> 0
A29: 22 | B29: Rescate en Accidente Aéreo | O29: =SUM(C29:N29) -> 0
A30: 23 | B30: Rescte en media y alta Montaña | O30: =SUM(C30:N30) -> 0
A31: 24 | B31: Rescate con exposición de Materiales peligrosos | O31: =SUM(C31:N31) -> 0
A32: 25 | B32: Otros auxilios y/o rescates | K32: 1 | O32: =SUM(C32:N32) -> 1
B33: SUB-TOTALES | C33: =SUM(C19:C32) -> 0 | D33: =SUM(D19:D32) -> 5 | E33: =SUM(E19:E32) -> 3 | F33: =SUM(F19:F32) -> 1 | G33: =SUM(G19:G32) -> 0 | H33: =SUM(H19:H32) -> 0 | I33: =SUM(I19:I32) -> 1 | J33: =SUM(J19:J32) -> 1 | ... O33: =SUM(O19:O32) -> 15
A34: III. | B34: ATENCION DE MATERIALES PELIGROSOS
A35: 26 | B35: Incidentes con materiales peligrosos | J35: 1 | O35: =SUM(C35:N35) -> 1
A36: 27 | B36: Fuga de gas GLP | C36: 1 | O36: =SUM(C36:N36) -> 1
A37: 28 | B37: Fuga de gas GNC | C37: 2 | E37: 1 | F37: 1 | H37: 2 | I37: 2 | K37: 2 | L37: 2 | M37: 3 | N37: 1 | O37: =SUM(C37:N37) -> 16
A38: 29 | B38: Derrames de combustible en vía pública | D38: 1 | N38: 1 | O38: =SUM(C38:N38) -> 2
B39: SUB-TOTALES | C39: =SUM(C35:C38) -> 3 | D39: =SUM(D35:D38) -> 1 | E39: =SUM(E35:E38) -> 1 | F39: =SUM(F35:F38) -> 1 | G39: =SUM(G35:G38) -> 0 | H39: =SUM(H35:H38) -> 2 | I39: =SUM(I35:I38) -> 2 | J39: =SUM(J35:J38) -> 1 | ... O39: =SUM(O35:O38) -> 20
A40: IV. | B40: ATENCION DE OTROS INCIDENTES
A41: 30 | B41: Colapsos en estructura | E41: 1 | O41: =SUM(C41:N41) -> 1
A42: 31 | B42: Derrumbes y deslizamientos | M42: 2 | O42: =SUM(C42:N42) -> 2
A43: 32 | B43: Explosiones por pólvora | O43: =SUM(C43:N43) -> 0
A44: 33 | B44: Explosiones de ollas a presión | O44: =SUM(C44:N44) -> 0
A45: 34 | B45: Otras explosiones | M45: 1 | O45: =SUM(C45:N45) -> 1
A46: 35 | B46: Inundaciones | F46: 1 | H46: 1 | J46: 1 | K46: 2 | M46: 7 | O46: =SUM(C46:N46) -> 12
A47: 36 | B47: Caídas de árboles, postes de energía y otros | C47: 1 | E47: 1 | F47: 4 | K47: 1 | L47: 2 | M47: 2 | O47: =SUM(C47:N47) -> 11
A48: 37 | B48: Atención de abejas | C48: 5 | D48: 4 | E48: 11 | F48: 6 | G48: 3 | H48: 2 | I48: 6 | J48: 4 | L48: 2 | M48: 3 | O48: =SUM(C48:N48) -> 46
A49: 38 | B49: Recuperación de cadáver | E49: 1 | O49: =SUM(C49:N49) -> 1
B50: SUB-TOTALES | C50: =SUM(C41:C49) -> 6 | D50: =SUM(D41:D49) -> 4 | E50: =SUM(E41:E49) -> 14 | F50: =SUM(F41:F49) -> 11 | G50: =SUM(G41:G49) -> 3 | H50: =SUM(H41:H49) -> 3 | I50: =SUM(I41:I49) -> 6 | J50: =SUM(J41:J49) -> 5 | ... O50: =SUM(O41:O49) -> 74
A51: V. | B51: ATENCION PREHOSPITALARIA
A52: 39 | B52: Atención y/o transporte de herido | H52: 2 | K52: 5 | L52: 3 | M52: 4 | N52: 1 | O52: =SUM(C52:N52) -> 15
A53: 40 | B53: Auxilio y/o transporte de enfermo | J53: 1 | K53: 2 | O53: =SUM(C53:N53) -> 3
B54: SUB-TOTALES | C54: =SUM(C52:C53) -> 0 | D54: =SUM(D52:D53) -> 0 | E54: =SUM(E52:E53) -> 0 | F54: =SUM(F52:F53) -> 0 | G54: =SUM(G52:G53) -> 0 | H54: =SUM(H52:H53) -> 2 | I54: =SUM(I52:I53) -> 0 | J54: =SUM(J52:J53) -> 1 | ... O54: =SUM(O52:O53) -> 18
B55: TOTAL DE INCIDENTES ATENDIDOS | C55: =SUM(C54+C50+C39+C33+C17) -> 15 | D55: =SUM(D54+D50+D39+D33+D17) -> 20 | E55: =SUM(E54+E50+E39+E33+E17) -> 20 | F55: =SUM(F54+F50+F39+F33+F17) -> 13 | G55: =SUM(G54+G50+G39+G33+G17) -> 4 | H55: =SUM(H54+H50+H39+H33+H17) -> 10 | I55: =SUM(I54+I50+I39+I33+I17) -> 16 | J55: =SUM(J54+J50+J39+J33+J17) -> 21 | ... O55: =SUM(O54+O50+O39+O33+O17) -> 179
A56: VI. | B56: LABORES DE PREVENCION Y OTROS
A57: 41 | B57: Inspecciones de prevencion y seguridad | K57: 1 | L57: 8 | M57: 22 | N57: 12 | O57: =SUM(C57:N57) -> 43
A58: 42 | B58: Labores sociales | E58: 1 | L58: 9 | M58: 2 | N58: 3 | O58: =SUM(C58:N58) -> 15
A59: 43 | B59: Labores de prevención diversas | C59: 2 | M59: 8 | N59: 5 | O59: =SUM(C59:N59) -> 15
A60: 44 | B60: Falsas alarmas por diversos casos | C60: 1 | D60: 1 | H60: 1 | I60: 2 | J60: 3 | K60: 3 | L60: 3 | M60: 2 | N60: 2 | O60: =SUM(C60:N60) -> 18
A61: 45 | B61: Suministro de Agua | M61: 2 | O61: =SUM(C61:N61) -> 2
A62: 46 | B62: Evacuaciones | O62: =SUM(C62:N62) -> 0
B63: SUB-TOTALES | C63: =SUM(C57:C62) -> 3 | D63: =SUM(D57:D62) -> 1 | E63: =SUM(E57:E62) -> 1 | F63: =SUM(F57:F62) -> 0 | G63: =SUM(G57:G62) -> 0 | H63: =SUM(H57:H62) -> 1 | I63: =SUM(I57:I62) -> 2 | J63: =SUM(J57:J62) -> 3 | ... N63: =SUM(N57:N62) -> 22 | O63: =SUM(O57:O61) -> 93
B64: Acumulado de incidentes Atendidos año | C64: =SUM(C55+C63) -> 18 | D64: =SUM(D55+D63) -> 21 | E64: =SUM(E55+E63) -> 21 | F64: =SUM(F55+F63) -> 13 | G64: =SUM(G55+G63) -> 4 | H64: =SUM(H55+H63) -> 11 | I64: =SUM(I55+I63) -> 18 | J64: =SUM(J55+J63) -> 24 | ... O64: =SUM(O55+O63) -> 272
A67: OBSERVACIONES:

Sheet 2016
A1: INFORME DE SINIESTRALIDAD DEPARTAMENTO DEL VALLE DEL CAUCA - AÑO 2016
A2: CUERPO DE BOMBEROS VOLUNTARIOS DE LA UNION
C3: PERIODO AÑO 2016 (Enero 1 al 31 de Diciembre)
A4: ITEM | B4: INCIDENTE | C4: ENERO | D4: FEBRERO | E4: MARZO | F4: ABRL | G4: MAYO | H4: JUNIO | I4: JULIO | J4: AGOSTO | K4: SEPTIEMBRE | L4: OCTUBRE | M4: NOMVIEMBRE | N4: DICIEMBRE | O4: TOTAL
A5: I. | B5: GESTION DEL RISGO DE INCENDIOS
A6: 1 | B6: Incendio estructural | D6: 1 | L6: 1 | N6: 3 | O6: =SUM(C6:N6) -> 5
A7: 2 | B7: Incendio forestal rural | C7: 1 | D7: 3 | E7: 3 | J7: 2 | L7: 1 | O7: =SUM(C7:N7) -> 10
A8: 3 | B8: Incendio forestal urbano | C8: 1 | D8: 4 | E8: 1 | J8: 3 | K8: 1 | L8: 1 | O8: =SUM(C8:N8) -> 11
A9: 4 | B9: Incendio vehicular | O9: =SUM(C9:N9) -> 0
A10: 5 | B10: Incendio de líquidos inflamables o gases | O10: =SUM(C10:N10) -> 0
A11: 6 | B11: Incendio Gas domiciliario | O11: =SUM(C11:N11) -> 0
A12: 7 | B12: Incendio en Cilindro de Gas | O12: =SUM(C12:N12) -> 0
A13: 8 | B13: Incendio eléctrico | D13: 1 | E13: 1 | J13: 1 | M13: 1 | O13: =SUM(C13:N13) -> 4
A14: 9 | B14: Incendio Agricola | C14: 5 | J14: 1 | M14: 1 | O14: =SUM(C14:N14) -> 7
A15: 10 | B15: Incendio Aereo | O15: =SUM(C15:N15) -> 0
A16: 11 | B16: Fuegos aislados o basuras | C16: 4 | D16: 2 | E16: 2 | F16: 1 | J16: 2 | O16: =SUM(C16:N16) -> 11
B17: SUB-TOTALES | C17: =SUM(C6:C16) -> 11 | D17: =SUM(D6:D16) -> 11 | E17: =SUM(E6:E16) -> 7 | F17: =SUM(F6:F16) -> 1 | G17: =SUM(G6:G16) -> 0 | H17: =SUM(H6:H16) -> 0 | I17: =SUM(I6:I16) -> 0 | J17: =SUM(J6:J16) -> 9 | ... O17: =SUM(O6:O16) -> 48
A18: II. | B18: RESCATE EN TODAS SUS MODALIDADES
A19: 12 | B19: Rescate, atención y/o traslado de lesionado en Accidentes de tránsito | C19: 4 | D19: 1 | F19: 4 | G19: 1 | H19: 1 | J19: 2 | K19: 1 | M19: 2 | N19: 1 | O19: =SUM(C19:N19) -> 17
A20: 13 | B20: Salvamento en mina | O20: =SUM(C20:N20) -> 0
A21: 14 | B21: Rescate de animal | E21: 2 | G21: 3 | I21: 2 | N21: 1 | O21: =SUM(C21:N21) -> 8
A22: 15 | B22: Auxilio a electrocutado | O22: =SUM(C22:N22) -> 0
A23: 16 | B23: Rescate en ascensor | O23: =SUM(C23:N23) -> 0
A24: 17 | B24: Rescate con apertura de puerta | C24: 1 | O24: =SUM(C24:N24) -> 1
A25: 18 | B25: Rescate Acuatico | O25: =SUM(C25:N25) -> 0
A26: 19 | B26: Rescate en Estructura Colapsada | O26: =SUM(C26:N26) -> 0
A27: 20 | B27: Rescate en Altura | O27: =SUM(C27:N27) -> 0
A28: 21 | B28: Rescate en espacio confinado | O28: =SUM(C28:N28) -> 0
A29: 22 | B29: Rescate en Accidente Aéreo | O29: =SUM(C29:N29) -> 0
A30: 23 | B30: Rescte en media y alta Montaña | H30: 1 | O30: =SUM(C30:N30) -> 1
A31: 24 | B31: Rescate con exposición de Materiales peligrosos | O31: =SUM(C31:N31) -> 0
A32: 25 | B32: Otros auxilios y/o rescates | L32: 1 | O32: =SUM(C32:N32) -> 1
B33: SUB-TOTALES | C33: =SUM(C19:C32) -> 5 | D33: =SUM(D19:D32) -> 1 | E33: =SUM(E19:E32) -> 2 | F33: =SUM(F19:F32) -> 4 | G33: =SUM(G19:G32) -> 4 | H33: =SUM(H19:H32) -> 2 | I33: =SUM(I19:I32) -> 2 | J33: =SUM(J19:J32) -> 2 | ... O33: =SUM(O19:O32) -> 28
A34: III. | B34: ATENCION DE MATERIALES PELIGROSOS
A35: 26 | B35: Incidentes con materiales peligrosos | O35: =SUM(C35:N35) -> 0
A36: 27 | B36: Fuga de gas GLP | N36: 1 | O36: =SUM(C36:N36) -> 1
A37: 28 | B37: Fuga de gas GNC | C37: 1 | E37: 1 | H37: 1 | I37: 1 | J37: 1 | M37: 1 | N37: 3 | O37: =SUM(C37:N37) -> 9
A38: 29 | B38: Derrames de combustible en vía pública | C38: 1 | H38: 1 | M38: 1 | N38: 1 | O38: =SUM(C38:N38) -> 4
B39: SUB-TOTALES | C39: =SUM(C35:C38) -> 2 | D39: =SUM(D35:D38) -> 0 | E39: =SUM(E35:E38) -> 1 | F39: =SUM(F35:F38) -> 0 | G39: =SUM(G35:G38) -> 0 | H39: =SUM(H35:H38) -> 2 | I39: =SUM(I35:I38) -> 1 | J39: =SUM(J35:J38) -> 1 | ... O39: =SUM(O35:O38) -> 14
A40: IV. | B40: ATENCION DE OTROS INCIDENTES
A41: 30 | B41: Colapsos en estructura | I41: 1 | K41: 1 | O41: =SUM(C41:N41) -> 2
A42: 31 | B42: Derrumbes y deslizamientos | O42: =SUM(C42:N42) -> 0
A43: 32 | B43: Explosiones por pólvora | O43: =SUM(C43:N43) -> 0
A44: 33 | B44: Explosiones de ollas a presión | O44: =SUM(C44:N44) -> 0
A45: 34 | B45: Otras explosiones | O45: =SUM(C45:N45) -> 0
A46: 35 | B46: Inundaciones | F46: 2 | G46: 1 | H46: 1 | I46: 1 | J46: 1 | L46: 2 | M46: 1 | O46: =SUM(C46:N46) -> 9
A47: 36 | B47: Caídas de árboles, postes de energía y otros | H47: 7 | J47: 3 | L47: 3 | M47: 2 | N47: 1 | O47: =SUM(C47:N47) -> 16
A48: 37 | B48: Atención de abejas | C48: 1 | D48: 5 | E48: 7 | F48: 12 | G48: 5 | H48: 10 | I48: 6 | J48: 3 | K48: 6 | L48: 3 | M48: 4 | N48: 5 | O48: =SUM(C48:N48) -> 67
A49: 38 | B49: Recuperación de cadáver | O49: =SUM(C49:N49) -> 0
B50: SUB-TOTALES | C50: =SUM(C41:C49) -> 1 | D50: =SUM(D41:D49) -> 5 | E50: =SUM(E41:E49) -> 7 | F50: =SUM(F41:F49) -> 14 | G50: =SUM(G41:G49) -> 6 | H50: =SUM(H41:H49) -> 18 | I50: =SUM(I41:I49) -> 8 | J50: =SUM(J41:J49) -> 7 | ... O50: =SUM(O41:O49) -> 94
A51: V. | B51: ATENCION PREHOSPITALARIA
A52: 39 | B52: Atención y/o transporte de herido | D52: 1 | L52: 1 | O52: =SUM(C52:N52) -> 2
A53: 40 | B53: Auxilio y/o transporte de enfermo | G53: 1 | O53: =SUM(C53:N53) -> 1
B54: SUB-TOTALES | C54: =SUM(C52:C53) -> 0 | D54: =SUM(D52:D53) -> 1 | E54: =SUM(E52:E53) -> 0 | F54: =SUM(F52:F53) -> 0 | G54: =SUM(G52:G53) -> 1 | H54: =SUM(H52:H53) -> 0 | I54: =SUM(I52:I53) -> 0 | J54: =SUM(J52:J53) -> 0 | ... O54: =SUM(O52:O53) -> 3
B55: TOTAL DE INCIDENTES ATENDIDOS | C55: =SUM(C54+C50+C39+C33+C17) -> 19 | D55: =SUM(D54+D50+D39+D33+D17) -> 18 | E55: =SUM(E54+E50+E39+E33+E17) -> 17 | F55: =SUM(F54+F50+F39+F33+F17) -> 19 | G55: =SUM(G54+G50+G39+G33+G17) -> 11 | H55: =SUM(H54+H50+H39+H33+H17) -> 22 | I55: =SUM(I54+I50+I39+I33+I17) -> 11 | J55: =SUM(J54+J50+J39+J33+J17) -> 19 | ... O55: =SUM(O54+O50+O39+O33+O17) -> 187
A56: VI. | B56: LABORES DE PREVENCION Y OTROS
A57: 41 | B57: Inspecciones de prevencion y seguridad | G57: 1
A58: 42 | B58: Labores sociales | O58: =SUM(C58:N58) -> 0
A59: 43 | B59: Labores de prevención diversas | J59: 1 | K59: 1 | O59: =SUM(C59:N59) -> 2
A60: 44 | B60: Falsas alarmas por diversos casos | C60: 1 | D60: 1 | E60: 3 | K60: 1 | N60: 1 | O60: =SUM(C60:N60) -> 7
A61: 45 | B61: Suministro de Agua
A62: 46 | B62: Evacuaciones
B63: SUB-TOTALES | C63: =SUM(C57:C62) -> 1 | D63: =SUM(D57:D62) -> 1 | E63: =SUM(E57:E62) -> 3 | F63: =SUM(F57:F62) -> 0 | G63: =SUM(G57:G62) -> 1 | H63: =SUM(H57:H62) -> 0 | I63: =SUM(I57:I62) -> 0 | J63: =SUM(J57:J62) -> 1 | ... N63: =SUM(N57:N62) -> 1 | O63: =SUM(O57:O60) -> 9
B64: Acumulado de incidentes Atendidos año | C64: =SUM(C55+C63) -> 20 | D64: =SUM(D55+D63) -> 19 | E64: =SUM(E55+E63) -> 20 | F64: =SUM(F55+F63) -> 19 | G64: =SUM(G55+G63) -> 12 | H64: =SUM(H55+H63) -> 22 | I64: =SUM(I55+I63) -> 11 | J64: =SUM(J55+J63) -> 20 | ... O64: =SUM(O55+O63) -> 196
A67: OBSERVACIONES:
A68: UNA DE LAS INUNDACIONES FUE UN APOYO A BOMBEROS TORO

Sheet 2015
A1: INFORME DE SINIESTRALIDAD DEPARTAMENTO DEL VALLE DEL CAUCA - AÑO 2015
A2: CUERPO DE BOMBEROS VOLUNTARIOS DE LA UNION
C3: PERIODO AÑO 2015 (Enero 1 al 31 de Diciembre) | Q3: enero
A4: ITEM | B4: INCIDENTE | C4: ENERO | D4: FEBRERO | E4: MARZO | F4: ABRL | G4: MAYO | H4: JUNIO | I4: JULIO | J4: AGOSTO | K4: SEPTIEMBRE | L4: OCTUBRE | M4: NOMVIEMBRE | N4: DICIEMBRE | O4: TOTAL
A5: I. | B5: GESTION DEL RISGO DE INCENDIOS | P5: CONTROL DE ABEJAS 2015 SIN APUNTAR
A6: 1 | B6: Incendio estructural | C6: 2 | E6: 1 | G6: 2 | H6: 1 | I6: 1 | J6: 1 | N6: 1 | O6: =SUM(C6:N6) -> 9 | Q6: 47
A7: 2 | B7: Incendio forestal rural | C7: 2 | D7: 3 | E7: 3 | F7: 1 | G7: 2 | H7: 1 | I7: 4 | J7: 1 | K7: 3 | L7: 2 | O7: =SUM(C7:N7) -> 22
A8: 3 | B8: Incendio forestal urbano | C8: 1 | G8: 1 | I8: 1 | J8: 2 | K8: 1 | L8: 2 | N8: 1 | O8: =SUM(C8:N8) -> 9
A9: 4 | B9: Incendio vehicular | E9: 1 | G9: 1 | L9: 1 | M9: 1 | N9: 1 | O9: =SUM(C9:N9) -> 5
A10: 5 | B10: Incendio de líquidos inflamables o gases | O10: =SUM(C10:N10) -> 0
A11: 6 | B11: Incendio Gas domiciliario | O11: =SUM(C11:N11) -> 0
A12: 7 | B12: Incendio en Cilindro de Gas | O12: =SUM(C12:N12) -> 0
A13: 8 | B13: Incendio eléctrico | H13: 1 | K13: 1 | O13: =SUM(C13:N13) -> 2
A14: 9 | B14: Incendio Agricola | D14: 1 | K14: 2 | O14: =SUM(C14:N14) -> 3
A15: 10 | B15: Incendio Aereo | O15: =SUM(C15:N15) -> 0
A16: 11 | B16: Fuegos aislados o basuras | C16: 1 | F16: 1 | G16: 1 | K16: 1 | N16: 1 | O16: =SUM(C16:N16) -> 5
B17: SUB-TOTALES | C17: =SUM(C6:C16) -> 6 | D17: =SUM(D6:D16) -> 4 | E17: =SUM(E6:E16) -> 5 | F17: =SUM(F6:F16) -> 2 | G17: =SUM(G6:G16) -> 7 | H17: =SUM(H6:H16) -> 3 | I17: =SUM(I6:I16) -> 6 | J17: =SUM(J6:J16) -> 4 | ... O17: =SUM(O6:O16) -> 55
A18: II. | B18: RESCATE EN TODAS SUS MODALIDADES
A19: 12 | B19: Rescate, atención y/o traslado de lesionado en Accidentes de tránsito | C19: 1 | D19: 6 | E19: 2 | F19: 11 | G19: 10 | H19: 2 | I19: 5 | J19: 4 | K19: 1 | L19: 1 | N19: 7 | O19: =SUM(C19:N19) -> 50
A20: 13 | B20: Salvamento en mina | O20: =SUM(C20:N20) -> 0
A21: 14 | B21: Rescate de animal | C21: 1 | D21: 1 | I21: 1 | K21: 1 | M21: 1 | O21: =SUM(C21:N21) -> 5
A22: 15 | B22: Auxilio a electrocutado | O22: =SUM(C22:N22) -> 0
A23: 16 | B23: Rescate en ascensor | O23: =SUM(C23:N23) -> 0
A24: 17 | B24: Rescate con apertura de puerta | O24: =SUM(C24:N24) -> 0
A25: 18 | B25: Rescate Acuatico | O25: =SUM(C25:N25) -> 0
A26: 19 | B26: Rescate en Estructura Colapsada | O26: =SUM(C26:N26) -> 0
A27: 20 | B27: Rescate en Altura | I27: 1 | O27: =SUM(C27:N27) -> 1
A28: 21 | B28: Rescate en espacio confinado | O28: =SUM(C28:N28) -> 0
A29: 22 | B29: Rescate en Accidente Aéreo | O29: =SUM(C29:N29) -> 0
A30: 23 | B30: Rescte en media y alta Montaña | O30: =SUM(C30:N30) -> 0
A31: 24 | B31: Rescate con exposición de Materiales peligrosos | O31: =SUM(C31:N31) -> 0
A32: 25 | B32: Otros auxilios y/o rescates | E32: 1 | M32: 2 | O32: =SUM(C32:N32) -> 3
B33: SUB-TOTALES | C33: =SUM(C19:C32) -> 2 | D33: =SUM(D19:D32) -> 7 | E33: =SUM(E19:E32) -> 3 | F33: =SUM(F19:F32) -> 11 | G33: =SUM(G19:G32) -> 10 | H33: =SUM(H19:H32) -> 2 | I33: =SUM(I19:I32) -> 7 | J33: =SUM(J19:J32) -> 4 | ... O33: =SUM(O19:O32) -> 59
A34: III. | B34: ATENCION DE MATERIALES PELIGROSOS
A35: 26 | B35: Incidentes con materiales peligrosos | F35: 1 | I35: 1 | O35: =SUM(C35:N35) -> 2
A36: 27 | B36: Fuga de gas GLP | D36: 1 | O36: =SUM(C36:N36) -> 1
A37: 28 | B37: Fuga de gas GNC | C37: 1 | G37: 1 | H37: 2 | I37: 2 | J37: 3 | K37: 1 | L37: 2 | N37: 2 | O37: =SUM(C37:N37) -> 14
A38: 29 | B38: Derrames de combustible en vía pública | L38: 1 | O38: =SUM(C38:N38) -> 1
B39: SUB-TOTALES | C39: =SUM(C35:C38) -> 1 | D39: =SUM(D35:D38) -> 1 | E39: =SUM(E35:E38) -> 0 | F39: =SUM(F35:F38) -> 1 | G39: =SUM(G35:G38) -> 1 | H39: =SUM(H35:H38) -> 2 | I39: =SUM(I35:I38) -> 3 | J39: =SUM(J35:J38) -> 3 | ... O39: =SUM(O35:O38) -> 18
A40: IV. | B40: ATENCION DE OTROS INCIDENTES
A41: 30 | B41: Colapsos en estructura | L41: 1 | O41: =SUM(C41:N41) -> 1
A42: 31 | B42: Derrumbes y deslizamientos | O42: =SUM(C42:N42) -> 0
A43: 32 | B43: Explosiones por pólvora | O43: =SUM(C43:N43) -> 0
A44: 33 | B44: Explosiones de ollas a presión | O44: =SUM(C44:N44) -> 0
A45: 34 | B45: Otras explosiones | O45: =SUM(C45:N45) -> 0
A46: 35 | B46: Inundaciones | E46: 2 | I46: 2 | K46: 1 | L46: 9 | O46: =SUM(C46:N46) -> 14
A47: 36 | B47: Caídas de árboles, postes de energía y otros | D47: 2 | I47: 2 | K47: 4 | L47: 2 | M47: 1 | O47: =SUM(C47:N47) -> 11
A48: 37 | B48: Atención de abejas | C48: 3 | D48: 1 | E48: 6 | F48: 12 | G48: 5 | H48: 2 | I48: 3 | J48: 6 | K48: 6 | L48: 9 | M48: 4 | N48: 2 | O48: =SUM(C48:N48) -> 59
A49: 38 | B49: Recuperación de cadáver | O49: =SUM(C49:N49) -> 0
B50: SUB-TOTALES | C50: =SUM(C41:C49) -> 3 | D50: =SUM(D41:D49) -> 3 | E50: =SUM(E41:E49) -> 8 | F50: =SUM(F41:F49) -> 12 | G50: =SUM(G41:G49) -> 5 | H50: =SUM(H41:H49) -> 2 | I50: =SUM(I41:I49) -> 7 | J50: =SUM(J41:J49) -> 6 | ... O50: =SUM(O41:O49) -> 85
A51: V. | B51: ATENCION PREHOSPITALARIA
A52: 39 | B52: Atención y/o transporte de herido | G52: 1 | J52: 3 | L52: 1 | O52: =SUM(C52:N52) -> 5
A53: 40 | B53: Auxilio y/o transporte de enfermo | H53: 1 | I53: 1 | O53: =SUM(C53:N53) -> 2
B54: SUB-TOTALES | C54: =SUM(C52:C53) -> 0 | D54: =SUM(D52:D53) -> 0 | E54: =SUM(E52:E53) -> 0 | F54: =SUM(F52:F53) -> 0 | G54: =SUM(G52:G53) -> 1 | H54: =SUM(H52:H53) -> 1 | I54: =SUM(I52:I53) -> 1 | J54: =SUM(J52:J53) -> 3 | ... O54: =SUM(O52:O53) -> 7
B55: TOTAL DE INCIDENTES ATENDIDOS | C55: =SUM(C54+C50+C39+C33+C17) -> 12 | D55: =SUM(D54+D50+D39+D33+D17) -> 15 | E55: =SUM(E54+E50+E39+E33+E17) -> 16 | F55: =SUM(F54+F50+F39+F33+F17) -> 26 | G55: =SUM(G54+G50+G39+G33+G17) -> 24 | H55: =SUM(H54+H50+H39+H33+H17) -> 10 | I55: =SUM(I54+I50+I39+I33+I17) -> 24 | J55: =SUM(J54+J50+J39+J33+J17) -> 20 | ... O55: =SUM(O54+O50+O39+O33+O17) -> 224
A56: VI. | B56: LABORES DE PREVENCION Y OTROS
A57: 41 | B57: Inspecciones de prevencion y seguridad
A58: 42 | B58: Labores sociales | O58: =SUM(C58:N58) -> 0
A59: 43 | B59: Labores de prevención diversas | O59: =SUM(C59:N59) -> 0
A60: 44 | B60: Falsas alarmas por diversos casos | E60: 1 | M60: 1 | O60: =SUM(C60:N60) -> 2
A61: 45 | B61: Suministro de Agua
A62: 46 | B62: Evacuaciones
B63: SUB-TOTALES | C63: =SUM(C57:C62) -> 0 | D63: =SUM(D57:D62) -> 0 | E63: =SUM(E57:E62) -> 1 | F63: =SUM(F57:F62) -> 0 | G63: =SUM(G57:G62) -> 0 | H63: =SUM(H57:H62) -> 0 | I63: =SUM(I57:I62) -> 0 | J63: =SUM(J57:J62) -> 0 | ... N63: =SUM(N57:N62) -> 0 | O63: =SUM(O57:O60) -> 2
B64: Acumulado de incidentes Atendidos año | C64: =SUM(C55+C63) -> 12 | D64: =SUM(D55+D63) -> 15 | E64: =SUM(E55+E63) -> 17 | F64: =SUM(F55+F63) -> 26 | G64: =SUM(G55+G63) -> 24 | H64: =SUM(H55+H63) -> 10 | I64: =SUM(I55+I63) -> 24 | J64: =SUM(J55+J63) -> 20 | ... N64: =SUM(N55+N63) -> 15 | O64: =SUM(O55+O63+Q6) -> 273
A67: OBSERVACIONES:
A68: LO INCENDIOS FORESTALES ADICIONALES QUE APARECEN SON APOYO QUE SE APRESTADO A BOMBEROS TORO
A69: NOTA SE ATENDIERON EN MAYO DOS INCENDIOS FORESTALES EN LA VICTORIA VALLE POR APOYO YA QUE LAS MAQUINAS NO SE ENCONTRABAN EN SERVICIO
A70: NOTA EL FORESTAL DE JUNIO FUE APOYO A BROS ROLDANILLO
A71: NOTA: EN SEPTIEMBRE SE APOYO UN INCENDIO FORESTAL A BROS ROLDANILLO EN LA VIA ROLDANILLO EL DOVIO
A72: LO INCENDIOS FORESTALES ADICIONALES DE OCTUBRE APARECEN SON APOYO QUE SE APRESTADO A BOMBEROS TORO

Sheet 2014
A2: COORDINACION EJECUTIVA DE LOS CUERPOS DE BOMBEROS DEL VALLE DEL CAUCA
A4: INFORME DE SINIESTRALIDAD DEPARTAMENTO DEL VALLE DEL CAUCA - AÑO 2014
A6: CUERPO DE BOMBEROS VOLUNTARIOS DE LA UNION
C8: PERIODO AÑO 2014 (Enero 1 al 31 de Diciembre)
A9: ITEM | B9: INCIDENTE | C9: ENERO | D9: FEBRERO | E9: MARZO | F9: ABRL | G9: MAYO | H9: JUNIO | I9: JULIO | J9: AGOSTO | K9: SEPTIEMBRE | L9: OCTUBRE | M9: NOMVIEMBRE | N9: DICIEMBRE | O9: TOTAL
A10: I. | B10: GESTION DEL RISGO DE INCENDIOS
A11: 1 | B11: Incendio estructural | F11: 1 | G11: 2 | I11: 2 | J11: 3 | K11: 2 | L11: 1 | O11: =SUM(C11:N11) -> 11
A12: 2 | B12: Incendio forestal rural | C12: 2 | D12: 1 | F12: 3 | H12: 3 | I12: 2 | J12: 6 | K12: 1 | L12: 1 | N12: 1 | O12: =SUM(C12:N12) -> 20
A13: 3 | B13: Incendio forestal urbano | C13: 2 | F13: 1 | J13: 3 | K13: 2 | L13: 1 | O13: =SUM(C13:N13) -> 9
A14: 4 | B14: Incendio vehicular | O14: =SUM(C14:N14) -> 0
A15: 5 | B15: Incendio de líquidos inflamables o gases | O15: =SUM(C15:N15) -> 0
A16: 6 | B16: Incendio Gas domiciliario | O16: =SUM(C16:N16) -> 0
A17: 7 | B17: Incendio en Cilindro de Gas | O17: =SUM(C17:N17) -> 0
A18: 8 | B18: Incendio eléctrico | I18: 1 | O18: =SUM(C18:N18) -> 1
A19: 9 | B19: Incendio Agricola | F19: 1 | O19: =SUM(C19:N19) -> 1
A20: 10 | B20: Incendio Aereo | O20: =SUM(C20:N20) -> 0
A21: 11 | B21: Fuegos aislados o basuras | D21: 1 | E21: 1 | K21: 1 | L21: 2 | O21: =SUM(C21:N21) -> 5
B22: SUB-TOTALES | C22: =SUM(C11:C21) -> 4 | D22: =SUM(D11:D21) -> 2 | E22: =SUM(E11:E21) -> 1 | F22: =SUM(F11:F21) -> 6 | G22: =SUM(G11:G21) -> 2 | H22: =SUM(H11:H21) -> 3 | I22: =SUM(I11:I21) -> 5 | J22: =SUM(J11:J21) -> 12 | ... O22: =SUM(O11:O21) -> 47
A23: II. | B23: RESCATE EN TODAS SUS MODALIDADES
A24: 12 | B24: Rescate, atención y/o traslado de lesionado en Accidentes de tránsito | C24: 11 | D24: 13 | E24: 10 | F24: 14 | G24: 13 | H24: 18 | I24: 9 | J24: 18 | K24: 7 | L24: 3 | M24: 2 | N24: 2 | O24: =SUM(C24:N24) -> 120
A25: 13 | B25: Salvamento en mina | O25: =SUM(C25:N25) -> 0
A26: 14 | B26: Rescate de animal | E26: 1 | H26: 1 | I26: 1 | J26: 1 | L26: 1 | M26: 2 | O26: =SUM(C26:N26) -> 7
A27: 15 | B27: Auxilio a electrocutado | D27: 1 | O27: =SUM(C27:N27) -> 1
A28: 16 | B28: Rescate en ascensor | O28: =SUM(C28:N28) -> 0
A29: 17 | B29: Rescate con apertura de puerta | O29: =SUM(C29:N29) -> 0
A30: 18 | B30: Rescate Acuatico | I30: 1 | O30: =SUM(C30:N30) -> 1
A31: 19 | B31: Rescate en Estructura Colapsada | O31: =SUM(C31:N31) -> 0
A32: 20 | B32: Rescate en Altura | O32: =SUM(C32:N32) -> 0
A33: 21 | B33: Rescate en espacio confinado | L33: 1 | O33: =SUM(C33:N33) -> 1
A34: 22 | B34: Rescate en Accidente Aéreo | O34: =SUM(C34:N34) -> 0
A35: 23 | B35: Rescte en media y alta Montaña | O35: =SUM(C35:N35) -> 0
A36: 24 | B36: Rescate con exposición de Materiales peligrosos | O36: =SUM(C36:N36) -> 0
A37: 25 | B37: Otros auxilios y/o rescates | D37: 1 | E37: 1 | J37: 1 | K37: 1 | O37: =SUM(C37:N37) -> 4
B38: SUB-TOTALES | C38: =SUM(C24:C37) -> 11 | D38: =SUM(D24:D37) -> 15 | E38: =SUM(E24:E37) -> 12 | F38: =SUM(F24:F37) -> 14 | G38: =SUM(G24:G37) -> 13 | H38: =SUM(H24:H37) -> 19 | I38: =SUM(I24:I37) -> 11 | J38: =SUM(J24:J37) -> 20 | ... O38: =SUM(O24:O37) -> 134
A39: III. | B39: ATENCION DE MATERIALES PELIGROSOS
A40: 26 | B40: Incidentes con materiales peligrosos | F40: 1 | H40: 1 | K40: 1 | N40: 1 | O40: =SUM(C40:N40) -> 4
A41: 27 | B41: Fuga de gas GLP | O41: =SUM(C41:N41) -> 0
A42: 28 | B42: Fuga de gas GNC | C42: 1 | D42: 1 | E42: 1 | F42: 3 | G42: 3 | H42: 2 | I42: 2 | J42: 3 | K42: 2 | L42: 1 | M42: 1 | N42: 2 | O42: =SUM(C42:N42) -> 22
A43: 29 | B43: Derrames de combustible en vía pública | N43: 1 | O43: =SUM(C43:N43) -> 1
B44: SUB-TOTALES | C44: =SUM(C40:C43) -> 1 | D44: =SUM(D40:D43) -> 1 | E44: =SUM(E40:E43) -> 1 | F44: =SUM(F40:F43) -> 4 | G44: =SUM(G40:G43) -> 3 | H44: =SUM(H40:H43) -> 3 | I44: =SUM(I40:I43) -> 2 | J44: =SUM(J40:J43) -> 3 | ... N44: =SUM(N40:N43) -> 4 | O44: =SUM(O37:O43) -> 165
A45: IV. | B45: ATENCION DE OTROS INCIDENTES
A46: 30 | B46: Colapsos en estructura | L46: 1 | O46: =SUM(C46:N46) -> 1
A47: 31 | B47: Derrumbes y deslizamientos | O47: =SUM(C47:N47) -> 0
A48: 32 | B48: Explosiones por pólvora | O48: =SUM(C48:N48) -> 0
A49: 33 | B49: Explosiones de ollas a presión | O49: =SUM(C49:N49) -> 0
A50: 34 | B50: Otras explosiones | O50: =SUM(C50:N50) -> 0
A51: 35 | B51: Inundaciones | C51: 1 | F51: 1 | G51: 21 | H51: 1 | M51: 1 | O51: =SUM(C51:N51) -> 25
A52: 36 | B52: Caídas de árboles, postes de energía y otros | C52: 1 | F52: 1 | L52: 1 | N52: 2 | O52: =SUM(C52:N52) -> 5
A53: 37 | B53: Atención de abejas | C53: 1 | E53: 4 | F53: 8 | G53: 3 | H53: 3 | I53: 3 | J53: 4 | K53: 3 | O53: =SUM(C53:N53) -> 29
A54: 38 | B54: Recuperación de cadáver | O54: =SUM(C54:N54) -> 0
B55: SUB-TOTALES | C55: =SUM(C46:C54) -> 3 | D55: =SUM(D46:D54) -> 0 | E55: =SUM(E46:E54) -> 4 | F55: =SUM(F46:F54) -> 10 | G55: =SUM(G46:G54) -> 24 | H55: =SUM(H46:H54) -> 4 | I55: =SUM(I46:I54) -> 3 | J55: =SUM(J46:J54) -> 4 | ... O55: =SUM(O46:O54) -> 60
A56: V. | B56: ATENCION PREHOSPITALARIA
A57: 39 | B57: Atención y/o transporte de herido | C57: 13 | D57: 6 | E57: 11 | F57: 7 | G57: 5 | H57: 5 | I57: 5 | J57: 5 | K57: 5 | L57: 1 | N57: 1 | O57: =SUM(C57:N57) -> 64
A58: 40 | B58: Auxilio y/o transporte de enfermo | E58: 23 | F58: 15 | G58: 11 | H58: 6 | I58: 10 | J58: 7 | K58: 1 | N58: 2 | O58: =SUM(C58:N58) -> 75
B59: SUB-TOTALES | C59: =SUM(C57:C58) -> 13 | D59: =SUM(D57:D58) -> 6 | E59: =SUM(E57:E58) -> 34 | F59: =SUM(F57:F58) -> 22 | G59: =SUM(G57:G58) -> 16 | H59: =SUM(H57:H58) -> 11 | I59: =SUM(I57:I58) -> 15 | J59: =SUM(J57:J58) -> 12 | ... O59: =SUM(O57:O58) -> 139
B60: TOTAL DE INCIDENTES ATENDIDOS | C60: =SUM(C59+C55+C44+C38+C22) -> 32 | D60: =SUM(D59+D55+D44+D38+D22) -> 24 | E60: =SUM(E59+E55+E44+E38+E22) -> 52 | F60: =SUM(F59+F55+F44+F38+F22) -> 56 | G60: =SUM(G59+G55+G44+G38+G22) -> 58 | H60: =SUM(H59+H55+H44+H38+H22) -> 40 | I60: =SUM(I59+I55+I44+I38+I22) -> 36 | J60: =SUM(J59+J55+J44+J38+J22) -> 51 | ... O60: =SUM(O59+O55+O44+O38+O22) -> 545
A61: VI. | B61: LABORES DE PREVENCION Y OTROS
A62: 41 | B62: Inspecciones de prevencion y seguridad | C62: 6 | D62: 7 | E62: 7 | F62: 4 | G62: 5
A63: 42 | B63: Labores sociales | J63: 1 | O63: =SUM(C63:N63) -> 1
A64: 43 | B64: Labores de prevención diversas | C64: 3 | G64: 2 | O64: =SUM(C64:N64) -> 5
A65: 44 | B65: Falsas alarmas por diversos casos | C65: 1 | F65: 4 | G65: 4 | H65: 2 | I65: 3 | J65: 1 | O65: =SUM(C65:N65) -> 15
A66: 45 | B66: Suministro de Agua
A67: 46 | B67: Evacuaciones
B68: SUB-TOTALES | C68: =SUM(C62:C67) -> 10 | D68: =SUM(D62:D67) -> 7 | E68: =SUM(E62:E67) -> 7 | F68: =SUM(F62:F67) -> 8 | G68: =SUM(G62:G67) -> 11 | H68: =SUM(H62:H67) -> 2 | I68: =SUM(I62:I67) -> 3 | J68: =SUM(J62:J67) -> 2 | ... N68: =SUM(N62:N67) -> 0 | O68: =SUM(O62:O65) -> 21
B69: Acumulado de incidentes Atendidos año | C69: =SUM(C60+C68) -> 42 | D69: =SUM(D60+D68) -> 31 | E69: =SUM(E60+E68) -> 59 | F69: =SUM(F60+F68) -> 64 | G69: =SUM(G60+G68) -> 69 | H69: =SUM(H60+H68) -> 42 | I69: =SUM(I60+I68) -> 39 | J69: =SUM(J60+J68) -> 53 | ... O69: =SUM(O60+O68) -> 566
A71: OBSERVACIONES:
A72: APARTIR DE SEPTIEMBRE LA DISMINUCION EN ACCIDENTES Y AUXILIOS A PERSONAS OBEDECE A QUE SE DEJO DE PRESTAR EL SERVICIO DE TRANSPORTE EN AMBULANCIA POR PARTE DE LA INSTITUCION YA QUE NO SE CUENTA CON UNA AMBULANCIA QUE CUMPLA CON TODOS LOS REQUISITOS DE LEY POR LO CUAL SE SIGUIO PRESTANDO APOYO SOLO PARA ATENCION DEJANDO EL TRASLADO EN MANOS DE LA ADMON MUNICIPAL Y SU CONTRATACION
Q83: enero

Sheet 2013
A1: EMERGENCIAS Y SERVICIOS PRESTADOS MES DE ENERO 2013 BRO JUAN DAVID HERRERA
A3: Nº | B3: DIA | C3: HORA DE SALIDA | D3: HORA DE REGRESO | E3: MQ # | F3: OPERADOR MQ # | G3: CLASE DE EMERGENCIA | H3: DIRECCION | I3: PROPIETARIO | J3: HERIDOS | K3: MUERTOS | L3: AREAS QUEMADAS | M3: TIPO DE QUEMA | N3: OBSERVACION
A5: 1 | B5: 1 | C5: 01.05 | D5: 02.10 | E5: 5 | F5: giraldo | G5: accidente de transito | H5: via toro | I5: via publica | J5: si | N5: asistieron 3 unidades
A6: 2 | B6: 1 | C6: 06.41 | D6: 07.11 | E6: 5 | F6: giraldo | G6: persona que cae de su altura | H6: calle 15 · 17-45 | I6: lucila garcia | J6: si | N6: asistieron 3 unidades | Q6: CAÍDA / CORTES DE ARBOL
A7: 3 | B7: 4 | C7: 10.44 | D7: 11.37 | E7: 5 | F7: zapata | G7: persona que cae de su altura | H7: via roldanillo | I7: finca la pista | J7: SI | N7: asistieron 3 unidades | Q7: CONTROL DE ABEJAS
A8: 4 | B8: 4 | C8: 13.21 | D8: 14.11 | E8: 5 | F8: carvajal | G8: accidente de transito | H8: via roldanillo por el portachuelo | I8: via publica | J8: si | N8: asistieron 3 unidades | Q8: CONTROL DE AVISPAS
A9: 5 | B9: 6 | C9: 09.07 | D9: 09.38 | E9: 5 | F9: giraldo | G9: arma de fuego | H9: parque de sanpedro | I9: via publica | K9: si | N9: asistieron 5 unidades | Q9: CAÍDA DE CUERDAS
A10: 6 | B10: 7 | C10: 16.41 | D10: 17.30 | E10: 2 | F10: giraldo | G10: fuga de gas | H10: cra 15 con cll 25 | I10: via publica | J10: no | N10: asistieron 5 unidades | Q10: CORTO CIRCUITO
A11: 7 | B11: 7 | C11: 22.03 | D11: 22.26 | E11: 5 | F11: caceres | G11: accidente de transito | H11: parque principal | I11: via publica | J11: si | N11: asistieron 4 unidades | Q11: COLAPSO DE ESTRUCTURAS
A12: 8 | B12: 10 | C12: 21.30 | D12: 22.00 | E12: 2 | F12: carvajal | G12: incendio forestal | H12: via versalles por la balastrera | I12: via publica | J12: no | N12: asistieron 9 unidades | Q12: CAPACITACIONES
A13: 9 | B13: 13 | C13: 04.55 | D13: 05.57 | E13: 5 | F13: giraldo | G13: accidente de transito | H13: cra 15 con cll 18 | I13: via publica | J13: si | N13: asistieron 5 unidades | Q13: EXTRICACIÓN VEHICULAR
A14: 10 | B14: 14 | C14: 19.43 | D14: 20.18 | E14: 1 | F14: giraldo | G14: incendio forestal | H14: calle 9 con 12 | I14: via publica | M14: basura | N14: asistieron 5 unidades | Q14: FUGA DE GAS NATURAL
A15: 11 | B15: 17 | C15: 02.59 | D15: 03.33 | E15: 5 | F15: villa | G15: auxilio a persona | H15: parque principal | I15: via publica | J15: si | N15: asistieron 3 unidades | Q15: FUGA DE GAS GLP
A16: 12 | B16: 17 | C16: 13.38 | D16: 14.29 | E16: 2 | F16: giraldo | G16: incendio forestal | H16: en grajales | I16: finca la rivera | L16: 150mts | M16: pastizal | N16: asistieron 5 unidades | Q16: INCENDIO FORESTAL
A17: 13 | B17: 17 | C17: 21.12 | D17: 22.35 | E17: 5 | F17: carvajal | G17: accidente de transito | H17: calle 11 con 14 | I17: via publica | J17: si | N17: asistieron 5 unidades | Q17: INCENDIO ESTRUCTURAL
A18: 14 | B18: 19 | C18: 17.33 | D18: 17.58 | E18: 5 | F18: miguel | G18: accidente de transito | H18: cra 15 | I18: estacion de servicio la andina | J18: si | N18: asistieron 5 unidades | Q18: INCENDIO VEHICULAR
